Workbook

Sheet COBRO 2025
B1: M3 GAS POR M3 DE AGUA | F1: 3.4 | AP1: M3 GAS POR M3 DE AGUA | AT1: 3.4
B2: 2017
B3: TORRE A
C4: ENERO | I4: FEBRERO | O4: MARZO | U4: ABRIL | Z4: MAYO | AE4: JUNIO | AJ4: JULIO | AP4: AGOSTO | AV4: SEPTIEMBRE | BB4: OCTUBRE | BG4: NOVIEMBRE | BL4: DICIEMBRE
B6: APTO | C6: AGUA | E6: GAS | F6: $ AGUA | G6: $GAS | H6: $ TOTAL | I6: AGUA | K6: GAS | L6: $ AGUA | M6: $GAS | N6: $ TOTAL | O6: AGUA | Q6: GAS | R6: $ AGUA | S6: $GAS | T6: $ TOTAL | U6: AGUA | V6: GAS | W6: $ AGUA | X6: $GAS | Y6: $ TOTAL | Z6: AGUA | AA6: GAS | AB6: $ AGUA | AC6: $GAS | AD6: $ TOTAL | AE6: AGUA | AF6: GAS | AG6: $ AGUA | AH6: $GAS | AI6: $ TOTAL | AJ6: AGUA | AK6: GAS | AM6: $ AGUA | AN6: $GAS | AO6: $ TOTAL | AP6: AGUA | AQ6: GAS | AS6: $ AGUA | AT6: $GAS | AU6: $ TOTAL | AV6: AGUA | AW6: GAS | AY6: $ AGUA | AZ6: $GAS | BA6: $ TOTAL | BB6: AGUA | BC6: GAS | BD6: $ AGUA | BE6: $GAS | BF6: $ TOTAL | BG6: AGUA | BH6: GAS | BI6: $ AGUA | BJ6: $GAS | BK6: $ TOTAL | BL6: AGUA | BM6: GAS | BN6: $ AGUA | BO6: $GAS | BP6: $ TOTAL
A7: 2017 TORRE A | B7: 201 | C7: 18 | E7: =+C7*$F$1 -> 61.2 | F7: =+C7*$E$48 -> 128815.26 | G7: =+E7*$E$47 -> #REF! | H7: =+G7+F7 -> #REF! | I7: 18 | K7: =+I7*$F$1 -> 61.2 | L7: =+I7*$K$48 -> 128815.26 | M7: =+K7*$K$47 -> 124200.4 | N7: =+M7+L7 -> 253015.67 | O7: 12 | Q7: =+O7*$F$1 -> 40.8 | R7: =+O7*$Q$48 -> 86022.84 | S7: =+Q7*$Q$47 -> 90173.852 | T7: =+S7+R7 -> 176196.69 | U7: 13 | V7: =+U7*$F$1 -> 44.2 | W7: =+U7*$V$48 -> 93191.41 | X7: =+V7*$V$47 -> 103653.82 | Y7: =+X7+W7 -> 196845.23 | Z7: 10 | AA7: =+Z7*$F$1 -> 34 | AB7: =+Z7*$AB$48 -> 75107.239 | AC7: =+AA7*$AB$47 -> 69931.076 | AD7: =+AC7+AB7 -> 145038.32 | AE7: 14 | AF7: =+AE7*$F$1 -> 47.6 | AG7: =+AE7*$AF$48 -> 105150.13 | AH7: =+AF7*$AF$47 -> 100312.99 | AI7: =+AH7+AG7 -> 205463.12 | AJ7: 12 | AK7: =+AJ7*$F$1 -> 40.8 | AM7: =+AJ7*$AK$48 -> 89128.607 | AN7: =+AK7*$AK$47 -> 87840.312 | AO7: =+AN7+AM7 -> 176968.92 | AP7: 14 | AQ7: =+AP7*$F$1 -> 47.6 | AS7: =+AP7*$AQ$48 -> 103983.37 | AT7: =+AQ7*$AQ$47 -> 98111.487 | AU7: =+AT7+AS7 -> 202094.86 | AV7: 12 | AW7: =+AV7*$F$1 -> 40.8 | AY7: =+AV7*$AW$48 -> 89130.428 | AZ7: =+AW7*$AW$47 -> 95922.437 | BA7: =+AZ7+AY7 -> 185052.87 | BB7: 25 | BC7: =+BB7*$F$1 -> 85 | BD7: =+BB7*$BC$48 -> 185688.39 | BE7: =+BC7*$BC$47 -> 190552.82 | BF7: =+BE7+BD7 -> 376241.21 | BG7: 23 | BH7: =+BG7*$F$1 -> 78.2 | BI7: =+BG7*$BH$48 -> 170842.56 | BJ7: =+BH7*$BH$47 -> 165357.38 | BK7: =+BJ7+BI7 -> 336199.94 | BL7: 26 | BM7: =+BL7*$F$1 -> 88.4 | BN7: =+BL7*$BM$48 -> 193126.38 | BO7: =+BM7*$BM$47 -> 190707.24 | BP7: =+BO7+BN7 -> 383833.62
A8: 2017 TORRE A | B8: 202 | C8: 1 | E8: =+C8*$F$1 -> 3.4 | F8: =+C8*$E$48 -> 7156.4036 | G8: =+E8*$E$47 -> #REF! | H8: =+G8+F8 -> #REF! | I8: 1 | K8: =+I8*$F$1 -> 3.4 | L8: =+I8*$K$48 -> 7156.4036 | M8: =+K8*$K$47 -> 6900.0223 | N8: =+M8+L8 -> 14056.426 | O8: 1 | Q8: =+O8*$F$1 -> 3.4 | R8: =+O8*$Q$48 -> 7168.57 | S8: =+Q8*$Q$47 -> 7514.4877 | T8: =+S8+R8 -> 14683.058 | U8: 1 | V8: =+U8*$F$1 -> 3.4 | W8: =+U8*$V$48 -> 7168.57 | X8: =+V8*$V$47 -> 7973.3711 | Y8: =+X8+W8 -> 15141.941 | Z8: 1 | AA8: =+Z8*$F$1 -> 3.4 | AB8: =+Z8*$AB$48 -> 7510.7239 | AC8: =+AA8*$AB$47 -> 6993.1076 | AD8: =+AC8+AB8 -> 14503.832 | AE8: 0 | AF8: =+AE8*$F$1 -> 0 | AG8: =+AE8*$AF$48 -> 0 | AH8: =+AF8*$AF$47 -> 0 | AI8: =+AH8+AG8 -> 0 | AJ8: 1 | AK8: =+AJ8*$F$1 -> 3.4 | AM8: =+AJ8*$AK$48 -> 7427.3839 | AN8: =+AK8*$AK$47 -> 7320.026 | AO8: =+AN8+AM8 -> 14747.41 | AP8: 1 | AQ8: =+AP8*$F$1 -> 3.4 | AS8: =+AP8*$AQ$48 -> 7427.3839 | AT8: =+AQ8*$AQ$47 -> 7007.9634 | AU8: =+AT8+AS8 -> 14435.347 | AV8: 1 | AW8: =+AV8*$F$1 -> 3.4 | AY8: =+AV8*$AW$48 -> 7427.5357 | AZ8: =+AW8*$AW$47 -> 7993.5364 | BA8: =+AZ8+AY8 -> 15421.072 | BB8: 1 | BC8: =+BB8*$F$1 -> 3.4 | BD8: =+BB8*$BC$48 -> 7427.5357 | BE8: =+BC8*$BC$47 -> 7622.1128 | BF8: =+BE8+BD8 -> 15049.648 | BG8: 1 | BH8: =+BG8*$F$1 -> 3.4 | BI8: =+BG8*$BH$48 -> 7427.9375 | BJ8: =+BH8*$BH$47 -> 7189.4514 | BK8: =+BJ8+BI8 -> 14617.389 | BL8: 1 | BM8: =+BL8*$F$1 -> 3.4 | BN8: =+BL8*$BM$48 -> 7427.9375 | BO8: =+BM8*$BM$47 -> 7334.894 | BP8: =+BO8+BN8 -> 14762.832
A9: 2017 TORRE A | B9: 203 | C9: 0 | E9: =+C9*$F$1 -> 0 | F9: =+C9*$E$48 -> 0 | G9: =+E9*$E$47 -> #REF! | H9: =+G9+F9 -> #REF! | I9: 0 | K9: =+I9*$F$1 -> 0 | L9: =+I9*$K$48 -> 0 | M9: =+K9*$K$47 -> 0 | N9: =+M9+L9 -> 0 | O9: 0 | Q9: =+O9*$F$1 -> 0 | R9: =+O9*$Q$48 -> 0 | S9: =+Q9*$Q$47 -> 0 | T9: =+S9+R9 -> 0 | U9: 0 | V9: =+U9*$F$1 -> 0 | W9: =+U9*$V$48 -> 0 | X9: =+V9*$V$47 -> 0 | Y9: =+X9+W9 -> 0 | Z9: 0 | AA9: =+Z9*$F$1 -> 0 | AB9: =+Z9*$AB$48 -> 0 | AC9: =+AA9*$AB$47 -> 0 | AD9: =+AC9+AB9 -> 0 | AE9: 0 | AF9: =+AE9*$F$1 -> 0 | AG9: =+AE9*$AF$48 -> 0 | AH9: =+AF9*$AF$47 -> 0 | AI9: =+AH9+AG9 -> 0 | AJ9: 0 | AK9: =+AJ9*$F$1 -> 0 | AM9: =+AJ9*$AK$48 -> 0 | AN9: =+AK9*$AK$47 -> 0 | AO9: =+AN9+AM9 -> 0 | AP9: 7 | AQ9: =+AP9*$F$1 -> 23.8 | AS9: =+AP9*$AQ$48 -> 51991.687 | AT9: =+AQ9*$AQ$47 -> 49055.744 | AU9: =+AT9+AS9 -> 101047.43 | AV9: 6 | AW9: =+AV9*$F$1 -> 20.4 | AY9: =+AV9*$AW$48 -> 44565.214 | AZ9: =+AW9*$AW$47 -> 47961.219 | BA9: =+AZ9+AY9 -> 92526.433 | BB9: 8 | BC9: =+BB9*$F$1 -> 27.2 | BD9: =+BB9*$BC$48 -> 59420.285 | BE9: =+BC9*$BC$47 -> 60976.902 | BF9: =+BE9+BD9 -> 120397.19 | BG9: 6 | BH9: =+BG9*$F$1 -> 20.4 | BI9: =+BG9*$BH$48 -> 44567.625 | BJ9: =+BH9*$BH$47 -> 43136.708 | BK9: =+BJ9+BI9 -> 87704.333 | BL9: 7 | BM9: =+BL9*$F$1 -> 23.8 | BN9: =+BL9*$BM$48 -> 51995.562 | BO9: =+BM9*$BM$47 -> 51344.258 | BP9: =+BO9+BN9 -> 103339.82
A10: 2017 TORRE A | B10: 301 | C10: 28 | E10: =+C10*$F$1 -> 95.2 | F10: =+C10*$E$48 -> 200379.3 | G10: =+E10*$E$47 -> #REF! | H10: =+G10+F10 -> #REF! | I10: 22 | K10: =+I10*$F$1 -> 74.8 | L10: =+I10*$K$48 -> 157440.88 | M10: =+K10*$K$47 -> 151800.49 | N10: =+M10+L10 -> 309241.37 | O10: 18 | Q10: =+O10*$F$1 -> 61.2 | R10: =+O10*$Q$48 -> 129034.26 | S10: =+Q10*$Q$47 -> 135260.78 | T10: =+S10+R10 -> 264295.04 | U10: 21 | V10: =+U10*$F$1 -> 71.4 | W10: =+U10*$V$48 -> 150539.97 | X10: =+V10*$V$47 -> 167440.79 | Y10: =+X10+W10 -> 317980.76 | Z10: 15 | AA10: =+Z10*$F$1 -> 51 | AB10: =+Z10*$AB$48 -> 112660.86 | AC10: =+AA10*$AB$47 -> 104896.61 | AD10: =+AC10+AB10 -> 217557.47 | AE10: 17 | AF10: =+AE10*$F$1 -> 57.8 | AG10: =+AE10*$AF$48 -> 127682.31 | AH10: =+AF10*$AF$47 -> 121808.63 | AI10: =+AH10+AG10 -> 249490.94 | AJ10: 18 | AK10: =+AJ10*$F$1 -> 61.2 | AM10: =+AJ10*$AK$48 -> 133692.91 | AN10: =+AK10*$AK$47 -> 131760.47 | AO10: =+AN10+AM10 -> 265453.38 | AP10: 20 | AQ10: =+AP10*$F$1 -> 68 | AS10: =+AP10*$AQ$48 -> 148547.68 | AT10: =+AQ10*$AQ$47 -> 140159.27 | AU10: =+AT10+AS10 -> 288706.95 | AV10: 20 | AW10: =+AV10*$F$1 -> 68 | AY10: =+AV10*$AW$48 -> 148550.71 | AZ10: =+AW10*$AW$47 -> 159870.73 | BA10: =+AZ10+AY10 -> 308421.44 | BB10: 20 | BC10: =+BB10*$F$1 -> 68 | BD10: =+BB10*$BC$48 -> 148550.71 | BE10: =+BC10*$BC$47 -> 152442.26 | BF10: =+BE10+BD10 -> 300992.97 | BG10: 18 | BH10: =+BG10*$F$1 -> 61.2 | BI10: =+BG10*$BH$48 -> 133702.88 | BJ10: =+BH10*$BH$47 -> 129410.12 | BK10: =+BJ10+BI10 -> 263113 | BL10: 18 | BM10: =+BL10*$F$1 -> 61.2 | BN10: =+BL10*$BM$48 -> 133702.88 | BO10: =+BM10*$BM$47 -> 132028.09 | BP10: =+BO10+BN10 -> 265730.97
A11: 2017 TORRE A | B11: 302 | C11: 10 | E11: =+C11*$F$1 -> 34 | F11: =+C11*$E$48 -> 71564.036 | G11: =+E11*$E$47 -> #REF! | H11: =+G11+F11 -> #REF! | I11: 9 | K11: =+I11*$F$1 -> 30.6 | L11: =+I11*$K$48 -> 64407.632 | M11: =+K11*$K$47 -> 62100.2 | N11: =+M11+L11 -> 126507.83 | O11: 10 | Q11: =+O11*$F$1 -> 34 | R11: =+O11*$Q$48 -> 71685.7 | S11: =+Q11*$Q$47 -> 75144.877 | T11: =+S11+R11 -> 146830.58 | U11: 15 | V11: =+U11*$F$1 -> 51 | W11: =+U11*$V$48 -> 107528.55 | X11: =+V11*$V$47 -> 119600.57 | Y11: =+X11+W11 -> 227129.12 | Z11: 12 | AA11: =+Z11*$F$1 -> 40.8 | AB11: =+Z11*$AB$48 -> 90128.687 | AC11: =+AA11*$AB$47 -> 83917.292 | AD11: =+AC11+AB11 -> 174045.98 | AE11: 13 | AF11: =+AE11*$F$1 -> 44.2 | AG11: =+AE11*$AF$48 -> 97639.411 | AH11: =+AF11*$AF$47 -> 93147.776 | AI11: =+AH11+AG11 -> 190787.19 | AJ11: 12 | AK11: =+AJ11*$F$1 -> 40.8 | AM11: =+AJ11*$AK$48 -> 89128.607 | AN11: =+AK11*$AK$47 -> 87840.312 | AO11: =+AN11+AM11 -> 176968.92 | AP11: 13 | AQ11: =+AP11*$F$1 -> 44.2 | AS11: =+AP11*$AQ$48 -> 96555.991 | AT11: =+AQ11*$AQ$47 -> 91103.524 | AU11: =+AT11+AS11 -> 187659.51 | AV11: 14 | AW11: =+AV11*$F$1 -> 47.6 | AY11: =+AV11*$AW$48 -> 103985.5 | AZ11: =+AW11*$AW$47 -> 111909.51 | BA11: =+AZ11+AY11 -> 215895.01 | BB11: 12 | BC11: =+BB11*$F$1 -> 40.8 | BD11: =+BB11*$BC$48 -> 89130.428 | BE11: =+BC11*$BC$47 -> 91465.353 | BF11: =+BE11+BD11 -> 180595.78 | BG11: 13 | BH11: =+BG11*$F$1 -> 44.2 | BI11: =+BG11*$BH$48 -> 96563.188 | BJ11: =+BH11*$BH$47 -> 93462.868 | BK11: =+BJ11+BI11 -> 190026.06 | BL11: 13 | BM11: =+BL11*$F$1 -> 44.2 | BN11: =+BL11*$BM$48 -> 96563.188 | BO11: =+BM11*$BM$47 -> 95353.622 | BP11: =+BO11+BN11 -> 191916.81
A12: 2017 TORRE A | B12: 401 | C12: 5 | E12: =+C12*$F$1 -> 17 | F12: =+C12*$E$48 -> 35782.018 | G12: =+E12*$E$47 -> #REF! | H12: =+G12+F12 -> #REF! | I12: 4 | K12: =+I12*$F$1 -> 13.6 | L12: =+I12*$K$48 -> 28625.614 | M12: =+K12*$K$47 -> 27600.089 | N12: =+M12+L12 -> 56225.703 | O12: 6 | Q12: =+O12*$F$1 -> 20.4 | R12: =+O12*$Q$48 -> 43011.42 | S12: =+Q12*$Q$47 -> 45086.926 | T12: =+S12+R12 -> 88098.346 | U12: 5 | V12: =+U12*$F$1 -> 17 | W12: =+U12*$V$48 -> 35842.85 | X12: =+V12*$V$47 -> 39866.855 | Y12: =+X12+W12 -> 75709.706 | Z12: 4 | AA12: =+Z12*$F$1 -> 13.6 | AB12: =+Z12*$AB$48 -> 30042.896 | AC12: =+AA12*$AB$47 -> 27972.431 | AD12: =+AC12+AB12 -> 58015.326 | AE12: 6 | AF12: =+AE12*$F$1 -> 20.4 | AG12: =+AE12*$AF$48 -> 45064.343 | AH12: =+AF12*$AF$47 -> 42991.281 | AI12: =+AH12+AG12 -> 88055.624 | AJ12: 5 | AK12: =+AJ12*$F$1 -> 17 | AM12: =+AJ12*$AK$48 -> 37136.919 | AN12: =+AK12*$AK$47 -> 36600.13 | AO12: =+AN12+AM12 -> 73737.049 | AP12: 5 | AQ12: =+AP12*$F$1 -> 17 | AS12: =+AP12*$AQ$48 -> 37136.919 | AT12: =+AQ12*$AQ$47 -> 35039.817 | AU12: =+AT12+AS12 -> 72176.736 | AV12: 5 | AW12: =+AV12*$F$1 -> 17 | AY12: =+AV12*$AW$48 -> 37137.678 | AZ12: =+AW12*$AW$47 -> 39967.682 | BA12: =+AZ12+AY12 -> 77105.361 | BB12: 6 | BC12: =+BB12*$F$1 -> 20.4 | BD12: =+BB12*$BC$48 -> 44565.214 | BE12: =+BC12*$BC$47 -> 45732.677 | BF12: =+BE12+BD12 -> 90297.891 | BG12: 4 | BH12: =+BG12*$F$1 -> 13.6 | BI12: =+BG12*$BH$48 -> 29711.75 | BJ12: =+BH12*$BH$47 -> 28757.806 | BK12: =+BJ12+BI12 -> 58469.556 | BL12: 7 | BM12: =+BL12*$F$1 -> 23.8 | BN12: =+BL12*$BM$48 -> 51995.562 | BO12: =+BM12*$BM$47 -> 51344.258 | BP12: =+BO12+BN12 -> 103339.82
A13: 2017 TORRE A | B13: 402 | C13: 3 | E13: =+C13*$F$1 -> 10.2 | F13: =+C13*$E$48 -> 21469.211 | G13: =+E13*$E$47 -> #REF! | H13: =+G13+F13 -> #REF! | I13: 4 | K13: =+I13*$F$1 -> 13.6 | L13: =+I13*$K$48 -> 28625.614 | M13: =+K13*$K$47 -> 27600.089 | N13: =+M13+L13 -> 56225.703 | O13: 3 | Q13: =+O13*$F$1 -> 10.2 | R13: =+O13*$Q$48 -> 21505.71 | S13: =+Q13*$Q$47 -> 22543.463 | T13: =+S13+R13 -> 44049.173 | U13: 4 | V13: =+U13*$F$1 -> 13.6 | W13: =+U13*$V$48 -> 28674.28 | X13: =+V13*$V$47 -> 31893.484 | Y13: =+X13+W13 -> 60567.764 | Z13: 2 | AA13: =+Z13*$F$1 -> 6.8 | AB13: =+Z13*$AB$48 -> 15021.448 | AC13: =+AA13*$AB$47 -> 13986.215 | AD13: =+AC13+AB13 -> 29007.663 | AE13: 3 | AF13: =+AE13*$F$1 -> 10.2 | AG13: =+AE13*$AF$48 -> 22532.172 | AH13: =+AF13*$AF$47 -> 21495.641 | AI13: =+AH13+AG13 -> 44027.812 | AJ13: 3 | AK13: =+AJ13*$F$1 -> 10.2 | AM13: =+AJ13*$AK$48 -> 22282.152 | AN13: =+AK13*$AK$47 -> 21960.078 | AO13: =+AN13+AM13 -> 44242.23 | AP13: 3 | AQ13: =+AP13*$F$1 -> 10.2 | AS13: =+AP13*$AQ$48 -> 22282.152 | AT13: =+AQ13*$AQ$47 -> 21023.89 | AU13: =+AT13+AS13 -> 43306.042 | AV13: 4 | AW13: =+AV13*$F$1 -> 13.6 | AY13: =+AV13*$AW$48 -> 29710.143 | AZ13: =+AW13*$AW$47 -> 31974.146 | BA13: =+AZ13+AY13 -> 61684.288 | BB13: 1 | BC13: =+BB13*$F$1 -> 3.4 | BD13: =+BB13*$BC$48 -> 7427.5357 | BE13: =+BC13*$BC$47 -> 7622.1128 | BF13: =+BE13+BD13 -> 15049.648 | BG13: 2 | BH13: =+BG13*$F$1 -> 6.8 | BI13: =+BG13*$BH$48 -> 14855.875 | BJ13: =+BH13*$BH$47 -> 14378.903 | BK13: =+BJ13+BI13 -> 29234.778 | BL13: 4 | BM13: =+BL13*$F$1 -> 13.6 | BN13: =+BL13*$BM$48 -> 29711.75 | BO13: =+BM13*$BM$47 -> 29339.576 | BP13: =+BO13+BN13 -> 59051.326
A14: 2017 TORRE A | B14: 403 | C14: 1 | E14: =+C14*$F$1 -> 3.4 | F14: =+C14*$E$48 -> 7156.4036 | G14: =+E14*$E$47 -> #REF! | H14: =+G14+F14 -> #REF! | I14: 1 | K14: =+I14*$F$1 -> 3.4 | L14: =+I14*$K$48 -> 7156.4036 | M14: =+K14*$K$47 -> 6900.0223 | N14: =+M14+L14 -> 14056.426 | O14: 1 | Q14: =+O14*$F$1 -> 3.4 | R14: =+O14*$Q$48 -> 7168.57 | S14: =+Q14*$Q$47 -> 7514.4877 | T14: =+S14+R14 -> 14683.058 | U14: 2 | V14: =+U14*$F$1 -> 6.8 | W14: =+U14*$V$48 -> 14337.14 | X14: =+V14*$V$47 -> 15946.742 | Y14: =+X14+W14 -> 30283.882 | Z14: 1 | AA14: =+Z14*$F$1 -> 3.4 | AB14: =+Z14*$AB$48 -> 7510.7239 | AC14: =+AA14*$AB$47 -> 6993.1076 | AD14: =+AC14+AB14 -> 14503.832 | AE14: 1 | AF14: =+AE14*$F$1 -> 3.4 | AG14: =+AE14*$AF$48 -> 7510.7239 | AH14: =+AF14*$AF$47 -> 7165.2135 | AI14: =+AH14+AG14 -> 14675.937 | AJ14: 1 | AK14: =+AJ14*$F$1 -> 3.4 | AM14: =+AJ14*$AK$48 -> 7427.3839 | AN14: =+AK14*$AK$47 -> 7320.026 | AO14: =+AN14+AM14 -> 14747.41 | AP14: 1 | AQ14: =+AP14*$F$1 -> 3.4 | AS14: =+AP14*$AQ$48 -> 7427.3839 | AT14: =+AQ14*$AQ$47 -> 7007.9634 | AU14: =+AT14+AS14 -> 14435.347 | AV14: 1 | AW14: =+AV14*$F$1 -> 3.4 | AY14: =+AV14*$AW$48 -> 7427.5357 | AZ14: =+AW14*$AW$47 -> 7993.5364 | BA14: =+AZ14+AY14 -> 15421.072 | BB14: 2 | BC14: =+BB14*$F$1 -> 6.8 | BD14: =+BB14*$BC$48 -> 14855.071 | BE14: =+BC14*$BC$47 -> 15244.226 | BF14: =+BE14+BD14 -> 30099.297 | BG14: 1 | BH14: =+BG14*$F$1 -> 3.4 | BI14: =+BG14*$BH$48 -> 7427.9375 | BJ14: =+BH14*$BH$47 -> 7189.4514 | BK14: =+BJ14+BI14 -> 14617.389 | BL14: 1 | BM14: =+BL14*$F$1 -> 3.4 | BN14: =+BL14*$BM$48 -> 7427.9375 | BO14: =+BM14*$BM$47 -> 7334.894 | BP14: =+BO14+BN14 -> 14762.832
A15: 2017 TORRE A | B15: 404 | C15: 6 | E15: =+C15*$F$1 -> 20.4 | F15: =+C15*$E$48 -> 42938.421 | G15: =+E15*$E$47 -> #REF! | H15: =+G15+F15 -> #REF! | I15: 5 | K15: =+I15*$F$1 -> 17 | L15: =+I15*$K$48 -> 35782.018 | M15: =+K15*$K$47 -> 34500.111 | N15: =+M15+L15 -> 70282.129 | O15: 7 | Q15: =+O15*$F$1 -> 23.8 | R15: =+O15*$Q$48 -> 50179.99 | S15: =+Q15*$Q$47 -> 52601.414 | T15: =+S15+R15 -> 102781.4 | U15: 6 | V15: =+U15*$F$1 -> 20.4 | W15: =+U15*$V$48 -> 43011.42 | X15: =+V15*$V$47 -> 47840.227 | Y15: =+X15+W15 -> 90851.647 | Z15: 6 | AA15: =+Z15*$F$1 -> 20.4 | AB15: =+Z15*$AB$48 -> 45064.343 | AC15: =+AA15*$AB$47 -> 41958.646 | AD15: =+AC15+AB15 -> 87022.989 | AE15: 7 | AF15: =+AE15*$F$1 -> 23.8 | AG15: =+AE15*$AF$48 -> 52575.067 | AH15: =+AF15*$AF$47 -> 50156.495 | AI15: =+AH15+AG15 -> 102731.56 | AJ15: 7 | AK15: =+AJ15*$F$1 -> 23.8 | AM15: =+AJ15*$AK$48 -> 51991.687 | AN15: =+AK15*$AK$47 -> 51240.182 | AO15: =+AN15+AM15 -> 103231.87 | AP15: 0 | AQ15: =+AP15*$F$1 -> 0 | AS15: =+AP15*$AQ$48 -> 0 | AT15: =+AQ15*$AQ$47 -> 0 | AU15: =+AT15+AS15 -> 0 | AV15: 0 | AW15: =+AV15*$F$1 -> 0 | AY15: =+AV15*$AW$48 -> 0 | AZ15: =+AW15*$AW$47 -> 0 | BA15: =+AZ15+AY15 -> 0 | BB15: 1 | BC15: =+BB15*$F$1 -> 3.4 | BD15: =+BB15*$BC$48 -> 7427.5357 | BE15: =+BC15*$BC$47 -> 7622.1128 | BF15: =+BE15+BD15 -> 15049.648 | BG15: 3 | BH15: =+BG15*$F$1 -> 10.2 | BI15: =+BG15*$BH$48 -> 22283.812 | BJ15: =+BH15*$BH$47 -> 21568.354 | BK15: =+BJ15+BI15 -> 43852.167 | BL15: 2 | BM15: =+BL15*$F$1 -> 6.8 | BN15: =+BL15*$BM$48 -> 14855.875 | BO15: =+BM15*$BM$47 -> 14669.788 | BP15: =+BO15+BN15 -> 29525.663
A16: 2017 TORRE A | B16: 501 | C16: 1 | E16: =+C16*$F$1 -> 3.4 | F16: =+C16*$E$48 -> 7156.4036 | G16: =+E16*$E$47 -> #REF! | H16: =+G16+F16 -> #REF! | I16: 1 | K16: =+I16*$F$1 -> 3.4 | L16: =+I16*$K$48 -> 7156.4036 | M16: =+K16*$K$47 -> 6900.0223 | N16: =+M16+L16 -> 14056.426 | O16: 2 | Q16: =+O16*$F$1 -> 6.8 | R16: =+O16*$Q$48 -> 14337.14 | S16: =+Q16*$Q$47 -> 15028.975 | T16: =+S16+R16 -> 29366.115 | U16: 2 | V16: =+U16*$F$1 -> 6.8 | W16: =+U16*$V$48 -> 14337.14 | X16: =+V16*$V$47 -> 15946.742 | Y16: =+X16+W16 -> 30283.882 | Z16: 2 | AA16: =+Z16*$F$1 -> 6.8 | AB16: =+Z16*$AB$48 -> 15021.448 | AC16: =+AA16*$AB$47 -> 13986.215 | AD16: =+AC16+AB16 -> 29007.663 | AE16: 2 | AF16: =+AE16*$F$1 -> 6.8 | AG16: =+AE16*$AF$48 -> 15021.448 | AH16: =+AF16*$AF$47 -> 14330.427 | AI16: =+AH16+AG16 -> 29351.875 | AJ16: 2 | AK16: =+AJ16*$F$1 -> 6.8 | AM16: =+AJ16*$AK$48 -> 14854.768 | AN16: =+AK16*$AK$47 -> 14640.052 | AO16: =+AN16+AM16 -> 29494.82 | AP16: 1 | AQ16: =+AP16*$F$1 -> 3.4 | AS16: =+AP16*$AQ$48 -> 7427.3839 | AT16: =+AQ16*$AQ$47 -> 7007.9634 | AU16: =+AT16+AS16 -> 14435.347 | AV16: 2 | AW16: =+AV16*$F$1 -> 6.8 | AY16: =+AV16*$AW$48 -> 14855.071 | AZ16: =+AW16*$AW$47 -> 15987.073 | BA16: =+AZ16+AY16 -> 30842.144 | BB16: 2 | BC16: =+BB16*$F$1 -> 6.8 | BD16: =+BB16*$BC$48 -> 14855.071 | BE16: =+BC16*$BC$47 -> 15244.226 | BF16: =+BE16+BD16 -> 30099.297 | BG16: 3 | BH16: =+BG16*$F$1 -> 10.2 | BI16: =+BG16*$BH$48 -> 22283.812 | BJ16: =+BH16*$BH$47 -> 21568.354 | BK16: =+BJ16+BI16 -> 43852.167 | BL16: 2 | BM16: =+BL16*$F$1 -> 6.8 | BN16: =+BL16*$BM$48 -> 14855.875 | BO16: =+BM16*$BM$47 -> 14669.788 | BP16: =+BO16+BN16 -> 29525.663
A17: 2017 TORRE A | B17: 502 | C17: 2 | E17: =+C17*$F$1 -> 6.8 | F17: =+C17*$E$48 -> 14312.807 | G17: =+E17*$E$47 -> #REF! | H17: =+G17+F17 -> #REF! | I17: 2 | K17: =+I17*$F$1 -> 6.8 | L17: =+I17*$K$48 -> 14312.807 | M17: =+K17*$K$47 -> 13800.045 | N17: =+M17+L17 -> 28112.852 | O17: 2 | Q17: =+O17*$F$1 -> 6.8 | R17: =+O17*$Q$48 -> 14337.14 | S17: =+Q17*$Q$47 -> 15028.975 | T17: =+S17+R17 -> 29366.115 | U17: 3 | V17: =+U17*$F$1 -> 10.2 | W17: =+U17*$V$48 -> 21505.71 | X17: =+V17*$V$47 -> 23920.113 | Y17: =+X17+W17 -> 45425.823 | Z17: 2 | AA17: =+Z17*$F$1 -> 6.8 | AB17: =+Z17*$AB$48 -> 15021.448 | AC17: =+AA17*$AB$47 -> 13986.215 | AD17: =+AC17+AB17 -> 29007.663 | AE17: 3 | AF17: =+AE17*$F$1 -> 10.2 | AG17: =+AE17*$AF$48 -> 22532.172 | AH17: =+AF17*$AF$47 -> 21495.641 | AI17: =+AH17+AG17 -> 44027.812 | AJ17: 2 | AK17: =+AJ17*$F$1 -> 6.8 | AM17: =+AJ17*$AK$48 -> 14854.768 | AN17: =+AK17*$AK$47 -> 14640.052 | AO17: =+AN17+AM17 -> 29494.82 | AP17: 2 | AQ17: =+AP17*$F$1 -> 6.8 | AS17: =+AP17*$AQ$48 -> 14854.768 | AT17: =+AQ17*$AQ$47 -> 14015.927 | AU17: =+AT17+AS17 -> 28870.695 | AV17: 1 | AW17: =+AV17*$F$1 -> 3.4 | AY17: =+AV17*$AW$48 -> 7427.5357 | AZ17: =+AW17*$AW$47 -> 7993.5364 | BA17: =+AZ17+AY17 -> 15421.072 | BB17: 3 | BC17: =+BB17*$F$1 -> 10.2 | BD17: =+BB17*$BC$48 -> 22282.607 | BE17: =+BC17*$BC$47 -> 22866.338 | BF17: =+BE17+BD17 -> 45148.945 | BG17: 3 | BH17: =+BG17*$F$1 -> 10.2 | BI17: =+BG17*$BH$48 -> 22283.812 | BJ17: =+BH17*$BH$47 -> 21568.354 | BK17: =+BJ17+BI17 -> 43852.167 | BL17: 3 | BM17: =+BL17*$F$1 -> 10.2 | BN17: =+BL17*$BM$48 -> 22283.812 | BO17: =+BM17*$BM$47 -> 22004.682 | BP17: =+BO17+BN17 -> 44288.495
A18: 2017 TORRE A | B18: 503 | C18: 4 | E18: =+C18*$F$1 -> 13.6 | F18: =+C18*$E$48 -> 28625.614 | G18: =+E18*$E$47 -> #REF! | H18: =+G18+F18 -> #REF! | I18: 5 | K18: =+I18*$F$1 -> 17 | L18: =+I18*$K$48 -> 35782.018 | M18: =+K18*$K$47 -> 34500.111 | N18: =+M18+L18 -> 70282.129 | O18: 5 | Q18: =+O18*$F$1 -> 17 | R18: =+O18*$Q$48 -> 35842.85 | S18: =+Q18*$Q$47 -> 37572.438 | T18: =+S18+R18 -> 73415.289 | U18: 7 | V18: =+U18*$F$1 -> 23.8 | W18: =+U18*$V$48 -> 50179.99 | X18: =+V18*$V$47 -> 55813.598 | Y18: =+X18+W18 -> 105993.59 | Z18: 5 | AA18: =+Z18*$F$1 -> 17 | AB18: =+Z18*$AB$48 -> 37553.619 | AC18: =+AA18*$AB$47 -> 34965.538 | AD18: =+AC18+AB18 -> 72519.158 | AE18: 5 | AF18: =+AE18*$F$1 -> 17 | AG18: =+AE18*$AF$48 -> 37553.619 | AH18: =+AF18*$AF$47 -> 35826.068 | AI18: =+AH18+AG18 -> 73379.687 | AJ18: 5 | AK18: =+AJ18*$F$1 -> 17 | AM18: =+AJ18*$AK$48 -> 37136.919 | AN18: =+AK18*$AK$47 -> 36600.13 | AO18: =+AN18+AM18 -> 73737.049 | AP18: 3 | AQ18: =+AP18*$F$1 -> 10.2 | AS18: =+AP18*$AQ$48 -> 22282.152 | AT18: =+AQ18*$AQ$47 -> 21023.89 | AU18: =+AT18+AS18 -> 43306.042 | AV18: 4 | AW18: =+AV18*$F$1 -> 13.6 | AY18: =+AV18*$AW$48 -> 29710.143 | AZ18: =+AW18*$AW$47 -> 31974.146 | BA18: =+AZ18+AY18 -> 61684.288 | BB18: 6 | BC18: =+BB18*$F$1 -> 20.4 | BD18: =+BB18*$BC$48 -> 44565.214 | BE18: =+BC18*$BC$47 -> 45732.677 | BF18: =+BE18+BD18 -> 90297.891 | BG18: 4 | BH18: =+BG18*$F$1 -> 13.6 | BI18: =+BG18*$BH$48 -> 29711.75 | BJ18: =+BH18*$BH$47 -> 28757.806 | BK18: =+BJ18+BI18 -> 58469.556 | BL18: 4 | BM18: =+BL18*$F$1 -> 13.6 | BN18: =+BL18*$BM$48 -> 29711.75 | BO18: =+BM18*$BM$47 -> 29339.576 | BP18: =+BO18+BN18 -> 59051.326
... A43: 2017 TORRE A | B43: 1302 | C43: 3 | E43: =+C43*$F$1 -> 10.2 | F43: =+C43*$E$48 -> 21469.211 | G43: =+E43*$E$47 -> #REF! | H43: =+G43+F43 -> #REF! | I43: 6 | K43: =+I43*$F$1 -> 20.4 | L43: =+I43*$K$48 -> 42938.421 | M43: =+K43*$K$47 -> 41400.134 | N43: =+M43+L43 -> 84338.555 | O43: 11 | Q43: =+O43*$F$1 -> 37.4 | R43: =+O43*$Q$48 -> 78854.27 | S43: =+Q43*$Q$47 -> 82659.364 | T43: =+S43+R43 -> 161513.63 | U43: 14 | V43: =+U43*$F$1 -> 47.6 | W43: =+U43*$V$48 -> 100359.98 | X43: =+V43*$V$47 -> 111627.2 | Y43: =+X43+W43 -> 211987.18 | Z43: 11 | AA43: =+Z43*$F$1 -> 37.4 | AB43: =+Z43*$AB$48 -> 82617.963 | AC43: =+AA43*$AB$47 -> 76924.184 | AD43: =+AC43+AB43 -> 159542.15 | AE43: 13 | AF43: =+AE43*$F$1 -> 44.2 | AG43: =+AE43*$AF$48 -> 97639.411 | AH43: =+AF43*$AF$47 -> 93147.776 | AI43: =+AH43+AG43 -> 190787.19 | AJ43: 8 | AK43: =+AJ43*$F$1 -> 27.2 | AM43: =+AJ43*$AK$48 -> 59419.071 | AN43: =+AK43*$AK$47 -> 58560.208 | AO43: =+AN43+AM43 -> 117979.28 | AP43: 11 | AQ43: =+AP43*$F$1 -> 37.4 | AS43: =+AP43*$AQ$48 -> 81701.223 | AT43: =+AQ43*$AQ$47 -> 77087.597 | AU43: =+AT43+AS43 -> 158788.82 | AV43: 14 | AW43: =+AV43*$F$1 -> 47.6 | AY43: =+AV43*$AW$48 -> 103985.5 | AZ43: =+AW43*$AW$47 -> 111909.51 | BA43: =+AZ43+AY43 -> 215895.01 | BB43: 16 | BC43: =+BB43*$F$1 -> 54.4 | BD43: =+BB43*$BC$48 -> 118840.57 | BE43: =+BC43*$BC$47 -> 121953.8 | BF43: =+BE43+BD43 -> 240794.38 | BG43: 9 | BH43: =+BG43*$F$1 -> 30.6 | BI43: =+BG43*$BH$48 -> 66851.438 | BJ43: =+BH43*$BH$47 -> 64705.062 | BK43: =+BJ43+BI43 -> 131556.5 | BL43: 14 | BM43: =+BL43*$F$1 -> 47.6 | BN43: =+BL43*$BM$48 -> 103991.12 | BO43: =+BM43*$BM$47 -> 102688.52 | BP43: =+BO43+BN43 -> 206679.64
A44: 2017 TORRE A | C44: =SUM(C7:C43) -> 186 | E44: =SUM(E7:E43) -> 632.4 | F44: =SUM(F7:F43) -> 1331091.1 | G44: =SUM(G7:G43) -> #REF! | H44: =SUM(H7:H43) -> #REF! | I44: =SUM(I7:I43) -> 183 | K44: =SUM(K7:K43) -> 622.2 | L44: =SUM(L7:L43) -> 1309621.9 | M44: =SUM(M7:M43) -> 1262704.1 | N44: =SUM(N7:N43) -> 2572325.9 | O44: =SUM(O7:O43) -> 187 | Q44: =SUM(Q7:Q43) -> 635.8 | R44: =SUM(R7:R43) -> 1340522.6 | S44: =SUM(S7:S43) -> 1405209.2 | T44: =SUM(T7:T43) -> 2745731.8 | U44: =SUM(U7:U43) -> 231 | V44: =SUM(V7:V43) -> 785.4 | W44: =SUM(W7:W43) -> 1655939.7 | X44: =SUM(X7:X43) -> 1841848.7 | ... AK44: =SUM(AK7:AK43) -> 686.8 | AM44: =SUM(AM7:AM43) -> 1500331.5 | AN44: =SUM(AN7:AN43) -> 1478645.3 | AO44: =SUM(AO7:AO43) -> 2978976.8 | AP44: =SUM(AP7:AP43) -> 195 | AQ44: =SUM(AQ7:AQ43) -> 663 | AS44: =SUM(AS7:AS43) -> 1448339.9 | AT44: =SUM(AT7:AT43) -> 1366552.9 | AU44: =SUM(AU7:AU43) -> 2814892.7 | AV44: =SUM(AV7:AV43) -> 238 | AW44: =SUM(AW7:AW43) -> 809.2 | AY44: =SUM(AY7:AY43) -> 1767753.5 | AZ44: =SUM(AZ7:AZ43) -> 1902461.7 | BA44: =SUM(BA7:BA43) -> 3670215.2 | BB44: =SUM(BB7:BB43) -> 267 | BC44: =SUM(BC7:BC43) -> 907.8 | BD44: =SUM(BD7:BD43) -> 1983152 | BE44: =SUM(BE7:BE43) -> 2035104.1 | BF44: =SUM(BF7:BF43) -> 4018256.1 | ... BP44: =SUM(BP7:BP43) -> 3749759.2
A45: 2017 TORRE A
A46: 2017 TORRE A | C46: ENERO DE 2017 | I46: FEBRERO DE 2017 | O46: MARZO DE 2017 | U46: ABRIL DE 2017 | AA46: MAYO DE 2017 | AE46: JUNIO DE 2017 | AJ46: JULIO DE 2017 | AP46: AGOSTO DE 2017 | AV46: SEPTIEMBRE DE 2017 | BB46: OCTUBRE DE 2017 | BG46: NOVIEMBRE DE 2017 | BL46: DICIEMBRE DE 2017
A47: 2017 TORRE A | C47: VR M3 GAS | E47: =+'Vr M3 DE GAS'!#REF! -> #REF! | I47: VR M3 GAS | K47: =+'Vr M3 DE GAS'!$F$62 -> 2029.4183 | O47: VR M3 GAS | Q47: =+'Vr M3 DE GAS'!$F$63 -> 2210.1434 | U47: VR M3 GAS | V47: =+'Vr M3 DE GAS'!$F$64 -> 2345.1091 | AA47: VR M3 GAS | AB47: =+'Vr M3 DE GAS'!$F$65 -> 2056.7964 | AE47: VR M3 GAS | AF47: =+'Vr M3 DE GAS'!$F$66 -> 2107.4157 | AJ47: VR M3 GAS | AK47: =+'Vr M3 DE GAS'!$F$67 -> 2152.9488 | AP47: VR M3 GAS | AQ47: =+'Vr M3 DE GAS'!$F$68 -> 2061.1657 | AV47: VR M3 GAS | AW47: =+'Vr M3 DE GAS'!$F$69 -> 2351.0401 | BB47: VR M3 GAS | BC47: =+'Vr M3 DE GAS'!$F$70 -> 2241.7979 | BG47: VR M3 GAS | BH47: =+'Vr M3 DE GAS'!$F$71 -> 2114.5445 | BL47: VR M3 GAS | BM47: =+'Vr M3 DE GAS'!$F$72 -> 2157.3218
A48: 2017 TORRE A | C48: VR M3 AGUA | E48: =+'Vr M3 DE AGUA'!$N$4 -> 7156.4036 | I48: VR M3 AGUA | K48: =+'Vr M3 DE AGUA'!$N$4 -> 7156.4036 | O48: VR M3 AGUA | Q48: =+'Vr M3 DE AGUA'!$N$5 -> 7168.57 | U48: VR M3 AGUA | V48: =+'Vr M3 DE AGUA'!$N$5 -> 7168.57 | AA48: VR M3 AGUA | AB48: =+'Vr M3 DE AGUA'!$N$6 -> 7510.7239 | AE48: VR M3 AGUA | AF48: =+'Vr M3 DE AGUA'!$N$6 -> 7510.7239 | AJ48: VR M3 AGUA | AK48: =+'Vr M3 DE AGUA'!$N$7 -> 7427.3839 | AP48: VR M3 AGUA | AQ48: =+'Vr M3 DE AGUA'!$N$7 -> 7427.3839 | AV48: VR M3 AGUA | AW48: =+'Vr M3 DE AGUA'!$N$8 -> 7427.5357 | BB48: VR M3 AGUA | BC48: =+'Vr M3 DE AGUA'!$N$8 -> 7427.5357 | BG48: VR M3 AGUA | BH48: =+'Vr M3 DE AGUA'!N$9 -> 7427.9375 | BL48: VR M3 AGUA | BM48: =+'Vr M3 DE AGUA'!$N$9 -> 7427.9375
B52: AÑO 2017
B53: TORRE B
C54: ENERO | I54: FEBRERO | O54: MARZO | U54: ABRIL | Z54: MAYO | AE54: JUNIO | AJ54: JULIO | AP54: AGOSTO | AV54: SEPTIEMBRE | BB54: OCTUBRE | BG54: NOVIEMBRE | BL54: DICIEMBRE
C56: AGUA | E56: GAS | F56: $ AGUA | G56: $GAS | H56: $ TOTAL | I56: AGUA | K56: GAS | L56: $ AGUA | M56: $GAS | N56: $ TOTAL | O56: AGUA | Q56: GAS | R56: $ AGUA | S56: $GAS | T56: $ TOTAL | U56: AGUA | V56: GAS | W56: $ AGUA | X56: $GAS | Y56: $ TOTAL | Z56: AGUA | AA56: GAS | AB56: $ AGUA | AC56: $GAS | AD56: $ TOTAL | AE56: AGUA | AF56: GAS | AG56: $ AGUA | AH56: $GAS | AI56: $ TOTAL | AJ56: AGUA | AK56: GAS | AM56: $ AGUA | AN56: $GAS | AO56: $ TOTAL | AP56: AGUA | AQ56: GAS | AS56: $ AGUA | AT56: $GAS | AU56: $ TOTAL | AV56: AGUA | AW56: GAS | AY56: $ AGUA | AZ56: $GAS | BA56: $ TOTAL | BB56: AGUA | BC56: GAS | BD56: $ AGUA | BE56: $GAS | BF56: $ TOTAL | BG56: AGUA | BH56: GAS | BI56: $ AGUA | BJ56: $GAS | BK56: $ TOTAL | BL56: AGUA | BM56: GAS | BN56: $ AGUA | BO56: $GAS | BP56: $ TOTAL
A57: 2017 TORRE B | B57: 201 | C57: 5 | E57: =+C57*3 -> 15 | F57: =+C57*$E$93 -> 35782.018 | G57: =+E57*E$92 -> #REF! | H57: =+F57+G57 -> #REF! | I57: 6 | K57: =+I57*$F$1 -> 20.4 | L57: =+I57*$K$93 -> 42938.421 | M57: =+K57*$K$92 -> 41400.134 | N57: =+M57+L57 -> 84338.555 | O57: 6 | Q57: =+O57*$F$1 -> 20.4 | R57: =+O57*$Q$93 -> 43011.42 | S57: =+Q57*$Q$92 -> 45086.926 | T57: =+S57+R57 -> 88098.346 | U57: 6 | V57: =+U57*$F$1 -> 20.4 | W57: =+U57*$V$93 -> 43011.42 | X57: =+V57*$V$92 -> 47840.227 | Y57: =+X57+W57 -> 90851.647 | Z57: 6 | AA57: =+Z57*$F$1 -> 20.4 | AB57: =+Z57*$AB$93 -> 45064.343 | AC57: =+AA57*$AB$92 -> 41958.646 | AD57: =+AC57+AB57 -> 87022.989 | AE57: 8 | AF57: =+AE57*$F$1 -> 27.2 | AG57: =+AE57*$AF$93 -> 60085.791 | AH57: =+AF57*$AF$92 -> 57321.708 | AI57: =+AH57+AG57 -> 117407.5 | AJ57: 5 | AK57: =+AJ57*$F$1 -> 17 | AM57: =+AJ57*$AK$93 -> 37136.919 | AN57: =+AK57*$AK$92 -> 36600.13 | AO57: =+AM57+AN57 -> 73737.049 | AP57: 7 | AQ57: =+AP57*$F$1 -> 23.8 | AS57: =+AP57*$AQ$93 -> 51991.687 | AT57: =+AQ57*$AQ$92 -> 49055.744 | AU57: =+AS57+AT57 -> 101047.43 | AV57: 8 | AW57: =+AV57*$F$1 -> 27.2 | AY57: =+AV57*$AW$93 -> 59420.285 | AZ57: =+AW57*$AW$92 -> 63948.291 | BA57: =+AY57+AZ57 -> 123368.58 | BB57: 7 | BC57: =+BB57*$F$1 -> 23.8 | BD57: =+BB57*$BC$93 -> 51992.75 | BE57: =+BC57*$BC$92 -> 53354.789 | BF57: =+BD57+BE57 -> 105347.54 | BG57: 8 | BH57: =+BG57*$F$1 -> 27.2 | BI57: =+BG57*$BH$93 -> 59423.5 | BJ57: =+BH57*$BH$92 -> 57515.611 | BK57: =+BJ57+BI57 -> 116939.11 | BL57: 9 | BM57: =+BL57*$F$1 -> 30.6 | BN57: =+BL57*$BM$93 -> 66851.438 | BO57: =+BM57*$BM$92 -> 66014.046 | BP57: =+BN57+BO57 -> 132865.48
A58: 2017 TORRE B | B58: 202 | C58: 5 | E58: =+C58*3 -> 15 | F58: =+C58*$E$93 -> 35782.018 | G58: =+E58*E$92 -> #REF! | H58: =+F58+G58 -> #REF! | I58: 5 | K58: =+I58*$F$1 -> 17 | L58: =+I58*$K$93 -> 35782.018 | M58: =+K58*$K$92 -> 34500.111 | N58: =+M58+L58 -> 70282.129 | O58: 5 | Q58: =+O58*$F$1 -> 17 | R58: =+O58*$Q$93 -> 35842.85 | S58: =+Q58*$Q$92 -> 37572.438 | T58: =+S58+R58 -> 73415.289 | U58: 4 | V58: =+U58*$F$1 -> 13.6 | W58: =+U58*$V$93 -> 28674.28 | X58: =+V58*$V$92 -> 31893.484 | Y58: =+X58+W58 -> 60567.764 | Z58: 4 | AA58: =+Z58*$F$1 -> 13.6 | AB58: =+Z58*$AB$93 -> 30042.896 | AC58: =+AA58*$AB$92 -> 27972.431 | AD58: =+AC58+AB58 -> 58015.326 | AE58: 5 | AF58: =+AE58*$F$1 -> 17 | AG58: =+AE58*$AF$93 -> 37553.619 | AH58: =+AF58*$AF$92 -> 35826.068 | AI58: =+AH58+AG58 -> 73379.687 | AJ58: 5 | AK58: =+AJ58*$F$1 -> 17 | AM58: =+AJ58*$AK$93 -> 37136.919 | AN58: =+AK58*$AK$92 -> 36600.13 | AO58: =+AM58+AN58 -> 73737.049 | AP58: 5 | AQ58: =+AP58*$F$1 -> 17 | AS58: =+AP58*$AQ$93 -> 37136.919 | AT58: =+AQ58*$AQ$92 -> 35039.817 | AU58: =+AS58+AT58 -> 72176.736 | AV58: 5 | AW58: =+AV58*$F$1 -> 17 | AY58: =+AV58*$AW$93 -> 37137.678 | AZ58: =+AW58*$AW$92 -> 39967.682 | BA58: =+AY58+AZ58 -> 77105.361 | BB58: 4 | BC58: =+BB58*$F$1 -> 13.6 | BD58: =+BB58*$BC$93 -> 29710.143 | BE58: =+BC58*$BC$92 -> 30488.451 | BF58: =+BD58+BE58 -> 60198.594 | BG58: 3 | BH58: =+BG58*$F$1 -> 10.2 | BI58: =+BG58*$BH$93 -> 22283.812 | BJ58: =+BH58*$BH$92 -> 21568.354 | BK58: =+BJ58+BI58 -> 43852.167 | BL58: 6 | BM58: =+BL58*$F$1 -> 20.4 | BN58: =+BL58*$BM$93 -> 44567.625 | BO58: =+BM58*$BM$92 -> 44009.364 | BP58: =+BN58+BO58 -> 88576.989
A59: 2017 TORRE B | B59: 203 | C59: 4 | E59: =+C59*3 -> 12 | F59: =+C59*$E$93 -> 28625.614 | G59: =+E59*E$92 -> #REF! | H59: =+F59+G59 -> #REF! | I59: 6 | K59: =+I59*$F$1 -> 20.4 | L59: =+I59*$K$93 -> 42938.421 | M59: =+K59*$K$92 -> 41400.134 | N59: =+M59+L59 -> 84338.555 | O59: 6 | Q59: =+O59*$F$1 -> 20.4 | R59: =+O59*$Q$93 -> 43011.42 | S59: =+Q59*$Q$92 -> 45086.926 | T59: =+S59+R59 -> 88098.346 | U59: 6 | V59: =+U59*$F$1 -> 20.4 | W59: =+U59*$V$93 -> 43011.42 | X59: =+V59*$V$92 -> 47840.227 | Y59: =+X59+W59 -> 90851.647 | Z59: 4 | AA59: =+Z59*$F$1 -> 13.6 | AB59: =+Z59*$AB$93 -> 30042.896 | AC59: =+AA59*$AB$92 -> 27972.431 | AD59: =+AC59+AB59 -> 58015.326 | AE59: 5 | AF59: =+AE59*$F$1 -> 17 | AG59: =+AE59*$AF$93 -> 37553.619 | AH59: =+AF59*$AF$92 -> 35826.068 | AI59: =+AH59+AG59 -> 73379.687 | AJ59: 3 | AK59: =+AJ59*$F$1 -> 10.2 | AM59: =+AJ59*$AK$93 -> 22282.152 | AN59: =+AK59*$AK$92 -> 21960.078 | AO59: =+AM59+AN59 -> 44242.23 | AP59: 3 | AQ59: =+AP59*$F$1 -> 10.2 | AS59: =+AP59*$AQ$93 -> 22282.152 | AT59: =+AQ59*$AQ$92 -> 21023.89 | AU59: =+AS59+AT59 -> 43306.042 | AV59: 5 | AW59: =+AV59*$F$1 -> 17 | AY59: =+AV59*$AW$93 -> 37137.678 | AZ59: =+AW59*$AW$92 -> 39967.682 | BA59: =+AY59+AZ59 -> 77105.361 | BB59: 4 | BC59: =+BB59*$F$1 -> 13.6 | BD59: =+BB59*$BC$93 -> 29710.143 | BE59: =+BC59*$BC$92 -> 30488.451 | BF59: =+BD59+BE59 -> 60198.594 | BG59: 5 | BH59: =+BG59*$F$1 -> 17 | BI59: =+BG59*$BH$93 -> 37139.688 | BJ59: =+BH59*$BH$92 -> 35947.257 | BK59: =+BJ59+BI59 -> 73086.944 | BL59: 5 | BM59: =+BL59*$F$1 -> 17 | BN59: =+BL59*$BM$93 -> 37139.688 | BO59: =+BM59*$BM$92 -> 36674.47 | BP59: =+BN59+BO59 -> 73814.158
A60: 2017 TORRE B | B60: 204 | C60: 0 | E60: =+C60*3 -> 0 | F60: =+C60*$E$93 -> 0 | G60: =+E60*E$92 -> #REF! | H60: =+F60+G60 -> #REF! | I60: 1 | K60: =+I60*$F$1 -> 3.4 | L60: =+I60*$K$93 -> 7156.4036 | M60: =+K60*$K$92 -> 6900.0223 | N60: =+M60+L60 -> 14056.426 | O60: 0 | Q60: =+O60*$F$1 -> 0 | R60: =+O60*$Q$93 -> 0 | S60: =+Q60*$Q$92 -> 0 | T60: =+S60+R60 -> 0 | U60: 1 | V60: =+U60*$F$1 -> 3.4 | W60: =+U60*$V$93 -> 7168.57 | X60: =+V60*$V$92 -> 7973.3711 | Y60: =+X60+W60 -> 15141.941 | Z60: 1 | AA60: =+Z60*$F$1 -> 3.4 | AB60: =+Z60*$AB$93 -> 7510.7239 | AC60: =+AA60*$AB$92 -> 6993.1076 | AD60: =+AC60+AB60 -> 14503.832 | AE60: 0 | AF60: =+AE60*$F$1 -> 0 | AG60: =+AE60*$AF$93 -> 0 | AH60: =+AF60*$AF$92 -> 0 | AI60: =+AH60+AG60 -> 0 | AJ60: 1 | AK60: =+AJ60*$F$1 -> 3.4 | AM60: =+AJ60*$AK$93 -> 7427.3839 | AN60: =+AK60*$AK$92 -> 7320.026 | AO60: =+AM60+AN60 -> 14747.41 | AP60: 0 | AQ60: =+AP60*$F$1 -> 0 | AS60: =+AP60*$AQ$93 -> 0 | AT60: =+AQ60*$AQ$92 -> 0 | AU60: =+AS60+AT60 -> 0 | AV60: 1 | AW60: =+AV60*$F$1 -> 3.4 | AY60: =+AV60*$AW$93 -> 7427.5357 | AZ60: =+AW60*$AW$92 -> 7993.5364 | BA60: =+AY60+AZ60 -> 15421.072 | BB60: 0 | BC60: =+BB60*$F$1 -> 0 | BD60: =+BB60*$BC$93 -> 0 | BE60: =+BC60*$BC$92 -> 0 | BF60: =+BD60+BE60 -> 0 | BG60: 0 | BH60: =+BG60*$F$1 -> 0 | BI60: =+BG60*$BH$93 -> 0 | BJ60: =+BH60*$BH$92 -> 0 | BK60: =+BJ60+BI60 -> 0 | BL60: 1 | BM60: =+BL60*$F$1 -> 3.4 | BN60: =+BL60*$BM$93 -> 7427.9375 | BO60: =+BM60*$BM$92 -> 7334.894 | BP60: =+BN60+BO60 -> 14762.832
A61: 2017 TORRE B | B61: 301 | C61: 5 | E61: =+C61*3 -> 15 | F61: =+C61*$E$93 -> 35782.018 | G61: =+E61*E$92 -> #REF! | H61: =+F61+G61 -> #REF! | I61: 5 | K61: =+I61*$F$1 -> 17 | L61: =+I61*$K$93 -> 35782.018 | M61: =+K61*$K$92 -> 34500.111 | N61: =+M61+L61 -> 70282.129 | O61: 4 | Q61: =+O61*$F$1 -> 13.6 | R61: =+O61*$Q$93 -> 28674.28 | S61: =+Q61*$Q$92 -> 30057.951 | T61: =+S61+R61 -> 58732.231 | U61: 6 | V61: =+U61*$F$1 -> 20.4 | W61: =+U61*$V$93 -> 43011.42 | X61: =+V61*$V$92 -> 47840.227 | Y61: =+X61+W61 -> 90851.647 | Z61: 4 | AA61: =+Z61*$F$1 -> 13.6 | AB61: =+Z61*$AB$93 -> 30042.896 | AC61: =+AA61*$AB$92 -> 27972.431 | AD61: =+AC61+AB61 -> 58015.326 | AE61: 5 | AF61: =+AE61*$F$1 -> 17 | AG61: =+AE61*$AF$93 -> 37553.619 | AH61: =+AF61*$AF$92 -> 35826.068 | AI61: =+AH61+AG61 -> 73379.687 | AJ61: 3 | AK61: =+AJ61*$F$1 -> 10.2 | AM61: =+AJ61*$AK$93 -> 22282.152 | AN61: =+AK61*$AK$92 -> 21960.078 | AO61: =+AM61+AN61 -> 44242.23 | AP61: 5 | AQ61: =+AP61*$F$1 -> 17 | AS61: =+AP61*$AQ$93 -> 37136.919 | AT61: =+AQ61*$AQ$92 -> 35039.817 | AU61: =+AS61+AT61 -> 72176.736 | AV61: 7 | AW61: =+AV61*$F$1 -> 23.8 | AY61: =+AV61*$AW$93 -> 51992.75 | AZ61: =+AW61*$AW$92 -> 55954.755 | BA61: =+AY61+AZ61 -> 107947.5 | BB61: 6 | BC61: =+BB61*$F$1 -> 20.4 | BD61: =+BB61*$BC$93 -> 44565.214 | BE61: =+BC61*$BC$92 -> 45732.677 | BF61: =+BD61+BE61 -> 90297.891 | BG61: 7 | BH61: =+BG61*$F$1 -> 23.8 | BI61: =+BG61*$BH$93 -> 51995.562 | BJ61: =+BH61*$BH$92 -> 50326.16 | BK61: =+BJ61+BI61 -> 102321.72 | BL61: 8 | BM61: =+BL61*$F$1 -> 27.2 | BN61: =+BL61*$BM$93 -> 59423.5 | BO61: =+BM61*$BM$92 -> 58679.152 | BP61: =+BN61+BO61 -> 118102.65
A62: 2017 TORRE B | B62: 302 | C62: 15 | E62: =+C62*3 -> 45 | F62: =+C62*$E$93 -> 107346.05 | G62: =+E62*E$92 -> #REF! | H62: =+F62+G62 -> #REF! | I62: 17 | K62: =+I62*$F$1 -> 57.8 | L62: =+I62*$K$93 -> 121658.86 | M62: =+K62*$K$92 -> 117300.38 | N62: =+M62+L62 -> 238959.24 | O62: 10 | Q62: =+O62*$F$1 -> 34 | R62: =+O62*$Q$93 -> 71685.7 | S62: =+Q62*$Q$92 -> 75144.877 | T62: =+S62+R62 -> 146830.58 | U62: 18 | V62: =+U62*$F$1 -> 61.2 | W62: =+U62*$V$93 -> 129034.26 | X62: =+V62*$V$92 -> 143520.68 | Y62: =+X62+W62 -> 272554.94 | Z62: 12 | AA62: =+Z62*$F$1 -> 40.8 | AB62: =+Z62*$AB$93 -> 90128.687 | AC62: =+AA62*$AB$92 -> 83917.292 | AD62: =+AC62+AB62 -> 174045.98 | AE62: 14 | AF62: =+AE62*$F$1 -> 47.6 | AG62: =+AE62*$AF$93 -> 105150.13 | AH62: =+AF62*$AF$92 -> 100312.99 | AI62: =+AH62+AG62 -> 205463.12 | AJ62: 16 | AK62: =+AJ62*$F$1 -> 54.4 | AM62: =+AJ62*$AK$93 -> 118838.14 | AN62: =+AK62*$AK$92 -> 117120.42 | AO62: =+AM62+AN62 -> 235958.56 | AP62: 17 | AQ62: =+AP62*$F$1 -> 57.8 | AS62: =+AP62*$AQ$93 -> 126265.53 | AT62: =+AQ62*$AQ$92 -> 119135.38 | AU62: =+AS62+AT62 -> 245400.9 | AV62: 17 | AW62: =+AV62*$F$1 -> 57.8 | AY62: =+AV62*$AW$93 -> 126268.11 | AZ62: =+AW62*$AW$92 -> 135890.12 | BA62: =+AY62+AZ62 -> 262158.23 | BB62: 15 | BC62: =+BB62*$F$1 -> 51 | BD62: =+BB62*$BC$93 -> 111413.04 | BE62: =+BC62*$BC$92 -> 114331.69 | BF62: =+BD62+BE62 -> 225744.73 | BG62: 10 | BH62: =+BG62*$F$1 -> 34 | BI62: =+BG62*$BH$93 -> 74279.375 | BJ62: =+BH62*$BH$92 -> 71894.514 | BK62: =+BJ62+BI62 -> 146173.89 | BL62: 0 | BM62: =+BL62*$F$1 -> 0 | BN62: =+BL62*$BM$93 -> 0 | BO62: =+BM62*$BM$92 -> 0 | BP62: =+BN62+BO62 -> 0
A63: 2017 TORRE B | B63: 303 | C63: 1 | E63: =+C63*3 -> 3 | F63: =+C63*$E$93 -> 7156.4036 | G63: =+E63*E$92 -> #REF! | H63: =+F63+G63 -> #REF! | I63: 1 | K63: =+I63*$F$1 -> 3.4 | L63: =+I63*$K$93 -> 7156.4036 | M63: =+K63*$K$92 -> 6900.0223 | N63: =+M63+L63 -> 14056.426 | O63: 0 | Q63: =+O63*$F$1 -> 0 | R63: =+O63*$Q$93 -> 0 | S63: =+Q63*$Q$92 -> 0 | T63: =+S63+R63 -> 0 | U63: 1 | V63: =+U63*$F$1 -> 3.4 | W63: =+U63*$V$93 -> 7168.57 | X63: =+V63*$V$92 -> 7973.3711 | Y63: =+X63+W63 -> 15141.941 | Z63: 1 | AA63: =+Z63*$F$1 -> 3.4 | AB63: =+Z63*$AB$93 -> 7510.7239 | AC63: =+AA63*$AB$92 -> 6993.1076 | AD63: =+AC63+AB63 -> 14503.832 | AE63: 0 | AF63: =+AE63*$F$1 -> 0 | AG63: =+AE63*$AF$93 -> 0 | AH63: =+AF63*$AF$92 -> 0 | AI63: =+AH63+AG63 -> 0 | AJ63: 1 | AK63: =+AJ63*$F$1 -> 3.4 | AM63: =+AJ63*$AK$93 -> 7427.3839 | AN63: =+AK63*$AK$92 -> 7320.026 | AO63: =+AM63+AN63 -> 14747.41 | AP63: 1 | AQ63: =+AP63*$F$1 -> 3.4 | AS63: =+AP63*$AQ$93 -> 7427.3839 | AT63: =+AQ63*$AQ$92 -> 7007.9634 | AU63: =+AS63+AT63 -> 14435.347 | AV63: 0 | AW63: =+AV63*$F$1 -> 0 | AY63: =+AV63*$AW$93 -> 0 | AZ63: =+AW63*$AW$92 -> 0 | BA63: =+AY63+AZ63 -> 0 | BB63: 1 | BC63: =+BB63*$F$1 -> 3.4 | BD63: =+BB63*$BC$93 -> 7427.5357 | BE63: =+BC63*$BC$92 -> 7622.1128 | BF63: =+BD63+BE63 -> 15049.648 | BG63: 0 | BH63: =+BG63*$F$1 -> 0 | BI63: =+BG63*$BH$93 -> 0 | BJ63: =+BH63*$BH$92 -> 0 | BK63: =+BJ63+BI63 -> 0 | BL63: 1 | BM63: =+BL63*$F$1 -> 3.4 | BN63: =+BL63*$BM$93 -> 7427.9375 | BO63: =+BM63*$BM$92 -> 7334.894 | BP63: =+BN63+BO63 -> 14762.832
A64: 2017 TORRE B | B64: 401 | C64: 20 | E64: =+C64*3 -> 60 | F64: =+C64*$E$93 -> 143128.07 | G64: =+E64*E$92 -> #REF! | H64: =+F64+G64 -> #REF! | I64: 17 | K64: =+I64*$F$1 -> 57.8 | L64: =+I64*$K$93 -> 121658.86 | M64: =+K64*$K$92 -> 117300.38 | N64: =+M64+L64 -> 238959.24 | O64: 17 | Q64: =+O64*$F$1 -> 57.8 | R64: =+O64*$Q$93 -> 121865.69 | S64: =+Q64*$Q$92 -> 127746.29 | T64: =+S64+R64 -> 249611.98 | U64: 20 | V64: =+U64*$F$1 -> 68 | W64: =+U64*$V$93 -> 143371.4 | X64: =+V64*$V$92 -> 159467.42 | Y64: =+X64+W64 -> 302838.82 | Z64: 6 | AA64: =+Z64*$F$1 -> 20.4 | AB64: =+Z64*$AB$93 -> 45064.343 | AC64: =+AA64*$AB$92 -> 41958.646 | AD64: =+AC64+AB64 -> 87022.989 | AE64: 14 | AF64: =+AE64*$F$1 -> 47.6 | AG64: =+AE64*$AF$93 -> 105150.13 | AH64: =+AF64*$AF$92 -> 100312.99 | AI64: =+AH64+AG64 -> 205463.12 | AJ64: 17 | AK64: =+AJ64*$F$1 -> 57.8 | AM64: =+AJ64*$AK$93 -> 126265.53 | AN64: =+AK64*$AK$92 -> 124440.44 | AO64: =+AM64+AN64 -> 250705.97 | AP64: 16 | AQ64: =+AP64*$F$1 -> 54.4 | AS64: =+AP64*$AQ$93 -> 118838.14 | AT64: =+AQ64*$AQ$92 -> 112127.41 | AU64: =+AS64+AT64 -> 230965.56 | AV64: 18 | AW64: =+AV64*$F$1 -> 61.2 | AY64: =+AV64*$AW$93 -> 133695.64 | AZ64: =+AW64*$AW$92 -> 143883.66 | BA64: =+AY64+AZ64 -> 277579.3 | BB64: 20 | BC64: =+BB64*$F$1 -> 68 | BD64: =+BB64*$BC$93 -> 148550.71 | BE64: =+BC64*$BC$92 -> 152442.26 | BF64: =+BD64+BE64 -> 300992.97 | BG64: 23 | BH64: =+BG64*$F$1 -> 78.2 | BI64: =+BG64*$BH$93 -> 170842.56 | BJ64: =+BH64*$BH$92 -> 165357.38 | BK64: =+BJ64+BI64 -> 336199.94 | BL64: 17 | BM64: =+BL64*$F$1 -> 57.8 | BN64: =+BL64*$BM$93 -> 126274.94 | BO64: =+BM64*$BM$92 -> 124693.2 | BP64: =+BN64+BO64 -> 250968.14
A65: 2017 TORRE B | B65: 402 | C65: 0 | E65: =+C65*3 -> 0 | F65: =+C65*$E$93 -> 0 | G65: =+E65*E$92 -> #REF! | H65: =+F65+G65 -> #REF! | I65: 0 | K65: =+I65*$F$1 -> 0 | L65: =+I65*$K$93 -> 0 | M65: =+K65*$K$92 -> 0 | N65: =+M65+L65 -> 0 | O65: 0 | Q65: =+O65*$F$1 -> 0 | R65: =+O65*$Q$93 -> 0 | S65: =+Q65*$Q$92 -> 0 | T65: =+S65+R65 -> 0 | U65: 0 | V65: =+U65*$F$1 -> 0 | W65: =+U65*$V$93 -> 0 | X65: =+V65*$V$92 -> 0 | Y65: =+X65+W65 -> 0 | Z65: 0 | AA65: =+Z65*$F$1 -> 0 | AB65: =+Z65*$AB$93 -> 0 | AC65: =+AA65*$AB$92 -> 0 | AD65: =+AC65+AB65 -> 0 | AE65: 0 | AF65: =+AE65*$F$1 -> 0 | AG65: =+AE65*$AF$93 -> 0 | AH65: =+AF65*$AF$92 -> 0 | AI65: =+AH65+AG65 -> 0 | AJ65: 0 | AK65: =+AJ65*$F$1 -> 0 | AM65: =+AJ65*$AK$93 -> 0 | AN65: =+AK65*$AK$92 -> 0 | AO65: =+AM65+AN65 -> 0 | AP65: 0 | AQ65: =+AP65*$F$1 -> 0 | AS65: =+AP65*$AQ$93 -> 0 | AT65: =+AQ65*$AQ$92 -> 0 | AU65: =+AS65+AT65 -> 0 | AV65: 0 | AW65: =+AV65*$F$1 -> 0 | AY65: =+AV65*$AW$93 -> 0 | AZ65: =+AW65*$AW$92 -> 0 | BA65: =+AY65+AZ65 -> 0 | BB65: 0 | BC65: =+BB65*$F$1 -> 0 | BD65: =+BB65*$BC$93 -> 0 | BE65: =+BC65*$BC$92 -> 0 | BF65: =+BD65+BE65 -> 0 | BG65: 0 | BH65: =+BG65*$F$1 -> 0 | BI65: =+BG65*$BH$93 -> 0 | BJ65: =+BH65*$BH$92 -> 0 | BK65: =+BJ65+BI65 -> 0 | BL65: 0 | BM65: =+BL65*$F$1 -> 0 | BN65: =+BL65*$BM$93 -> 0 | BO65: =+BM65*$BM$92 -> 0 | BP65: =+BN65+BO65 -> 0
A66: 2017 TORRE B | B66: 403 | C66: 7 | E66: =+C66*3 -> 21 | F66: =+C66*$E$93 -> 50094.825 | G66: =+E66*E$92 -> #REF! | H66: =+F66+G66 -> #REF! | I66: 5 | K66: =+I66*$F$1 -> 17 | L66: =+I66*$K$93 -> 35782.018 | M66: =+K66*$K$92 -> 34500.111 | N66: =+M66+L66 -> 70282.129 | O66: 5 | Q66: =+O66*$F$1 -> 17 | R66: =+O66*$Q$93 -> 35842.85 | S66: =+Q66*$Q$92 -> 37572.438 | T66: =+S66+R66 -> 73415.289 | U66: 9 | V66: =+U66*$F$1 -> 30.6 | W66: =+U66*$V$93 -> 64517.13 | X66: =+V66*$V$92 -> 71760.34 | Y66: =+X66+W66 -> 136277.47 | Z66: 5 | AA66: =+Z66*$F$1 -> 17 | AB66: =+Z66*$AB$93 -> 37553.619 | AC66: =+AA66*$AB$92 -> 34965.538 | AD66: =+AC66+AB66 -> 72519.158 | AE66: 6 | AF66: =+AE66*$F$1 -> 20.4 | AG66: =+AE66*$AF$93 -> 45064.343 | AH66: =+AF66*$AF$92 -> 42991.281 | AI66: =+AH66+AG66 -> 88055.624 | AJ66: 7 | AK66: =+AJ66*$F$1 -> 23.8 | AM66: =+AJ66*$AK$93 -> 51991.687 | AN66: =+AK66*$AK$92 -> 51240.182 | AO66: =+AM66+AN66 -> 103231.87 | AP66: 6 | AQ66: =+AP66*$F$1 -> 20.4 | AS66: =+AP66*$AQ$93 -> 44564.303 | AT66: =+AQ66*$AQ$92 -> 42047.78 | AU66: =+AS66+AT66 -> 86612.084 | AV66: 6 | AW66: =+AV66*$F$1 -> 20.4 | AY66: =+AV66*$AW$93 -> 44565.214 | AZ66: =+AW66*$AW$92 -> 47961.219 | BA66: =+AY66+AZ66 -> 92526.433 | BB66: 6 | BC66: =+BB66*$F$1 -> 20.4 | BD66: =+BB66*$BC$93 -> 44565.214 | BE66: =+BC66*$BC$92 -> 45732.677 | BF66: =+BD66+BE66 -> 90297.891 | BG66: 6 | BH66: =+BG66*$F$1 -> 20.4 | BI66: =+BG66*$BH$93 -> 44567.625 | BJ66: =+BH66*$BH$92 -> 43136.708 | BK66: =+BJ66+BI66 -> 87704.333 | BL66: 7 | BM66: =+BL66*$F$1 -> 23.8 | BN66: =+BL66*$BM$93 -> 51995.562 | BO66: =+BM66*$BM$92 -> 51344.258 | BP66: =+BN66+BO66 -> 103339.82
A67: 2017 TORRE B | B67: 501 | C67: 2 | E67: =+C67*3 -> 6 | F67: =+C67*$E$93 -> 14312.807 | G67: =+E67*E$92 -> #REF! | H67: =+F67+G67 -> #REF! | I67: 4 | K67: =+I67*$F$1 -> 13.6 | L67: =+I67*$K$93 -> 28625.614 | M67: =+K67*$K$92 -> 27600.089 | N67: =+M67+L67 -> 56225.703 | O67: 5 | Q67: =+O67*$F$1 -> 17 | R67: =+O67*$Q$93 -> 35842.85 | S67: =+Q67*$Q$92 -> 37572.438 | T67: =+S67+R67 -> 73415.289 | U67: 5 | V67: =+U67*$F$1 -> 17 | W67: =+U67*$V$93 -> 35842.85 | X67: =+V67*$V$92 -> 39866.855 | Y67: =+X67+W67 -> 75709.706 | Z67: 5 | AA67: =+Z67*$F$1 -> 17 | AB67: =+Z67*$AB$93 -> 37553.619 | AC67: =+AA67*$AB$92 -> 34965.538 | AD67: =+AC67+AB67 -> 72519.158 | AE67: 6 | AF67: =+AE67*$F$1 -> 20.4 | AG67: =+AE67*$AF$93 -> 45064.343 | AH67: =+AF67*$AF$92 -> 42991.281 | AI67: =+AH67+AG67 -> 88055.624 | AJ67: 6 | AK67: =+AJ67*$F$1 -> 20.4 | AM67: =+AJ67*$AK$93 -> 44564.303 | AN67: =+AK67*$AK$92 -> 43920.156 | AO67: =+AM67+AN67 -> 88484.459 | AP67: 6 | AQ67: =+AP67*$F$1 -> 20.4 | AS67: =+AP67*$AQ$93 -> 44564.303 | AT67: =+AQ67*$AQ$92 -> 42047.78 | AU67: =+AS67+AT67 -> 86612.084 | AV67: 6 | AW67: =+AV67*$F$1 -> 20.4 | AY67: =+AV67*$AW$93 -> 44565.214 | AZ67: =+AW67*$AW$92 -> 47961.219 | BA67: =+AY67+AZ67 -> 92526.433 | BB67: 6 | BC67: =+BB67*$F$1 -> 20.4 | BD67: =+BB67*$BC$93 -> 44565.214 | BE67: =+BC67*$BC$92 -> 45732.677 | BF67: =+BD67+BE67 -> 90297.891 | BG67: 3 | BH67: =+BG67*$F$1 -> 10.2 | BI67: =+BG67*$BH$93 -> 22283.812 | BJ67: =+BH67*$BH$92 -> 21568.354 | BK67: =+BJ67+BI67 -> 43852.167 | BL67: 7 | BM67: =+BL67*$F$1 -> 23.8 | BN67: =+BL67*$BM$93 -> 51995.562 | BO67: =+BM67*$BM$92 -> 51344.258 | BP67: =+BN67+BO67 -> 103339.82
A68: 2017 TORRE B | B68: 502 | C68: 3 | E68: =+C68*3 -> 9 | F68: =+C68*$E$93 -> 21469.211 | G68: =+E68*E$92 -> #REF! | H68: =+F68+G68 -> #REF! | I68: 3 | K68: =+I68*$F$1 -> 10.2 | L68: =+I68*$K$93 -> 21469.211 | M68: =+K68*$K$92 -> 20700.067 | N68: =+M68+L68 -> 42169.278 | O68: 4 | Q68: =+O68*$F$1 -> 13.6 | R68: =+O68*$Q$93 -> 28674.28 | S68: =+Q68*$Q$92 -> 30057.951 | T68: =+S68+R68 -> 58732.231 | U68: 4 | V68: =+U68*$F$1 -> 13.6 | W68: =+U68*$V$93 -> 28674.28 | X68: =+V68*$V$92 -> 31893.484 | Y68: =+X68+W68 -> 60567.764 | Z68: 3 | AA68: =+Z68*$F$1 -> 10.2 | AB68: =+Z68*$AB$93 -> 22532.172 | AC68: =+AA68*$AB$92 -> 20979.323 | AD68: =+AC68+AB68 -> 43511.495 | AE68: 5 | AF68: =+AE68*$F$1 -> 17 | AG68: =+AE68*$AF$93 -> 37553.619 | AH68: =+AF68*$AF$92 -> 35826.068 | AI68: =+AH68+AG68 -> 73379.687 | AJ68: 4 | AK68: =+AJ68*$F$1 -> 13.6 | AM68: =+AJ68*$AK$93 -> 29709.536 | AN68: =+AK68*$AK$92 -> 29280.104 | AO68: =+AM68+AN68 -> 58989.64 | AP68: 4 | AQ68: =+AP68*$F$1 -> 13.6 | AS68: =+AP68*$AQ$93 -> 29709.536 | AT68: =+AQ68*$AQ$92 -> 28031.854 | AU68: =+AS68+AT68 -> 57741.389 | AV68: 6 | AW68: =+AV68*$F$1 -> 20.4 | AY68: =+AV68*$AW$93 -> 44565.214 | AZ68: =+AW68*$AW$92 -> 47961.219 | BA68: =+AY68+AZ68 -> 92526.433 | BB68: 5 | BC68: =+BB68*$F$1 -> 17 | BD68: =+BB68*$BC$93 -> 37137.678 | BE68: =+BC68*$BC$92 -> 38110.564 | BF68: =+BD68+BE68 -> 75248.242 | BG68: 5 | BH68: =+BG68*$F$1 -> 17 | BI68: =+BG68*$BH$93 -> 37139.688 | BJ68: =+BH68*$BH$92 -> 35947.257 | BK68: =+BJ68+BI68 -> 73086.944 | BL68: 6 | BM68: =+BL68*$F$1 -> 20.4 | BN68: =+BL68*$BM$93 -> 44567.625 | BO68: =+BM68*$BM$92 -> 44009.364 | BP68: =+BN68+BO68 -> 88576.989
... A88: 2017 TORRE B | B88: 1302 | C88: 6 | E88: =+C88*3 -> 18 | F88: =+C88*$E$93 -> 42938.421 | G88: =+E88*E$92 -> #REF! | H88: =+F88+G88 -> #REF! | I88: 1 | K88: =+I88*$F$1 -> 3.4 | L88: =+I88*$K$93 -> 7156.4036 | M88: =+K88*$K$92 -> 6900.0223 | N88: =+M88+L88 -> 14056.426 | O88: 8 | Q88: =+O88*$F$1 -> 27.2 | R88: =+O88*$Q$93 -> 57348.56 | S88: =+Q88*$Q$92 -> 60115.901 | T88: =+S88+R88 -> 117464.46 | U88: 8 | V88: =+U88*$F$1 -> 27.2 | W88: =+U88*$V$93 -> 57348.56 | X88: =+V88*$V$92 -> 63786.969 | Y88: =+X88+W88 -> 121135.53 | Z88: 4 | AA88: =+Z88*$F$1 -> 13.6 | AB88: =+Z88*$AB$93 -> 30042.896 | AC88: =+AA88*$AB$92 -> 27972.431 | AD88: =+AC88+AB88 -> 58015.326 | AE88: 7 | AF88: =+AE88*$F$1 -> 23.8 | AG88: =+AE88*$AF$93 -> 52575.067 | AH88: =+AF88*$AF$92 -> 50156.495 | AI88: =+AH88+AG88 -> 102731.56 | AJ88: 6 | AK88: =+AJ88*$F$1 -> 20.4 | AM88: =+AJ88*$AK$93 -> 44564.303 | AN88: =+AK88*$AK$92 -> 43920.156 | AO88: =+AM88+AN88 -> 88484.459 | AP88: 5 | AQ88: =+AP88*$F$1 -> 17 | AS88: =+AP88*$AQ$93 -> 37136.919 | AT88: =+AQ88*$AQ$92 -> 35039.817 | AU88: =+AS88+AT88 -> 72176.736 | AV88: 7 | AW88: =+AV88*$F$1 -> 23.8 | AY88: =+AV88*$AW$93 -> 51992.75 | AZ88: =+AW88*$AW$92 -> 55954.755 | BA88: =+AY88+AZ88 -> 107947.5 | BB88: 8 | BC88: =+BB88*$F$1 -> 27.2 | BD88: =+BB88*$BC$93 -> 59420.285 | BE88: =+BC88*$BC$92 -> 60976.902 | BF88: =+BD88+BE88 -> 120397.19 | BG88: 12 | BH88: =+BG88*$F$1 -> 40.8 | BI88: =+BG88*$BH$93 -> 89135.25 | BJ88: =+BH88*$BH$92 -> 86273.417 | BK88: =+BJ88+BI88 -> 175408.67 | BL88: 0 | BM88: =+BL88*$F$1 -> 0 | BN88: =+BL88*$BM$93 -> 0 | BO88: =+BM88*$BM$92 -> 0 | BP88: =+BN88+BO88 -> 0
A89: 2017 TORRE B | C89: =SUM(C57:C88) -> 221 | E89: =SUM(E57:E88) -> 663 | F89: =SUM(F57:F88) -> 1581565.2 | G89: =SUM(G57:G88) -> #REF! | H89: =SUM(H57:H88) -> #REF! | I89: =SUM(I57:I88) -> 202 | K89: =SUM(K57:K88) -> 686.8 | L89: =SUM(L57:L88) -> 1445593.5 | M89: =SUM(M57:M88) -> 1393804.5 | N89: =SUM(N57:N88) -> 2839398 | O89: =SUM(O57:O88) -> 193 | Q89: =SUM(Q57:Q88) -> 656.2 | R89: =SUM(R57:R88) -> 1383534 | S89: =SUM(S57:S88) -> 1450296.1 | T89: =SUM(T57:T88) -> 2833830.1 | U89: =SUM(U57:U88) -> 231 | V89: =SUM(V57:V88) -> 785.4 | W89: =SUM(W57:W88) -> 1655939.7 | X89: =SUM(X57:X88) -> 1841848.7 | ... AK89: =SUM(AK57:AK88) -> 571.2 | AM89: =SUM(AM57:AM88) -> 1247800.5 | AN89: =SUM(AN57:AN88) -> 1229764.4 | AO89: =SUM(AO57:AO88) -> 2477564.9 | AP89: =SUM(AP57:AP88) -> 183 | AQ89: =SUM(AQ57:AQ88) -> 622.2 | AS89: =SUM(AS57:AS88) -> 1359211.3 | AT89: =SUM(AT57:AT88) -> 1282457.3 | AU89: =SUM(AU57:AU88) -> 2641668.6 | AV89: =SUM(AV57:AV88) -> 224 | AW89: =SUM(AW57:AW88) -> 761.6 | AY89: =SUM(AY57:AY88) -> 1663768 | AZ89: =SUM(AZ57:AZ88) -> 1790552.2 | BA89: =SUM(BA57:BA88) -> 3454320.2 | BB89: =SUM(BB57:BB88) -> 210 | BC89: =SUM(BC57:BC88) -> 714 | BD89: =SUM(BD57:BD88) -> 1559782.5 | BE89: =SUM(BE57:BE88) -> 1600643.7 | BF89: =SUM(BF57:BF88) -> 3160426.2 | ... BP89: =SUM(BP57:BP88) -> 2982092
A90: 2017 TORRE B
A91: 2017 TORRE B | C91: ENERO DE 2017 | I91: FEBRERO DE 2017 | O91: MARZO DE 2017 | U91: ABRIL DE 2017 | AA91: MAYO DE 2017 | AE91: JUNIO DE 2017 | AJ91: JULIO DE 2017 | AP91: AGOSTO DE 2017 | AV91: SEPTIEMBRE DE 2017 | BB91: OCTUBRE DE 2017 | BG91: NOVIEMBRE DE 2017 | BL91: DICIEMBRE DE 2017
A92: 2017 TORRE B | C92: VR M3 GAS | E92: =+'Vr M3 DE GAS'!#REF! -> #REF! | I92: VR M3 GAS | K92: =+'Vr M3 DE GAS'!$F$62 -> 2029.4183 | O92: VR M3 GAS | Q92: =+'Vr M3 DE GAS'!$F$63 -> 2210.1434 | U92: VR M3 GAS | V92: =+'Vr M3 DE GAS'!$F$64 -> 2345.1091 | AA92: VR M3 GAS | AB92: =+'Vr M3 DE GAS'!$F$65 -> 2056.7964 | AE92: VR M3 GAS | AF92: =+'Vr M3 DE GAS'!$F$66 -> 2107.4157 | AJ92: VR M3 GAS | AK92: =+'Vr M3 DE GAS'!$F$67 -> 2152.9488 | AP92: VR M3 GAS | AQ92: =+'Vr M3 DE GAS'!$F$68 -> 2061.1657 | AV92: VR M3 GAS | AW92: =+'Vr M3 DE GAS'!$F$69 -> 2351.0401 | BB92: VR M3 GAS | BC92: =+'Vr M3 DE GAS'!$F$70 -> 2241.7979 | BG92: VR M3 GAS | BH92: =+'Vr M3 DE GAS'!$F$71 -> 2114.5445 | BL92: VR M3 GAS | BM92: =+'Vr M3 DE GAS'!$F$72 -> 2157.3218
A93: 2017 TORRE B | C93: VR M3 AGUA | E93: =+'Vr M3 DE AGUA'!$N$4 -> 7156.4036 | I93: VR M3 AGUA | K93: =+'Vr M3 DE AGUA'!$N$4 -> 7156.4036 | O93: VR M3 AGUA | Q93: =+'Vr M3 DE AGUA'!$N$5 -> 7168.57 | U93: VR M3 AGUA | V93: =+'Vr M3 DE AGUA'!$N$5 -> 7168.57 | AA93: VR M3 AGUA | AB93: =+'Vr M3 DE AGUA'!$N$6 -> 7510.7239 | AE93: VR M3 AGUA | AF93: =+'Vr M3 DE AGUA'!$N$6 -> 7510.7239 | AJ93: VR M3 AGUA | AK93: =+'Vr M3 DE AGUA'!$N$7 -> 7427.3839 | AP93: VR M3 AGUA | AQ93: =+'Vr M3 DE AGUA'!$N$7 -> 7427.3839 | AV93: VR M3 AGUA | AW93: =+'Vr M3 DE AGUA'!$N$8 -> 7427.5357 | BB93: VR M3 AGUA | BC93: =+'Vr M3 DE AGUA'!$N$8 -> 7427.5357 | BG93: VR M3 AGUA | BH93: =+'Vr M3 DE AGUA'!N$9 -> 7427.9375 | BL93: VR M3 AGUA | BM93: =+'Vr M3 DE AGUA'!$N$9 -> 7427.9375
B97: AÑO 2017
B98: TORRE C
C99: ENERO | I99: FEBRERO | O99: MARZO | U99: ABRIL | Z99: MAYO | AE99: JUNIO | AJ99: JULIO | AP99: AGOSTO | AV99: SEPTIEMBRE | BB99: OCTUBRE | BG99: NOVIEMBRE | BL99: DICIEMBRE
C101: AGUA | E101: GAS | F101: $ AGUA | G101: $GAS | H101: $ TOTAL | I101: AGUA | K101: GAS | L101: $ AGUA | M101: $GAS | N101: $ TOTAL | O101: AGUA | Q101: GAS | R101: $ AGUA | S101: $GAS | T101: $ TOTAL | U101: AGUA | V101: GAS | W101: $ AGUA | X101: $GAS | Y101: $ TOTAL | Z101: AGUA | AA101: GAS | AB101: $ AGUA | AC101: $GAS | AD101: $ TOTAL | AE101: AGUA | AF101: GAS | AG101: $ AGUA | AH101: $GAS | AI101: $ TOTAL | AJ101: AGUA | AK101: GAS | AM101: $ AGUA | AN101: $GAS | AO101: $ TOTAL | AP101: AGUA | AQ101: GAS | AS101: $ AGUA | AT101: $GAS | AU101: $ TOTAL | AV101: AGUA | AW101: GAS | AY101: $ AGUA | AZ101: $GAS | BA101: $ TOTAL | BB101: AGUA | BC101: GAS | BD101: $ AGUA | BE101: $GAS | BF101: $ TOTAL | BG101: AGUA | BH101: GAS | BI101: $ AGUA | BJ101: $GAS | BK101: $ TOTAL | BL101: AGUA | BM101: GAS | BN101: $ AGUA | BO101: $GAS | BP101: $ TOTAL
A102: 2017 TORRE C | B102: 201 | C102: 0 | E102: =+C102*3 -> 0 | F102: =+C102*E$136 -> 0 | G102: =+E102*E$135 -> #REF! | H102: =+F102+G102 -> #REF! | I102: 1 | K102: =+I102*$F$1 -> 3.4 | L102: =+I102*K$136 -> 7156.4036 | M102: =+K102*$K$135 -> 6900.0223 | N102: =+L102+M102 -> 14056.426 | O102: 0 | Q102: =+O102*$F$1 -> 0 | R102: =+O102*Q$136 -> 0 | S102: =+Q102*$Q$135 -> 0 | T102: =+R102+S102 -> 0 | U102: 0 | V102: =+U102*$F$1 -> 0 | W102: =+U102*$V$136 -> 0 | X102: =+V102*$V$135 -> 0 | Y102: =+W102+X102 -> 0 | Z102: 1 | AA102: =+Z102*$F$1 -> 3.4 | AB102: =+Z102*$AB$136 -> 7510.7239 | AC102: =+AA102*$AB$135 -> 6993.1076 | AD102: =+AB102+AC102 -> 14503.832 | AE102: 0 | AF102: =+AE102*$F$1 -> 0 | AG102: =+AE102*$AF$136 -> 0 | AH102: =+AF102*$AF$135 -> 0 | AI102: =+AG102+AH102 -> 0 | AJ102: 0 | AK102: =+AJ102*$F$1 -> 0 | AM102: =+AJ102*$AK$136 -> 0 | AN102: =+AK102*$AK$135 -> 0 | AO102: =+AM102+AN102 -> 0 | AP102: 0 | AQ102: =+AP102*$F$1 -> 0 | AS102: =+AP102*$AQ$136 -> 0 | AT102: =+AQ102*$AQ$135 -> 0 | AU102: =+AS102+AT102 -> 0 | AV102: 0 | AW102: =+AV102*$F$1 -> 0 | AY102: =+AV102*$AW$136 -> 0 | AZ102: =+AW102*$AW$135 -> 0 | BA102: =+AY102+AZ102 -> 0 | BB102: 1 | BC102: =+BB102*$F$1 -> 3.4 | BD102: =+BB102*$BC$136 -> 7427.5357 | BE102: =+BC102*$BC$135 -> 7622.1128 | BF102: =+BD102+BE102 -> 15049.648 | BG102: 0 | BH102: =+BG102*$F$1 -> 0 | BI102: =+BG102*$BH$136 -> 0 | BJ102: =+BH102*$BH$135 -> 0 | BK102: =+BI102+BJ102 -> 0 | BL102: 0 | BM102: =+BL102*$F$1 -> 0 | BN102: =+BL102*$BM$136 -> 0 | BO102: =+BM102*$BM$135 -> 0 | BP102: =+BN102+BO102 -> 0
A103: 2017 TORRE C | B103: 202 | C103: 9 | E103: =+C103*3 -> 27 | F103: =+C103*E$136 -> 64407.632 | G103: =+E103*E$135 -> #REF! | H103: =+F103+G103 -> #REF! | I103: 9 | K103: =+I103*$F$1 -> 30.6 | L103: =+I103*K$136 -> 64407.632 | M103: =+K103*$K$135 -> 62100.2 | N103: =+L103+M103 -> 126507.83 | O103: 1 | Q103: =+O103*$F$1 -> 3.4 | R103: =+O103*Q$136 -> 7168.57 | S103: =+Q103*$Q$135 -> 7514.4877 | T103: =+R103+S103 -> 14683.058 | U103: 19 | V103: =+U103*$F$1 -> 64.6 | W103: =+U103*$V$136 -> 136202.83 | X103: =+V103*$V$135 -> 151494.05 | Y103: =+W103+X103 -> 287696.88 | Z103: 8 | AA103: =+Z103*$F$1 -> 27.2 | AB103: =+Z103*$AB$136 -> 60085.791 | AC103: =+AA103*$AB$135 -> 55944.861 | AD103: =+AB103+AC103 -> 116030.65 | AE103: 10 | AF103: =+AE103*$F$1 -> 34 | AG103: =+AE103*$AF$136 -> 75107.239 | AH103: =+AF103*$AF$135 -> 71652.135 | AI103: =+AG103+AH103 -> 146759.37 | AJ103: 10 | AK103: =+AJ103*$F$1 -> 34 | AM103: =+AJ103*$AK$136 -> 74273.839 | AN103: =+AK103*$AK$135 -> 73200.26 | AO103: =+AM103+AN103 -> 147474.1 | AP103: 10 | AQ103: =+AP103*$F$1 -> 34 | AS103: =+AP103*$AQ$136 -> 74273.839 | AT103: =+AQ103*$AQ$135 -> 70079.634 | AU103: =+AS103+AT103 -> 144353.47 | AV103: 11 | AW103: =+AV103*$F$1 -> 37.4 | AY103: =+AV103*$AW$136 -> 81702.892 | AZ103: =+AW103*$AW$135 -> 87928.901 | BA103: =+AY103+AZ103 -> 169631.79 | BB103: 9 | BC103: =+BB103*$F$1 -> 30.6 | BD103: =+BB103*$BC$136 -> 66847.821 | BE103: =+BC103*$BC$135 -> 68599.015 | BF103: =+BD103+BE103 -> 135446.84 | BG103: 9 | BH103: =+BG103*$F$1 -> 30.6 | BI103: =+BG103*$BH$136 -> 66851.438 | BJ103: =+BH103*$BH$135 -> 64705.062 | BK103: =+BI103+BJ103 -> 131556.5 | BL103: 11 | BM103: =+BL103*$F$1 -> 37.4 | BN103: =+BL103*$BM$136 -> 81707.312 | BO103: =+BM103*$BM$135 -> 80683.834 | BP103: =+BN103+BO103 -> 162391.15
A104: 2017 TORRE C | B104: 203 | C104: 10 | E104: =+C104*3 -> 30 | F104: =+C104*E$136 -> 71564.036 | G104: =+E104*E$135 -> #REF! | H104: =+F104+G104 -> #REF! | I104: 9 | K104: =+I104*$F$1 -> 30.6 | L104: =+I104*K$136 -> 64407.632 | M104: =+K104*$K$135 -> 62100.2 | N104: =+L104+M104 -> 126507.83 | O104: 9 | Q104: =+O104*$F$1 -> 30.6 | R104: =+O104*Q$136 -> 64517.13 | S104: =+Q104*$Q$135 -> 67630.389 | T104: =+R104+S104 -> 132147.52 | U104: 11 | V104: =+U104*$F$1 -> 37.4 | W104: =+U104*$V$136 -> 78854.27 | X104: =+V104*$V$135 -> 87707.082 | Y104: =+W104+X104 -> 166561.35 | Z104: 9 | AA104: =+Z104*$F$1 -> 30.6 | AB104: =+Z104*$AB$136 -> 67596.515 | AC104: =+AA104*$AB$135 -> 62937.969 | AD104: =+AB104+AC104 -> 130534.48 | AE104: 9 | AF104: =+AE104*$F$1 -> 30.6 | AG104: =+AE104*$AF$136 -> 67596.515 | AH104: =+AF104*$AF$135 -> 64486.922 | AI104: =+AG104+AH104 -> 132083.44 | AJ104: 9 | AK104: =+AJ104*$F$1 -> 30.6 | AM104: =+AJ104*$AK$136 -> 66846.455 | AN104: =+AK104*$AK$135 -> 65880.234 | AO104: =+AM104+AN104 -> 132726.69 | AP104: 7 | AQ104: =+AP104*$F$1 -> 23.8 | AS104: =+AP104*$AQ$136 -> 51991.687 | AT104: =+AQ104*$AQ$135 -> 49055.744 | AU104: =+AS104+AT104 -> 101047.43 | AV104: 11 | AW104: =+AV104*$F$1 -> 37.4 | AY104: =+AV104*$AW$136 -> 81702.892 | AZ104: =+AW104*$AW$135 -> 87928.901 | BA104: =+AY104+AZ104 -> 169631.79 | BB104: 9 | BC104: =+BB104*$F$1 -> 30.6 | BD104: =+BB104*$BC$136 -> 66847.821 | BE104: =+BC104*$BC$135 -> 68599.015 | BF104: =+BD104+BE104 -> 135446.84 | BG104: 8 | BH104: =+BG104*$F$1 -> 27.2 | BI104: =+BG104*$BH$136 -> 59423.5 | BJ104: =+BH104*$BH$135 -> 57515.611 | BK104: =+BI104+BJ104 -> 116939.11 | BL104: 10 | BM104: =+BL104*$F$1 -> 34 | BN104: =+BL104*$BM$136 -> 74279.375 | BO104: =+BM104*$BM$135 -> 73348.94 | BP104: =+BN104+BO104 -> 147628.32
A105: 2017 TORRE C | B105: 301 | C105: 7 | E105: =+C105*3 -> 21 | F105: =+C105*E$136 -> 50094.825 | G105: =+E105*E$135 -> #REF! | H105: =+F105+G105 -> #REF! | I105: 6 | K105: =+I105*$F$1 -> 20.4 | L105: =+I105*K$136 -> 42938.421 | M105: =+K105*$K$135 -> 41400.134 | N105: =+L105+M105 -> 84338.555 | O105: 6 | Q105: =+O105*$F$1 -> 20.4 | R105: =+O105*Q$136 -> 43011.42 | S105: =+Q105*$Q$135 -> 45086.926 | T105: =+R105+S105 -> 88098.346 | U105: 7 | V105: =+U105*$F$1 -> 23.8 | W105: =+U105*$V$136 -> 50179.99 | X105: =+V105*$V$135 -> 55813.598 | Y105: =+W105+X105 -> 105993.59 | Z105: 6 | AA105: =+Z105*$F$1 -> 20.4 | AB105: =+Z105*$AB$136 -> 45064.343 | AC105: =+AA105*$AB$135 -> 41958.646 | AD105: =+AB105+AC105 -> 87022.989 | AE105: 7 | AF105: =+AE105*$F$1 -> 23.8 | AG105: =+AE105*$AF$136 -> 52575.067 | AH105: =+AF105*$AF$135 -> 50156.495 | AI105: =+AG105+AH105 -> 102731.56 | AJ105: 7 | AK105: =+AJ105*$F$1 -> 23.8 | AM105: =+AJ105*$AK$136 -> 51991.687 | AN105: =+AK105*$AK$135 -> 51240.182 | AO105: =+AM105+AN105 -> 103231.87 | AP105: 6 | AQ105: =+AP105*$F$1 -> 20.4 | AS105: =+AP105*$AQ$136 -> 44564.303 | AT105: =+AQ105*$AQ$135 -> 42047.78 | AU105: =+AS105+AT105 -> 86612.084 | AV105: 7 | AW105: =+AV105*$F$1 -> 23.8 | AY105: =+AV105*$AW$136 -> 51992.75 | AZ105: =+AW105*$AW$135 -> 55954.755 | BA105: =+AY105+AZ105 -> 107947.5 | BB105: 8 | BC105: =+BB105*$F$1 -> 27.2 | BD105: =+BB105*$BC$136 -> 59420.285 | BE105: =+BC105*$BC$135 -> 60976.902 | BF105: =+BD105+BE105 -> 120397.19 | BG105: 9 | BH105: =+BG105*$F$1 -> 30.6 | BI105: =+BG105*$BH$136 -> 66851.438 | BJ105: =+BH105*$BH$135 -> 64705.062 | BK105: =+BI105+BJ105 -> 131556.5 | BL105: 9 | BM105: =+BL105*$F$1 -> 30.6 | BN105: =+BL105*$BM$136 -> 66851.438 | BO105: =+BM105*$BM$135 -> 66014.046 | BP105: =+BN105+BO105 -> 132865.48
A106: 2017 TORRE C | B106: 302 | C106: 4 | E106: =+C106*3 -> 12 | F106: =+C106*E$136 -> 28625.614 | G106: =+E106*E$135 -> #REF! | H106: =+F106+G106 -> #REF! | I106: 7 | K106: =+I106*$F$1 -> 23.8 | L106: =+I106*K$136 -> 50094.825 | M106: =+K106*$K$135 -> 48300.156 | N106: =+L106+M106 -> 98394.981 | O106: 1 | Q106: =+O106*$F$1 -> 3.4 | R106: =+O106*Q$136 -> 7168.57 | S106: =+Q106*$Q$135 -> 7514.4877 | T106: =+R106+S106 -> 14683.058 | U106: 2 | V106: =+U106*$F$1 -> 6.8 | W106: =+U106*$V$136 -> 14337.14 | X106: =+V106*$V$135 -> 15946.742 | Y106: =+W106+X106 -> 30283.882 | Z106: 3 | AA106: =+Z106*$F$1 -> 10.2 | AB106: =+Z106*$AB$136 -> 22532.172 | AC106: =+AA106*$AB$135 -> 20979.323 | AD106: =+AB106+AC106 -> 43511.495 | AE106: 4 | AF106: =+AE106*$F$1 -> 13.6 | AG106: =+AE106*$AF$136 -> 30042.896 | AH106: =+AF106*$AF$135 -> 28660.854 | AI106: =+AG106+AH106 -> 58703.75 | AJ106: 4 | AK106: =+AJ106*$F$1 -> 13.6 | AM106: =+AJ106*$AK$136 -> 29709.536 | AN106: =+AK106*$AK$135 -> 29280.104 | AO106: =+AM106+AN106 -> 58989.64 | AP106: 3 | AQ106: =+AP106*$F$1 -> 10.2 | AS106: =+AP106*$AQ$136 -> 22282.152 | AT106: =+AQ106*$AQ$135 -> 21023.89 | AU106: =+AS106+AT106 -> 43306.042 | AV106: 5 | AW106: =+AV106*$F$1 -> 17 | AY106: =+AV106*$AW$136 -> 37137.678 | AZ106: =+AW106*$AW$135 -> 39967.682 | BA106: =+AY106+AZ106 -> 77105.361 | BB106: 4 | BC106: =+BB106*$F$1 -> 13.6 | BD106: =+BB106*$BC$136 -> 29710.143 | BE106: =+BC106*$BC$135 -> 30488.451 | BF106: =+BD106+BE106 -> 60198.594 | BG106: 4 | BH106: =+BG106*$F$1 -> 13.6 | BI106: =+BG106*$BH$136 -> 29711.75 | BJ106: =+BH106*$BH$135 -> 28757.806 | BK106: =+BI106+BJ106 -> 58469.556 | BL106: 3 | BM106: =+BL106*$F$1 -> 10.2 | BN106: =+BL106*$BM$136 -> 22283.812 | BO106: =+BM106*$BM$135 -> 22004.682 | BP106: =+BN106+BO106 -> 44288.495
A107: 2017 TORRE C | B107: 303 | C107: 8 | E107: =+C107*3 -> 24 | F107: =+C107*E$136 -> 57251.229 | G107: =+E107*E$135 -> #REF! | H107: =+F107+G107 -> #REF! | I107: 4 | K107: =+I107*$F$1 -> 13.6 | L107: =+I107*K$136 -> 28625.614 | M107: =+K107*$K$135 -> 27600.089 | N107: =+L107+M107 -> 56225.703 | O107: 7 | Q107: =+O107*$F$1 -> 23.8 | R107: =+O107*Q$136 -> 50179.99 | S107: =+Q107*$Q$135 -> 52601.414 | T107: =+R107+S107 -> 102781.4 | U107: 8 | V107: =+U107*$F$1 -> 27.2 | W107: =+U107*$V$136 -> 57348.56 | X107: =+V107*$V$135 -> 63786.969 | Y107: =+W107+X107 -> 121135.53 | Z107: 5 | AA107: =+Z107*$F$1 -> 17 | AB107: =+Z107*$AB$136 -> 37553.619 | AC107: =+AA107*$AB$135 -> 34965.538 | AD107: =+AB107+AC107 -> 72519.158 | AE107: 16 | AF107: =+AE107*$F$1 -> 54.4 | AG107: =+AE107*$AF$136 -> 120171.58 | AH107: =+AF107*$AF$135 -> 114643.42 | AI107: =+AG107+AH107 -> 234815 | AJ107: 0 | AK107: =+AJ107*$F$1 -> 0 | AM107: =+AJ107*$AK$136 -> 0 | AN107: =+AK107*$AK$135 -> 0 | AO107: =+AM107+AN107 -> 0 | AP107: 5 | AQ107: =+AP107*$F$1 -> 17 | AS107: =+AP107*$AQ$136 -> 37136.919 | AT107: =+AQ107*$AQ$135 -> 35039.817 | AU107: =+AS107+AT107 -> 72176.736 | AV107: 7 | AW107: =+AV107*$F$1 -> 23.8 | AY107: =+AV107*$AW$136 -> 51992.75 | AZ107: =+AW107*$AW$135 -> 55954.755 | BA107: =+AY107+AZ107 -> 107947.5 | BB107: 7 | BC107: =+BB107*$F$1 -> 23.8 | BD107: =+BB107*$BC$136 -> 51992.75 | BE107: =+BC107*$BC$135 -> 53354.789 | BF107: =+BD107+BE107 -> 105347.54 | BG107: 9 | BH107: =+BG107*$F$1 -> 30.6 | BI107: =+BG107*$BH$136 -> 66851.438 | BJ107: =+BH107*$BH$135 -> 64705.062 | BK107: =+BI107+BJ107 -> 131556.5 | BL107: 8 | BM107: =+BL107*$F$1 -> 27.2 | BN107: =+BL107*$BM$136 -> 59423.5 | BO107: =+BM107*$BM$135 -> 58679.152 | BP107: =+BN107+BO107 -> 118102.65
A108: 2017 TORRE C | B108: 401 | C108: 5 | E108: =+C108*3 -> 15 | F108: =+C108*E$136 -> 35782.018 | G108: =+E108*E$135 -> #REF! | H108: =+F108+G108 -> #REF! | I108: 4 | K108: =+I108*$F$1 -> 13.6 | L108: =+I108*K$136 -> 28625.614 | M108: =+K108*$K$135 -> 27600.089 | N108: =+L108+M108 -> 56225.703 | O108: 5 | Q108: =+O108*$F$1 -> 17 | R108: =+O108*Q$136 -> 35842.85 | S108: =+Q108*$Q$135 -> 37572.438 | T108: =+R108+S108 -> 73415.289 | U108: 6 | V108: =+U108*$F$1 -> 20.4 | W108: =+U108*$V$136 -> 43011.42 | X108: =+V108*$V$135 -> 47840.227 | Y108: =+W108+X108 -> 90851.647 | Z108: 5 | AA108: =+Z108*$F$1 -> 17 | AB108: =+Z108*$AB$136 -> 37553.619 | AC108: =+AA108*$AB$135 -> 34965.538 | AD108: =+AB108+AC108 -> 72519.158 | AE108: 4 | AF108: =+AE108*$F$1 -> 13.6 | AG108: =+AE108*$AF$136 -> 30042.896 | AH108: =+AF108*$AF$135 -> 28660.854 | AI108: =+AG108+AH108 -> 58703.75 | AJ108: 6 | AK108: =+AJ108*$F$1 -> 20.4 | AM108: =+AJ108*$AK$136 -> 44564.303 | AN108: =+AK108*$AK$135 -> 43920.156 | AO108: =+AM108+AN108 -> 88484.459 | AP108: 4 | AQ108: =+AP108*$F$1 -> 13.6 | AS108: =+AP108*$AQ$136 -> 29709.536 | AT108: =+AQ108*$AQ$135 -> 28031.854 | AU108: =+AS108+AT108 -> 57741.389 | AV108: 4 | AW108: =+AV108*$F$1 -> 13.6 | AY108: =+AV108*$AW$136 -> 29710.143 | AZ108: =+AW108*$AW$135 -> 31974.146 | BA108: =+AY108+AZ108 -> 61684.288 | BB108: 6 | BC108: =+BB108*$F$1 -> 20.4 | BD108: =+BB108*$BC$136 -> 44565.214 | BE108: =+BC108*$BC$135 -> 45732.677 | BF108: =+BD108+BE108 -> 90297.891 | BG108: 5 | BH108: =+BG108*$F$1 -> 17 | BI108: =+BG108*$BH$136 -> 37139.688 | BJ108: =+BH108*$BH$135 -> 35947.257 | BK108: =+BI108+BJ108 -> 73086.944 | BL108: 5 | BM108: =+BL108*$F$1 -> 17 | BN108: =+BL108*$BM$136 -> 37139.688 | BO108: =+BM108*$BM$135 -> 36674.47 | BP108: =+BN108+BO108 -> 73814.158
A109: 2017 TORRE C | B109: 402 | C109: 12 | E109: =+C109*3 -> 36 | F109: =+C109*E$136 -> 85876.843 | G109: =+E109*E$135 -> #REF! | H109: =+F109+G109 -> #REF! | I109: 7 | K109: =+I109*$F$1 -> 23.8 | L109: =+I109*K$136 -> 50094.825 | M109: =+K109*$K$135 -> 48300.156 | N109: =+L109+M109 -> 98394.981 | O109: 9 | Q109: =+O109*$F$1 -> 30.6 | R109: =+O109*Q$136 -> 64517.13 | S109: =+Q109*$Q$135 -> 67630.389 | T109: =+R109+S109 -> 132147.52 | U109: 12 | V109: =+U109*$F$1 -> 40.8 | W109: =+U109*$V$136 -> 86022.84 | X109: =+V109*$V$135 -> 95680.453 | Y109: =+W109+X109 -> 181703.29 | Z109: 11 | AA109: =+Z109*$F$1 -> 37.4 | AB109: =+Z109*$AB$136 -> 82617.963 | AC109: =+AA109*$AB$135 -> 76924.184 | AD109: =+AB109+AC109 -> 159542.15 | AE109: 12 | AF109: =+AE109*$F$1 -> 40.8 | AG109: =+AE109*$AF$136 -> 90128.687 | AH109: =+AF109*$AF$135 -> 85982.562 | AI109: =+AG109+AH109 -> 176111.25 | AJ109: 10 | AK109: =+AJ109*$F$1 -> 34 | AM109: =+AJ109*$AK$136 -> 74273.839 | AN109: =+AK109*$AK$135 -> 73200.26 | AO109: =+AM109+AN109 -> 147474.1 | AP109: 8 | AQ109: =+AP109*$F$1 -> 27.2 | AS109: =+AP109*$AQ$136 -> 59419.071 | AT109: =+AQ109*$AQ$135 -> 56063.707 | AU109: =+AS109+AT109 -> 115482.78 | AV109: 13 | AW109: =+AV109*$F$1 -> 44.2 | AY109: =+AV109*$AW$136 -> 96557.964 | AZ109: =+AW109*$AW$135 -> 103915.97 | BA109: =+AY109+AZ109 -> 200473.94 | BB109: 10 | BC109: =+BB109*$F$1 -> 34 | BD109: =+BB109*$BC$136 -> 74275.357 | BE109: =+BC109*$BC$135 -> 76221.128 | BF109: =+BD109+BE109 -> 150496.48 | BG109: 0 | BH109: =+BG109*$F$1 -> 0 | BI109: =+BG109*$BH$136 -> 0 | BJ109: =+BH109*$BH$135 -> 0 | BK109: =+BI109+BJ109 -> 0 | BL109: 0 | BM109: =+BL109*$F$1 -> 0 | BN109: =+BL109*$BM$136 -> 0 | BO109: =+BM109*$BM$135 -> 0 | BP109: =+BN109+BO109 -> 0
A110: 2017 TORRE C | B110: 403 | C110: 11 | E110: =+C110*3 -> 33 | F110: =+C110*E$136 -> 78720.439 | G110: =+E110*E$135 -> #REF! | H110: =+F110+G110 -> #REF! | I110: 10 | K110: =+I110*$F$1 -> 34 | L110: =+I110*K$136 -> 71564.036 | M110: =+K110*$K$135 -> 69000.223 | N110: =+L110+M110 -> 140564.26 | O110: 9 | Q110: =+O110*$F$1 -> 30.6 | R110: =+O110*Q$136 -> 64517.13 | S110: =+Q110*$Q$135 -> 67630.389 | T110: =+R110+S110 -> 132147.52 | U110: 11 | V110: =+U110*$F$1 -> 37.4 | W110: =+U110*$V$136 -> 78854.27 | X110: =+V110*$V$135 -> 87707.082 | Y110: =+W110+X110 -> 166561.35 | Z110: 6 | AA110: =+Z110*$F$1 -> 20.4 | AB110: =+Z110*$AB$136 -> 45064.343 | AC110: =+AA110*$AB$135 -> 41958.646 | AD110: =+AB110+AC110 -> 87022.989 | AE110: 9 | AF110: =+AE110*$F$1 -> 30.6 | AG110: =+AE110*$AF$136 -> 67596.515 | AH110: =+AF110*$AF$135 -> 64486.922 | AI110: =+AG110+AH110 -> 132083.44 | AJ110: 9 | AK110: =+AJ110*$F$1 -> 30.6 | AM110: =+AJ110*$AK$136 -> 66846.455 | AN110: =+AK110*$AK$135 -> 65880.234 | AO110: =+AM110+AN110 -> 132726.69 | AP110: 9 | AQ110: =+AP110*$F$1 -> 30.6 | AS110: =+AP110*$AQ$136 -> 66846.455 | AT110: =+AQ110*$AQ$135 -> 63071.671 | AU110: =+AS110+AT110 -> 129918.13 | AV110: 9 | AW110: =+AV110*$F$1 -> 30.6 | AY110: =+AV110*$AW$136 -> 66847.821 | AZ110: =+AW110*$AW$135 -> 71941.828 | BA110: =+AY110+AZ110 -> 138789.65 | BB110: 10 | BC110: =+BB110*$F$1 -> 34 | BD110: =+BB110*$BC$136 -> 74275.357 | BE110: =+BC110*$BC$135 -> 76221.128 | BF110: =+BD110+BE110 -> 150496.48 | BG110: 6 | BH110: =+BG110*$F$1 -> 20.4 | BI110: =+BG110*$BH$136 -> 44567.625 | BJ110: =+BH110*$BH$135 -> 43136.708 | BK110: =+BI110+BJ110 -> 87704.333 | BL110: 12 | BM110: =+BL110*$F$1 -> 40.8 | BN110: =+BL110*$BM$136 -> 89135.25 | BO110: =+BM110*$BM$135 -> 88018.728 | BP110: =+BN110+BO110 -> 177153.98
A111: 2017 TORRE C | B111: 501 | C111: 4 | E111: =+C111*3 -> 12 | F111: =+C111*E$136 -> 28625.614 | G111: =+E111*E$135 -> #REF! | H111: =+F111+G111 -> #REF! | I111: 3 | K111: =+I111*$F$1 -> 10.2 | L111: =+I111*K$136 -> 21469.211 | M111: =+K111*$K$135 -> 20700.067 | N111: =+L111+M111 -> 42169.278 | O111: 4 | Q111: =+O111*$F$1 -> 13.6 | R111: =+O111*Q$136 -> 28674.28 | S111: =+Q111*$Q$135 -> 30057.951 | T111: =+R111+S111 -> 58732.231 | U111: 5 | V111: =+U111*$F$1 -> 17 | W111: =+U111*$V$136 -> 35842.85 | X111: =+V111*$V$135 -> 39866.855 | Y111: =+W111+X111 -> 75709.706 | Z111: 2 | AA111: =+Z111*$F$1 -> 6.8 | AB111: =+Z111*$AB$136 -> 15021.448 | AC111: =+AA111*$AB$135 -> 13986.215 | AD111: =+AB111+AC111 -> 29007.663 | AE111: 3 | AF111: =+AE111*$F$1 -> 10.2 | AG111: =+AE111*$AF$136 -> 22532.172 | AH111: =+AF111*$AF$135 -> 21495.641 | AI111: =+AG111+AH111 -> 44027.812 | AJ111: 3 | AK111: =+AJ111*$F$1 -> 10.2 | AM111: =+AJ111*$AK$136 -> 22282.152 | AN111: =+AK111*$AK$135 -> 21960.078 | AO111: =+AM111+AN111 -> 44242.23 | AP111: 3 | AQ111: =+AP111*$F$1 -> 10.2 | AS111: =+AP111*$AQ$136 -> 22282.152 | AT111: =+AQ111*$AQ$135 -> 21023.89 | AU111: =+AS111+AT111 -> 43306.042 | AV111: 2 | AW111: =+AV111*$F$1 -> 6.8 | AY111: =+AV111*$AW$136 -> 14855.071 | AZ111: =+AW111*$AW$135 -> 15987.073 | BA111: =+AY111+AZ111 -> 30842.144 | BB111: 3 | BC111: =+BB111*$F$1 -> 10.2 | BD111: =+BB111*$BC$136 -> 22282.607 | BE111: =+BC111*$BC$135 -> 22866.338 | BF111: =+BD111+BE111 -> 45148.945 | BG111: 2 | BH111: =+BG111*$F$1 -> 6.8 | BI111: =+BG111*$BH$136 -> 14855.875 | BJ111: =+BH111*$BH$135 -> 14378.903 | BK111: =+BI111+BJ111 -> 29234.778 | BL111: 2 | BM111: =+BL111*$F$1 -> 6.8 | BN111: =+BL111*$BM$136 -> 14855.875 | BO111: =+BM111*$BM$135 -> 14669.788 | BP111: =+BN111+BO111 -> 29525.663
A112: 2017 TORRE C | B112: 502 | C112: 2 | E112: =+C112*3 -> 6 | F112: =+C112*E$136 -> 14312.807 | G112: =+E112*E$135 -> #REF! | H112: =+F112+G112 -> #REF! | I112: 2 | K112: =+I112*$F$1 -> 6.8 | L112: =+I112*K$136 -> 14312.807 | M112: =+K112*$K$135 -> 13800.045 | N112: =+L112+M112 -> 28112.852 | O112: 1 | Q112: =+O112*$F$1 -> 3.4 | R112: =+O112*Q$136 -> 7168.57 | S112: =+Q112*$Q$135 -> 7514.4877 | T112: =+R112+S112 -> 14683.058 | U112: 2 | V112: =+U112*$F$1 -> 6.8 | W112: =+U112*$V$136 -> 14337.14 | X112: =+V112*$V$135 -> 15946.742 | Y112: =+W112+X112 -> 30283.882 | Z112: 1 | AA112: =+Z112*$F$1 -> 3.4 | AB112: =+Z112*$AB$136 -> 7510.7239 | AC112: =+AA112*$AB$135 -> 6993.1076 | AD112: =+AB112+AC112 -> 14503.832 | AE112: 2 | AF112: =+AE112*$F$1 -> 6.8 | AG112: =+AE112*$AF$136 -> 15021.448 | AH112: =+AF112*$AF$135 -> 14330.427 | AI112: =+AG112+AH112 -> 29351.875 | AJ112: 2 | AK112: =+AJ112*$F$1 -> 6.8 | AM112: =+AJ112*$AK$136 -> 14854.768 | AN112: =+AK112*$AK$135 -> 14640.052 | AO112: =+AM112+AN112 -> 29494.82 | AP112: 2 | AQ112: =+AP112*$F$1 -> 6.8 | AS112: =+AP112*$AQ$136 -> 14854.768 | AT112: =+AQ112*$AQ$135 -> 14015.927 | AU112: =+AS112+AT112 -> 28870.695 | AV112: 3 | AW112: =+AV112*$F$1 -> 10.2 | AY112: =+AV112*$AW$136 -> 22282.607 | AZ112: =+AW112*$AW$135 -> 23980.609 | BA112: =+AY112+AZ112 -> 46263.216 | BB112: 2 | BC112: =+BB112*$F$1 -> 6.8 | BD112: =+BB112*$BC$136 -> 14855.071 | BE112: =+BC112*$BC$135 -> 15244.226 | BF112: =+BD112+BE112 -> 30099.297 | BG112: 2 | BH112: =+BG112*$F$1 -> 6.8 | BI112: =+BG112*$BH$136 -> 14855.875 | BJ112: =+BH112*$BH$135 -> 14378.903 | BK112: =+BI112+BJ112 -> 29234.778 | BL112: 2 | BM112: =+BL112*$F$1 -> 6.8 | BN112: =+BL112*$BM$136 -> 14855.875 | BO112: =+BM112*$BM$135 -> 14669.788 | BP112: =+BN112+BO112 -> 29525.663
A113: 2017 TORRE C | B113: 503 | C113: 1 | E113: =+C113*3 -> 3 | F113: =+C113*E$136 -> 7156.4036 | G113: =+E113*E$135 -> #REF! | H113: =+F113+G113 -> #REF! | I113: 1 | K113: =+I113*$F$1 -> 3.4 | L113: =+I113*K$136 -> 7156.4036 | M113: =+K113*$K$135 -> 6900.0223 | N113: =+L113+M113 -> 14056.426 | O113: 0 | Q113: =+O113*$F$1 -> 0 | R113: =+O113*Q$136 -> 0 | S113: =+Q113*$Q$135 -> 0 | T113: =+R113+S113 -> 0 | U113: 0 | V113: =+U113*$F$1 -> 0 | W113: =+U113*$V$136 -> 0 | X113: =+V113*$V$135 -> 0 | Y113: =+W113+X113 -> 0 | Z113: 0 | AA113: =+Z113*$F$1 -> 0 | AB113: =+Z113*$AB$136 -> 0 | AC113: =+AA113*$AB$135 -> 0 | AD113: =+AB113+AC113 -> 0 | AE113: 1 | AF113: =+AE113*$F$1 -> 3.4 | AG113: =+AE113*$AF$136 -> 7510.7239 | AH113: =+AF113*$AF$135 -> 7165.2135 | AI113: =+AG113+AH113 -> 14675.937 | AJ113: 1 | AK113: =+AJ113*$F$1 -> 3.4 | AM113: =+AJ113*$AK$136 -> 7427.3839 | AN113: =+AK113*$AK$135 -> 7320.026 | AO113: =+AM113+AN113 -> 14747.41 | AP113: 0 | AQ113: =+AP113*$F$1 -> 0 | AS113: =+AP113*$AQ$136 -> 0 | AT113: =+AQ113*$AQ$135 -> 0 | AU113: =+AS113+AT113 -> 0 | AV113: 0 | AW113: =+AV113*$F$1 -> 0 | AY113: =+AV113*$AW$136 -> 0 | AZ113: =+AW113*$AW$135 -> 0 | BA113: =+AY113+AZ113 -> 0 | BB113: 1 | BC113: =+BB113*$F$1 -> 3.4 | BD113: =+BB113*$BC$136 -> 7427.5357 | BE113: =+BC113*$BC$135 -> 7622.1128 | BF113: =+BD113+BE113 -> 15049.648 | BG113: 0 | BH113: =+BG113*$F$1 -> 0 | BI113: =+BG113*$BH$136 -> 0 | BJ113: =+BH113*$BH$135 -> 0 | BK113: =+BI113+BJ113 -> 0 | BL113: 0 | BM113: =+BL113*$F$1 -> 0 | BN113: =+BL113*$BM$136 -> 0 | BO113: =+BM113*$BM$135 -> 0 | BP113: =+BN113+BO113 -> 0
... A131: 2017 TORRE C | B131: 1302 | C131: 12 | E131: =+C131*3 -> 36 | F131: =+C131*E$136 -> 85876.843 | G131: =+E131*E$135 -> #REF! | H131: =+F131+G131 -> #REF! | I131: 8 | K131: =+I131*$F$1 -> 27.2 | L131: =+I131*K$136 -> 57251.229 | M131: =+K131*$K$135 -> 55200.178 | N131: =+L131+M131 -> 112451.41 | O131: 13 | Q131: =+O131*$F$1 -> 44.2 | R131: =+O131*Q$136 -> 93191.41 | S131: =+Q131*$Q$135 -> 97688.34 | T131: =+R131+S131 -> 190879.75 | U131: 16 | V131: =+U131*$F$1 -> 54.4 | W131: =+U131*$V$136 -> 114697.12 | X131: =+V131*$V$135 -> 127573.94 | Y131: =+W131+X131 -> 242271.06 | Z131: 10 | AA131: =+Z131*$F$1 -> 34 | AB131: =+Z131*$AB$136 -> 75107.239 | AC131: =+AA131*$AB$135 -> 69931.076 | AD131: =+AB131+AC131 -> 145038.32 | AE131: 13 | AF131: =+AE131*$F$1 -> 44.2 | AG131: =+AE131*$AF$136 -> 97639.411 | AH131: =+AF131*$AF$135 -> 93147.776 | AI131: =+AG131+AH131 -> 190787.19 | AJ131: 10 | AK131: =+AJ131*$F$1 -> 34 | AM131: =+AJ131*$AK$136 -> 74273.839 | AN131: =+AK131*$AK$135 -> 73200.26 | AO131: =+AM131+AN131 -> 147474.1 | AP131: 12 | AQ131: =+AP131*$F$1 -> 40.8 | AS131: =+AP131*$AQ$136 -> 89128.607 | AT131: =+AQ131*$AQ$135 -> 84095.561 | AU131: =+AS131+AT131 -> 173224.17 | AV131: 18 | AW131: =+AV131*$F$1 -> 61.2 | AY131: =+AV131*$AW$136 -> 133695.64 | AZ131: =+AW131*$AW$135 -> 143883.66 | BA131: =+AY131+AZ131 -> 277579.3 | BB131: 17 | BC131: =+BB131*$F$1 -> 57.8 | BD131: =+BB131*$BC$136 -> 126268.11 | BE131: =+BC131*$BC$135 -> 129575.92 | BF131: =+BD131+BE131 -> 255844.02 | BG131: 16 | BH131: =+BG131*$F$1 -> 54.4 | BI131: =+BG131*$BH$136 -> 118847 | BJ131: =+BH131*$BH$135 -> 115031.22 | BK131: =+BI131+BJ131 -> 233878.22 | BL131: 15 | BM131: =+BL131*$F$1 -> 51 | BN131: =+BL131*$BM$136 -> 111419.06 | BO131: =+BM131*$BM$135 -> 110023.41 | BP131: =+BN131+BO131 -> 221442.47
A132: 2017 TORRE C | C132: =SUM(C102:C131) -> 216 | E132: =SUM(E102:E131) -> 648 | F132: =SUM(F102:F131) -> 1545783.2 | G132: =SUM(G102:G131) -> #REF! | H132: =SUM(H102:H131) -> #REF! | I132: =SUM(I102:I131) -> 179 | K132: =SUM(K102:K131) -> 608.6 | L132: =SUM(L102:L131) -> 1280996.2 | M132: =SUM(M102:M131) -> 1235104 | N132: =SUM(N102:N131) -> 2516100.2 | O132: =SUM(O102:O131) -> 190 | Q132: =SUM(Q102:Q131) -> 646 | R132: =SUM(R102:R131) -> 1362028.3 | S132: =SUM(S102:S131) -> 1427752.7 | T132: =SUM(T102:T131) -> 2789781 | U132: =SUM(U102:U131) -> 256 | V132: =SUM(V102:V131) -> 870.4 | W132: =SUM(W102:W131) -> 1835153.9 | X132: =SUM(X102:X131) -> 2041183 | ... AK132: =SUM(AK102:AK131) -> 693.6 | AM132: =SUM(AM102:AM131) -> 1515186.3 | AN132: =SUM(AN102:AN131) -> 1493285.3 | AO132: =SUM(AO102:AO131) -> 3008471.6 | AP132: =SUM(AP102:AP131) -> 187 | AQ132: =SUM(AQ102:AQ131) -> 635.8 | AS132: =SUM(AS102:AS131) -> 1388920.8 | AT132: =SUM(AT102:AT131) -> 1310489.2 | AU132: =SUM(AU102:AU131) -> 2699409.9 | AV132: =SUM(AV102:AV131) -> 234 | AW132: =SUM(AW102:AW131) -> 795.6 | AY132: =SUM(AY102:AY131) -> 1738043.3 | AZ132: =SUM(AZ102:AZ131) -> 1870487.5 | BA132: =SUM(BA102:BA131) -> 3608530.9 | BB132: =SUM(BB102:BB131) -> 214 | BC132: =SUM(BC102:BC131) -> 727.6 | BD132: =SUM(BD102:BD131) -> 1589492.6 | BE132: =SUM(BE102:BE131) -> 1631132.1 | BF132: =SUM(BF102:BF131) -> 3220624.8 | ... BP132: =SUM(BP102:BP131) -> 3026380.5
A133: 2017 TORRE C
A134: 2017 TORRE C | C134: ENERO DE 2017 | I134: FEBRERO DE 2017 | O134: MARZO DE 2017 | U134: ABRIL DE 2017 | AA134: MAYO DE 2017 | AE134: JUNIO DE 2017 | AJ134: JULIO DE 2017 | AP134: AGOSTO DE 2017 | AV134: SEPTIEMBRE DE 2017 | BB134: OCTUBRE DE 2017 | BG134: NOVIEMBRE DE 2017 | BL134: DICIEMBRE DE 2017
A135: 2017 TORRE C | C135: VR M3 GAS | E135: =+'Vr M3 DE GAS'!#REF! -> #REF! | I135: VR M3 GAS | K135: =+'Vr M3 DE GAS'!$F$62 -> 2029.4183 | O135: VR M3 GAS | Q135: =+'Vr M3 DE GAS'!$F$63 -> 2210.1434 | U135: VR M3 GAS | V135: =+'Vr M3 DE GAS'!$F$64 -> 2345.1091 | AA135: VR M3 GAS | AB135: =+'Vr M3 DE GAS'!$F$65 -> 2056.7964 | AE135: VR M3 GAS | AF135: =+'Vr M3 DE GAS'!$F$66 -> 2107.4157 | AJ135: VR M3 GAS | AK135: =+'Vr M3 DE GAS'!$F$67 -> 2152.9488 | AP135: VR M3 GAS | AQ135: =+'Vr M3 DE GAS'!$F$68 -> 2061.1657 | AV135: VR M3 GAS | AW135: =+'Vr M3 DE GAS'!$F$69 -> 2351.0401 | BB135: VR M3 GAS | BC135: =+'Vr M3 DE GAS'!$F$70 -> 2241.7979 | BG135: VR M3 GAS | BH135: =+'Vr M3 DE GAS'!$F$71 -> 2114.5445 | BL135: VR M3 GAS | BM135: =+'Vr M3 DE GAS'!$F$72 -> 2157.3218
A136: 2017 TORRE C | C136: VR M3 AGUA | E136: =+'Vr M3 DE AGUA'!$N$4 -> 7156.4036 | I136: VR M3 AGUA | K136: =+'Vr M3 DE AGUA'!$N$4 -> 7156.4036 | O136: VR M3 AGUA | Q136: =+'Vr M3 DE AGUA'!$N$5 -> 7168.57 | U136: VR M3 AGUA | V136: =+'Vr M3 DE AGUA'!$N$5 -> 7168.57 | AA136: VR M3 AGUA | AB136: =+'Vr M3 DE AGUA'!$N$6 -> 7510.7239 | AE136: VR M3 AGUA | AF136: =+'Vr M3 DE AGUA'!$N$6 -> 7510.7239 | AJ136: VR M3 AGUA | AK136: =+'Vr M3 DE AGUA'!$N$7 -> 7427.3839 | AP136: VR M3 AGUA | AQ136: =+'Vr M3 DE AGUA'!$N$7 -> 7427.3839 | AV136: VR M3 AGUA | AW136: =+'Vr M3 DE AGUA'!$N$8 -> 7427.5357 | BB136: VR M3 AGUA | BC136: =+'Vr M3 DE AGUA'!$N$8 -> 7427.5357 | BG136: VR M3 AGUA | BH136: =+'Vr M3 DE AGUA'!N$9 -> 7427.9375 | BL136: VR M3 AGUA | BM136: =+'Vr M3 DE AGUA'!$N$9 -> 7427.9375
B140: 2018
B141: TORRE A
C142: ENERO | I142: FEBRERO | O142: MARZO | U142: ABRIL | Z142: MAYO | AE142: JUNIO | AJ142: JULIO | AP142: AGOSTO | AV142: SEPTIEMBRE | BB142: OCTUBRE | BG142: NOVIEMBRE | BL142: DICIEMBRE
C144: AGUA | E144: GAS | F144: $ AGUA | G144: $GAS | H144: $ TOTAL | I144: AGUA | K144: GAS | L144: $ AGUA | M144: $GAS | N144: $ TOTAL | O144: AGUA | Q144: GAS | R144: $ AGUA | S144: $GAS | T144: $ TOTAL | U144: AGUA | V144: GAS | W144: $ AGUA | X144: $GAS | Y144: $ TOTAL | Z144: AGUA | AA144: GAS | AB144: $ AGUA | AC144: $GAS | AD144: $ TOTAL | AE144: AGUA | AF144: GAS | AG144: $ AGUA | AH144: $GAS | AI144: $ TOTAL | AJ144: AGUA | AK144: GAS | AM144: $ AGUA | AN144: $GAS | AO144: $ TOTAL | AP144: AGUA | AQ144: GAS | AS144: $ AGUA | AT144: $GAS | AU144: $ TOTAL | AV144: AGUA | AW144: GAS | AY144: $ AGUA | AZ144: $GAS | BA144: $ TOTAL | BB144: AGUA | BC144: GAS | BD144: $ AGUA | BE144: $GAS | BF144: $ TOTAL | BG144: AGUA | BH144: GAS | BI144: $ AGUA | BJ144: $GAS | BK144: $ TOTAL | BL144: AGUA | BM144: GAS | BN144: $ AGUA | BO144: $GAS | BP144: $ TOTAL
A145: 2018 TORRE A | B145: 201 | C145: 18 | E145: =+C145*$F$1 -> 61.2 | F145: =+C145*$E$186 -> 134007.85 | G145: =+E145*$E$185 -> 130556.4 | H145: =+G145+F145 -> 264564.25 | I145: 19 | K145: =+I145*$F$1 -> 64.6 | L145: =+I145*$K$186 -> 141452.73 | M145: =+K145*$K$185 -> 138100.53 | N145: =+M145+L145 -> 279553.26 | O145: 23 | Q145: =+O145*$F$1 -> 78.2 | R145: =+O145*$Q$186 -> 171374.87 | S145: =+Q145*$Q$185 -> 170058.05 | T145: =+S145+R145 -> 341432.92 | U145: 19 | V145: =+U145*$F$1 -> 64.6 | W145: =+U145*$V$186 -> 141570.55 | X145: =+V145*$V$185 -> 132988.78 | Y145: =+X145+W145 -> 274559.33 | Z145: 16 | AA145: =+Z145*$F$1 -> 54.4 | AB145: =+Z145*$AB$186 -> 123890.54 | AC145: =+AA145*$AB$185 -> 115101.94 | AD145: =+AC145+AB145 -> 238992.48 | AE145: 19 | AF145: =+AE145*$F$1 -> 64.6 | AG145: =+AE145*$AF$186 -> 147120.01 | AH145: =+AF145*$AF$185 -> 143054.8 | AI145: =+AH145+AG145 -> 290174.81 | AJ145: 21 | AK145: =+AJ145*$F$1 -> 71.4 | AM145: =+AJ145*$AK$186 -> 167148.18 | AN145: =+AK145*$AK$185 -> 146459.19 | AO145: =+AN145+AM145 -> 313607.37 | AP145: 16 | AQ145: =+AP145*$F$1 -> 54.4 | AS145: =+AP145*$AQ$186 -> 127350.99 | AT145: =+AQ145*$AQ$185 -> 107552.91 | AU145: =+AT145+AS145 -> 234903.9 | AV145: 15 | AW145: =+AV145*$F$1 -> 51 | AY145: =+AV145*$AW$186 -> 119608.47 | AZ145: =+AW145*$AW$185 -> 102258.9 | BA145: =+AZ145+AY145 -> 221867.36 | BB145: 17 | BC145: =+BB145*$F$1 -> 57.8 | BD145: =+BB145*$BC$186 -> 135556.26 | BE145: =+BC145*$BC$185 -> 112578.03 | BF145: =+BE145+BD145 -> 248134.3 | BG145: 12 | BH145: =+BG145*$F$1 -> 40.8 | BI145: =+BG145*$BH$186 -> 95893.403 | BJ145: =+BH145*$BH$185 -> 85737.079 | BK145: =+BJ145+BI145 -> 181630.48 | BL145: 17 | BM145: =+BL145*$F$1 -> 57.8 | BN145: =+BL145*$BM$186 -> 135848.99 | BO145: =+BM145*$BM$185 -> 122440.87 | BP145: =+BO145+BN145 -> 258289.85
A146: 2018 TORRE A | B146: 202 | C146: 2 | E146: =+C146*$F$1 -> 6.8 | F146: =+C146*$E$186 -> 14889.761 | G146: =+E146*E$185 -> 14506.267 | H146: =+G146+F146 -> 29396.028 | I146: 1 | K146: =+I146*$F$1 -> 3.4 | L146: =+I146*$K$186 -> 7444.8804 | M146: =+K146*$K$185 -> 7268.4491 | N146: =+M146+L146 -> 14713.33 | O146: 1 | Q146: =+O146*$F$1 -> 3.4 | R146: =+O146*$Q$186 -> 7451.0814 | S146: =+Q146*$Q$185 -> 7393.8284 | T146: =+S146+R146 -> 14844.91 | U146: 1 | V146: =+U146*$F$1 -> 3.4 | W146: =+U146*$V$186 -> 7451.0814 | X146: =+V146*$V$185 -> 6999.4094 | Y146: =+X146+W146 -> 14450.491 | Z146: 1 | AA146: =+Z146*$F$1 -> 3.4 | AB146: =+Z146*$AB$186 -> 7743.1585 | AC146: =+AA146*$AB$185 -> 7193.8713 | AD146: =+AC146+AB146 -> 14937.03 | AE146: 1 | AF146: =+AE146*$F$1 -> 3.4 | AG146: =+AE146*$AF$186 -> 7743.1585 | AH146: =+AF146*$AF$185 -> 7529.1999 | AI146: =+AH146+AG146 -> 15272.358 | AJ146: 2 | AK146: =+AJ146*$F$1 -> 6.8 | AM146: =+AJ146*$AK$186 -> 15918.874 | AN146: =+AK146*$AK$185 -> 13948.495 | AO146: =+AN146+AM146 -> 29867.369 | AP146: 1 | AQ146: =+AP146*$F$1 -> 3.4 | AS146: =+AP146*$AQ$186 -> 7959.437 | AT146: =+AQ146*$AQ$185 -> 6722.0569 | AU146: =+AT146+AS146 -> 14681.494 | AV146: 1 | AW146: =+AV146*$F$1 -> 3.4 | AY146: =+AV146*$AW$186 -> 7973.8978 | AZ146: =+AW146*$AW$185 -> 6817.2597 | BA146: =+AZ146+AY146 -> 14791.158 | BB146: 2 | BC146: =+BB146*$F$1 -> 6.8 | BD146: =+BB146*$BC$186 -> 15947.796 | BE146: =+BC146*$BC$185 -> 13244.474 | BF146: =+BE146+BD146 -> 29192.27 | BG146: 1 | BH146: =+BG146*$F$1 -> 3.4 | BI146: =+BG146*$BH$186 -> 7991.1169 | BJ146: =+BH146*$BH$185 -> 7144.7566 | BK146: =+BJ146+BI146 -> 15135.873 | BL146: 1 | BM146: =+BL146*$F$1 -> 3.4 | BN146: =+BL146*$BM$186 -> 7991.1169 | BO146: =+BM146*$BM$185 -> 7202.404 | BP146: =+BO146+BN146 -> 15193.521
A147: 2018 TORRE A | B147: 203 | C147: 8 | E147: =+C147*$F$1 -> 27.2 | F147: =+C147*$E$186 -> 59559.043 | G147: =+E147*E$185 -> 58025.067 | H147: =+G147+F147 -> 117584.11 | I147: 9 | K147: =+I147*$F$1 -> 30.6 | L147: =+I147*$K$186 -> 67003.924 | M147: =+K147*$K$185 -> 65416.042 | N147: =+M147+L147 -> 132419.97 | O147: 0 | Q147: =+O147*$F$1 -> 0 | R147: =+O147*$Q$186 -> 0 | S147: =+Q147*$Q$185 -> 0 | T147: =+S147+R147 -> 0 | U147: 0 | V147: =+U147*$F$1 -> 0 | W147: =+U147*$V$186 -> 0 | X147: =+V147*$V$185 -> 0 | Y147: =+X147+W147 -> 0 | Z147: 0 | AA147: =+Z147*$F$1 -> 0 | AB147: =+Z147*$AB$186 -> 0 | AC147: =+AA147*$AB$185 -> 0 | AD147: =+AC147+AB147 -> 0 | AE147: 0 | AF147: =+AE147*$F$1 -> 0 | AG147: =+AE147*$AF$186 -> 0 | AH147: =+AF147*$AF$185 -> 0 | AI147: =+AH147+AG147 -> 0 | AJ147: 0 | AK147: =+AJ147*$F$1 -> 0 | AM147: =+AJ147*$AK$186 -> 0 | AN147: =+AK147*$AK$185 -> 0 | AO147: =+AN147+AM147 -> 0 | AP147: 0 | AQ147: =+AP147*$F$1 -> 0 | AS147: =+AP147*$AQ$186 -> 0 | AT147: =+AQ147*$AQ$185 -> 0 | AU147: =+AT147+AS147 -> 0 | AV147: 1 | AW147: =+AV147*$F$1 -> 3.4 | AY147: =+AV147*$AW$186 -> 7973.8978 | AZ147: =+AW147*$AW$185 -> 6817.2597 | BA147: =+AZ147+AY147 -> 14791.158 | BB147: 6 | BC147: =+BB147*$F$1 -> 20.4 | BD147: =+BB147*$BC$186 -> 47843.387 | BE147: =+BC147*$BC$185 -> 39733.423 | BF147: =+BE147+BD147 -> 87576.81 | BG147: 0 | BH147: =+BG147*$F$1 -> 0 | BI147: =+BG147*$BH$186 -> 0 | BJ147: =+BH147*$BH$185 -> 0 | BK147: =+BJ147+BI147 -> 0 | BL147: 0 | BM147: =+BL147*$F$1 -> 0 | BN147: =+BL147*$BM$186 -> 0 | BO147: =+BM147*$BM$185 -> 0 | BP147: =+BO147+BN147 -> 0
A148: 2018 TORRE A | B148: 301 | C148: 20 | E148: =+C148*$F$1 -> 68 | F148: =+C148*$E$186 -> 148897.61 | G148: =+E148*E$185 -> 145062.67 | H148: =+G148+F148 -> 293960.28 | I148: 14 | K148: =+I148*$F$1 -> 47.6 | L148: =+I148*$K$186 -> 104228.33 | M148: =+K148*$K$185 -> 101758.29 | N148: =+M148+L148 -> 205986.61 | O148: 11 | Q148: =+O148*$F$1 -> 37.4 | R148: =+O148*$Q$186 -> 81961.895 | S148: =+Q148*$Q$185 -> 81332.112 | T148: =+S148+R148 -> 163294.01 | U148: 14 | V148: =+U148*$F$1 -> 47.6 | W148: =+U148*$V$186 -> 104315.14 | X148: =+V148*$V$185 -> 97991.732 | Y148: =+X148+W148 -> 202306.87 | Z148: 13 | AA148: =+Z148*$F$1 -> 44.2 | AB148: =+Z148*$AB$186 -> 100661.06 | AC148: =+AA148*$AB$185 -> 93520.327 | AD148: =+AC148+AB148 -> 194181.39 | AE148: 18 | AF148: =+AE148*$F$1 -> 61.2 | AG148: =+AE148*$AF$186 -> 139376.85 | AH148: =+AF148*$AF$185 -> 135525.6 | AI148: =+AH148+AG148 -> 274902.45 | AJ148: 14 | AK148: =+AJ148*$F$1 -> 47.6 | AM148: =+AJ148*$AK$186 -> 111432.12 | AN148: =+AK148*$AK$185 -> 97639.462 | AO148: =+AN148+AM148 -> 209071.58 | AP148: 13 | AQ148: =+AP148*$F$1 -> 44.2 | AS148: =+AP148*$AQ$186 -> 103472.68 | AT148: =+AQ148*$AQ$185 -> 87386.74 | AU148: =+AT148+AS148 -> 190859.42 | AV148: 16 | AW148: =+AV148*$F$1 -> 54.4 | AY148: =+AV148*$AW$186 -> 127582.37 | AZ148: =+AW148*$AW$185 -> 109076.15 | BA148: =+AZ148+AY148 -> 236658.52 | BB148: 14 | BC148: =+BB148*$F$1 -> 47.6 | BD148: =+BB148*$BC$186 -> 111634.57 | BE148: =+BC148*$BC$185 -> 92711.321 | BF148: =+BE148+BD148 -> 204345.89 | BG148: 12 | BH148: =+BG148*$F$1 -> 40.8 | BI148: =+BG148*$BH$186 -> 95893.403 | BJ148: =+BH148*$BH$185 -> 85737.079 | BK148: =+BJ148+BI148 -> 181630.48 | BL148: 20 | BM148: =+BL148*$F$1 -> 68 | BN148: =+BL148*$BM$186 -> 159822.34 | BO148: =+BM148*$BM$185 -> 144048.08 | BP148: =+BO148+BN148 -> 303870.42
A149: 2018 TORRE A | B149: 302 | C149: 9 | E149: =+C149*$F$1 -> 30.6 | F149: =+C149*$E$186 -> 67003.924 | G149: =+E149*E$185 -> 65278.2 | H149: =+G149+F149 -> 132282.12 | I149: 9 | K149: =+I149*$F$1 -> 30.6 | L149: =+I149*$K$186 -> 67003.924 | M149: =+K149*$K$185 -> 65416.042 | N149: =+M149+L149 -> 132419.97 | O149: 9 | Q149: =+O149*$F$1 -> 30.6 | R149: =+O149*$Q$186 -> 67059.732 | S149: =+Q149*$Q$185 -> 66544.455 | T149: =+S149+R149 -> 133604.19 | U149: 10 | V149: =+U149*$F$1 -> 34 | W149: =+U149*$V$186 -> 74510.814 | X149: =+V149*$V$185 -> 69994.094 | Y149: =+X149+W149 -> 144504.91 | Z149: 10 | AA149: =+Z149*$F$1 -> 34 | AB149: =+Z149*$AB$186 -> 77431.585 | AC149: =+AA149*$AB$185 -> 71938.713 | AD149: =+AC149+AB149 -> 149370.3 | AE149: 12 | AF149: =+AE149*$F$1 -> 40.8 | AG149: =+AE149*$AF$186 -> 92917.902 | AH149: =+AF149*$AF$185 -> 90350.399 | AI149: =+AH149+AG149 -> 183268.3 | AJ149: 9 | AK149: =+AJ149*$F$1 -> 30.6 | AM149: =+AJ149*$AK$186 -> 71634.933 | AN149: =+AK149*$AK$185 -> 62768.226 | AO149: =+AN149+AM149 -> 134403.16 | AP149: 8 | AQ149: =+AP149*$F$1 -> 27.2 | AS149: =+AP149*$AQ$186 -> 63675.496 | AT149: =+AQ149*$AQ$185 -> 53776.456 | AU149: =+AT149+AS149 -> 117451.95 | AV149: 14 | AW149: =+AV149*$F$1 -> 47.6 | AY149: =+AV149*$AW$186 -> 111634.57 | AZ149: =+AW149*$AW$185 -> 95441.635 | BA149: =+AZ149+AY149 -> 207076.21 | BB149: 9 | BC149: =+BB149*$F$1 -> 30.6 | BD149: =+BB149*$BC$186 -> 71765.081 | BE149: =+BC149*$BC$185 -> 59600.135 | BF149: =+BE149+BD149 -> 131365.22 | BG149: 6 | BH149: =+BG149*$F$1 -> 20.4 | BI149: =+BG149*$BH$186 -> 47946.701 | BJ149: =+BH149*$BH$185 -> 42868.54 | BK149: =+BJ149+BI149 -> 90815.241 | BL149: 11 | BM149: =+BL149*$F$1 -> 37.4 | BN149: =+BL149*$BM$186 -> 87902.286 | BO149: =+BM149*$BM$185 -> 79226.444 | BP149: =+BO149+BN149 -> 167128.73
A150: 2018 TORRE A | B150: 401 | C150: 6 | E150: =+C150*$F$1 -> 20.4 | F150: =+C150*$E$186 -> 44669.283 | G150: =+E150*E$185 -> 43518.8 | H150: =+G150+F150 -> 88188.083 | I150: 5 | K150: =+I150*$F$1 -> 17 | L150: =+I150*$K$186 -> 37224.402 | M150: =+K150*$K$185 -> 36342.245 | N150: =+M150+L150 -> 73566.648 | O150: 6 | Q150: =+O150*$F$1 -> 20.4 | R150: =+O150*$Q$186 -> 44706.488 | S150: =+Q150*$Q$185 -> 44362.97 | T150: =+S150+R150 -> 89069.458 | U150: 4 | V150: =+U150*$F$1 -> 13.6 | W150: =+U150*$V$186 -> 29804.325 | X150: =+V150*$V$185 -> 27997.638 | Y150: =+X150+W150 -> 57801.963 | Z150: 6 | AA150: =+Z150*$F$1 -> 20.4 | AB150: =+Z150*$AB$186 -> 46458.951 | AC150: =+AA150*$AB$185 -> 43163.228 | AD150: =+AC150+AB150 -> 89622.179 | AE150: 4 | AF150: =+AE150*$F$1 -> 13.6 | AG150: =+AE150*$AF$186 -> 30972.634 | AH150: =+AF150*$AF$185 -> 30116.8 | AI150: =+AH150+AG150 -> 61089.433 | AJ150: 6 | AK150: =+AJ150*$F$1 -> 20.4 | AM150: =+AJ150*$AK$186 -> 47756.622 | AN150: =+AK150*$AK$185 -> 41845.484 | AO150: =+AN150+AM150 -> 89602.106 | AP150: 6 | AQ150: =+AP150*$F$1 -> 20.4 | AS150: =+AP150*$AQ$186 -> 47756.622 | AT150: =+AQ150*$AQ$185 -> 40332.342 | AU150: =+AT150+AS150 -> 88088.963 | AV150: 6 | AW150: =+AV150*$F$1 -> 20.4 | AY150: =+AV150*$AW$186 -> 47843.387 | AZ150: =+AW150*$AW$185 -> 40903.558 | BA150: =+AZ150+AY150 -> 88746.945 | BB150: 7 | BC150: =+BB150*$F$1 -> 23.8 | BD150: =+BB150*$BC$186 -> 55817.285 | BE150: =+BC150*$BC$185 -> 46355.661 | BF150: =+BE150+BD150 -> 102172.95 | BG150: 4 | BH150: =+BG150*$F$1 -> 13.6 | BI150: =+BG150*$BH$186 -> 31964.468 | BJ150: =+BH150*$BH$185 -> 28579.026 | BK150: =+BJ150+BI150 -> 60543.494 | BL150: 7 | BM150: =+BL150*$F$1 -> 23.8 | BN150: =+BL150*$BM$186 -> 55937.818 | BO150: =+BM150*$BM$185 -> 50416.828 | BP150: =+BO150+BN150 -> 106354.65
A151: 2018 TORRE A | B151: 402 | C151: 4 | E151: =+C151*$F$1 -> 13.6 | F151: =+C151*$E$186 -> 29779.522 | G151: =+E151*E$185 -> 29012.533 | H151: =+G151+F151 -> 58792.055 | I151: 4 | K151: =+I151*$F$1 -> 13.6 | L151: =+I151*$K$186 -> 29779.522 | M151: =+K151*$K$185 -> 29073.796 | N151: =+M151+L151 -> 58853.318 | O151: 4 | Q151: =+O151*$F$1 -> 13.6 | R151: =+O151*$Q$186 -> 29804.325 | S151: =+Q151*$Q$185 -> 29575.313 | T151: =+S151+R151 -> 59379.639 | U151: 4 | V151: =+U151*$F$1 -> 13.6 | W151: =+U151*$V$186 -> 29804.325 | X151: =+V151*$V$185 -> 27997.638 | Y151: =+X151+W151 -> 57801.963 | Z151: 3 | AA151: =+Z151*$F$1 -> 10.2 | AB151: =+Z151*$AB$186 -> 23229.475 | AC151: =+AA151*$AB$185 -> 21581.614 | AD151: =+AC151+AB151 -> 44811.089 | AE151: 5 | AF151: =+AE151*$F$1 -> 17 | AG151: =+AE151*$AF$186 -> 38715.792 | AH151: =+AF151*$AF$185 -> 37645.999 | AI151: =+AH151+AG151 -> 76361.792 | AJ151: 1 | AK151: =+AJ151*$F$1 -> 3.4 | AM151: =+AJ151*$AK$186 -> 7959.437 | AN151: =+AK151*$AK$185 -> 6974.2473 | AO151: =+AN151+AM151 -> 14933.684 | AP151: 4 | AQ151: =+AP151*$F$1 -> 13.6 | AS151: =+AP151*$AQ$186 -> 31837.748 | AT151: =+AQ151*$AQ$185 -> 26888.228 | AU151: =+AT151+AS151 -> 58725.976 | AV151: 4 | AW151: =+AV151*$F$1 -> 13.6 | AY151: =+AV151*$AW$186 -> 31895.591 | AZ151: =+AW151*$AW$185 -> 27269.039 | BA151: =+AZ151+AY151 -> 59164.63 | BB151: 5 | BC151: =+BB151*$F$1 -> 17 | BD151: =+BB151*$BC$186 -> 39869.489 | BE151: =+BC151*$BC$185 -> 33111.186 | BF151: =+BE151+BD151 -> 72980.675 | BG151: 3 | BH151: =+BG151*$F$1 -> 10.2 | BI151: =+BG151*$BH$186 -> 23973.351 | BJ151: =+BH151*$BH$185 -> 21434.27 | BK151: =+BJ151+BI151 -> 45407.62 | BL151: 4 | BM151: =+BL151*$F$1 -> 13.6 | BN151: =+BL151*$BM$186 -> 31964.468 | BO151: =+BM151*$BM$185 -> 28809.616 | BP151: =+BO151+BN151 -> 60774.083
A152: 2018 TORRE A | B152: 403 | C152: 2 | E152: =+C152*$F$1 -> 6.8 | F152: =+C152*$E$186 -> 14889.761 | G152: =+E152*E$185 -> 14506.267 | H152: =+G152+F152 -> 29396.028 | I152: 1 | K152: =+I152*$F$1 -> 3.4 | L152: =+I152*$K$186 -> 7444.8804 | M152: =+K152*$K$185 -> 7268.4491 | N152: =+M152+L152 -> 14713.33 | O152: 1 | Q152: =+O152*$F$1 -> 3.4 | R152: =+O152*$Q$186 -> 7451.0814 | S152: =+Q152*$Q$185 -> 7393.8284 | T152: =+S152+R152 -> 14844.91 | U152: 2 | V152: =+U152*$F$1 -> 6.8 | W152: =+U152*$V$186 -> 14902.163 | X152: =+V152*$V$185 -> 13998.819 | Y152: =+X152+W152 -> 28900.982 | Z152: 1 | AA152: =+Z152*$F$1 -> 3.4 | AB152: =+Z152*$AB$186 -> 7743.1585 | AC152: =+AA152*$AB$185 -> 7193.8713 | AD152: =+AC152+AB152 -> 14937.03 | AE152: 1 | AF152: =+AE152*$F$1 -> 3.4 | AG152: =+AE152*$AF$186 -> 7743.1585 | AH152: =+AF152*$AF$185 -> 7529.1999 | AI152: =+AH152+AG152 -> 15272.358 | AJ152: 2 | AK152: =+AJ152*$F$1 -> 6.8 | AM152: =+AJ152*$AK$186 -> 15918.874 | AN152: =+AK152*$AK$185 -> 13948.495 | AO152: =+AN152+AM152 -> 29867.369 | AP152: 1 | AQ152: =+AP152*$F$1 -> 3.4 | AS152: =+AP152*$AQ$186 -> 7959.437 | AT152: =+AQ152*$AQ$185 -> 6722.0569 | AU152: =+AT152+AS152 -> 14681.494 | AV152: 2 | AW152: =+AV152*$F$1 -> 6.8 | AY152: =+AV152*$AW$186 -> 15947.796 | AZ152: =+AW152*$AW$185 -> 13634.519 | BA152: =+AZ152+AY152 -> 29582.315 | BB152: 2 | BC152: =+BB152*$F$1 -> 6.8 | BD152: =+BB152*$BC$186 -> 15947.796 | BE152: =+BC152*$BC$185 -> 13244.474 | BF152: =+BE152+BD152 -> 29192.27 | BG152: 1 | BH152: =+BG152*$F$1 -> 3.4 | BI152: =+BG152*$BH$186 -> 7991.1169 | BJ152: =+BH152*$BH$185 -> 7144.7566 | BK152: =+BJ152+BI152 -> 15135.873 | BL152: 2 | BM152: =+BL152*$F$1 -> 6.8 | BN152: =+BL152*$BM$186 -> 15982.234 | BO152: =+BM152*$BM$185 -> 14404.808 | BP152: =+BO152+BN152 -> 30387.042
A153: 2018 TORRE A | B153: 404 | C153: 2 | E153: =+C153*$F$1 -> 6.8 | F153: =+C153*$E$186 -> 14889.761 | G153: =+E153*E$185 -> 14506.267 | H153: =+G153+F153 -> 29396.028 | I153: 2 | K153: =+I153*$F$1 -> 6.8 | L153: =+I153*$K$186 -> 14889.761 | M153: =+K153*$K$185 -> 14536.898 | N153: =+M153+L153 -> 29426.659 | O153: 2 | Q153: =+O153*$F$1 -> 6.8 | R153: =+O153*$Q$186 -> 14902.163 | S153: =+Q153*$Q$185 -> 14787.657 | T153: =+S153+R153 -> 29689.819 | U153: 2 | V153: =+U153*$F$1 -> 6.8 | W153: =+U153*$V$186 -> 14902.163 | X153: =+V153*$V$185 -> 13998.819 | Y153: =+X153+W153 -> 28900.982 | Z153: 1 | AA153: =+Z153*$F$1 -> 3.4 | AB153: =+Z153*$AB$186 -> 7743.1585 | AC153: =+AA153*$AB$185 -> 7193.8713 | AD153: =+AC153+AB153 -> 14937.03 | AE153: 1 | AF153: =+AE153*$F$1 -> 3.4 | AG153: =+AE153*$AF$186 -> 7743.1585 | AH153: =+AF153*$AF$185 -> 7529.1999 | AI153: =+AH153+AG153 -> 15272.358 | AJ153: 2 | AK153: =+AJ153*$F$1 -> 6.8 | AM153: =+AJ153*$AK$186 -> 15918.874 | AN153: =+AK153*$AK$185 -> 13948.495 | AO153: =+AN153+AM153 -> 29867.369 | AP153: 2 | AQ153: =+AP153*$F$1 -> 6.8 | AS153: =+AP153*$AQ$186 -> 15918.874 | AT153: =+AQ153*$AQ$185 -> 13444.114 | AU153: =+AT153+AS153 -> 29362.988 | AV153: 2 | AW153: =+AV153*$F$1 -> 6.8 | AY153: =+AV153*$AW$186 -> 15947.796 | AZ153: =+AW153*$AW$185 -> 13634.519 | BA153: =+AZ153+AY153 -> 29582.315 | BB153: 1 | BC153: =+BB153*$F$1 -> 3.4 | BD153: =+BB153*$BC$186 -> 7973.8978 | BE153: =+BC153*$BC$185 -> 6622.2372 | BF153: =+BE153+BD153 -> 14596.135 | BG153: 1 | BH153: =+BG153*$F$1 -> 3.4 | BI153: =+BG153*$BH$186 -> 7991.1169 | BJ153: =+BH153*$BH$185 -> 7144.7566 | BK153: =+BJ153+BI153 -> 15135.873 | BL153: 1 | BM153: =+BL153*$F$1 -> 3.4 | BN153: =+BL153*$BM$186 -> 7991.1169 | BO153: =+BM153*$BM$185 -> 7202.404 | BP153: =+BO153+BN153 -> 15193.521
A154: 2018 TORRE A | B154: 501 | C154: 2 | E154: =+C154*$F$1 -> 6.8 | F154: =+C154*$E$186 -> 14889.761 | G154: =+E154*E$185 -> 14506.267 | H154: =+G154+F154 -> 29396.028 | I154: 2 | K154: =+I154*$F$1 -> 6.8 | L154: =+I154*$K$186 -> 14889.761 | M154: =+K154*$K$185 -> 14536.898 | N154: =+M154+L154 -> 29426.659 | O154: 3 | Q154: =+O154*$F$1 -> 10.2 | R154: =+O154*$Q$186 -> 22353.244 | S154: =+Q154*$Q$185 -> 22181.485 | T154: =+S154+R154 -> 44534.729 | U154: 1 | V154: =+U154*$F$1 -> 3.4 | W154: =+U154*$V$186 -> 7451.0814 | X154: =+V154*$V$185 -> 6999.4094 | Y154: =+X154+W154 -> 14450.491 | Z154: 2 | AA154: =+Z154*$F$1 -> 6.8 | AB154: =+Z154*$AB$186 -> 15486.317 | AC154: =+AA154*$AB$185 -> 14387.743 | AD154: =+AC154+AB154 -> 29874.06 | AE154: 2 | AF154: =+AE154*$F$1 -> 6.8 | AG154: =+AE154*$AF$186 -> 15486.317 | AH154: =+AF154*$AF$185 -> 15058.4 | AI154: =+AH154+AG154 -> 30544.717 | AJ154: 1 | AK154: =+AJ154*$F$1 -> 3.4 | AM154: =+AJ154*$AK$186 -> 7959.437 | AN154: =+AK154*$AK$185 -> 6974.2473 | AO154: =+AN154+AM154 -> 14933.684 | AP154: 2 | AQ154: =+AP154*$F$1 -> 6.8 | AS154: =+AP154*$AQ$186 -> 15918.874 | AT154: =+AQ154*$AQ$185 -> 13444.114 | AU154: =+AT154+AS154 -> 29362.988 | AV154: 1 | AW154: =+AV154*$F$1 -> 3.4 | AY154: =+AV154*$AW$186 -> 7973.8978 | AZ154: =+AW154*$AW$185 -> 6817.2597 | BA154: =+AZ154+AY154 -> 14791.158 | BB154: 2 | BC154: =+BB154*$F$1 -> 6.8 | BD154: =+BB154*$BC$186 -> 15947.796 | BE154: =+BC154*$BC$185 -> 13244.474 | BF154: =+BE154+BD154 -> 29192.27 | BG154: 1 | BH154: =+BG154*$F$1 -> 3.4 | BI154: =+BG154*$BH$186 -> 7991.1169 | BJ154: =+BH154*$BH$185 -> 7144.7566 | BK154: =+BJ154+BI154 -> 15135.873 | BL154: 3 | BM154: =+BL154*$F$1 -> 10.2 | BN154: =+BL154*$BM$186 -> 23973.351 | BO154: =+BM154*$BM$185 -> 21607.212 | BP154: =+BO154+BN154 -> 45580.563
A155: 2018 TORRE A | B155: 502 | C155: 2 | E155: =+C155*$F$1 -> 6.8 | F155: =+C155*$E$186 -> 14889.761 | G155: =+E155*E$185 -> 14506.267 | H155: =+G155+F155 -> 29396.028 | I155: 3 | K155: =+I155*$F$1 -> 10.2 | L155: =+I155*$K$186 -> 22334.641 | M155: =+K155*$K$185 -> 21805.347 | N155: =+M155+L155 -> 44139.989 | O155: 2 | Q155: =+O155*$F$1 -> 6.8 | R155: =+O155*$Q$186 -> 14902.163 | S155: =+Q155*$Q$185 -> 14787.657 | T155: =+S155+R155 -> 29689.819 | U155: 3 | V155: =+U155*$F$1 -> 10.2 | W155: =+U155*$V$186 -> 22353.244 | X155: =+V155*$V$185 -> 20998.228 | Y155: =+X155+W155 -> 43351.472 | Z155: 2 | AA155: =+Z155*$F$1 -> 6.8 | AB155: =+Z155*$AB$186 -> 15486.317 | AC155: =+AA155*$AB$185 -> 14387.743 | AD155: =+AC155+AB155 -> 29874.06 | AE155: 3 | AF155: =+AE155*$F$1 -> 10.2 | AG155: =+AE155*$AF$186 -> 23229.475 | AH155: =+AF155*$AF$185 -> 22587.6 | AI155: =+AH155+AG155 -> 45817.075 | AJ155: 3 | AK155: =+AJ155*$F$1 -> 10.2 | AM155: =+AJ155*$AK$186 -> 23878.311 | AN155: =+AK155*$AK$185 -> 20922.742 | AO155: =+AN155+AM155 -> 44801.053 | AP155: 2 | AQ155: =+AP155*$F$1 -> 6.8 | AS155: =+AP155*$AQ$186 -> 15918.874 | AT155: =+AQ155*$AQ$185 -> 13444.114 | AU155: =+AT155+AS155 -> 29362.988 | AV155: 3 | AW155: =+AV155*$F$1 -> 10.2 | AY155: =+AV155*$AW$186 -> 23921.694 | AZ155: =+AW155*$AW$185 -> 20451.779 | BA155: =+AZ155+AY155 -> 44373.473 | BB155: 4 | BC155: =+BB155*$F$1 -> 13.6 | BD155: =+BB155*$BC$186 -> 31895.591 | BE155: =+BC155*$BC$185 -> 26488.949 | BF155: =+BE155+BD155 -> 58384.54 | BG155: 2 | BH155: =+BG155*$F$1 -> 6.8 | BI155: =+BG155*$BH$186 -> 15982.234 | BJ155: =+BH155*$BH$185 -> 14289.513 | BK155: =+BJ155+BI155 -> 30271.747 | BL155: 4 | BM155: =+BL155*$F$1 -> 13.6 | BN155: =+BL155*$BM$186 -> 31964.468 | BO155: =+BM155*$BM$185 -> 28809.616 | BP155: =+BO155+BN155 -> 60774.083
A156: 2018 TORRE A | B156: 503 | C156: 4 | E156: =+C156*$F$1 -> 13.6 | F156: =+C156*$E$186 -> 29779.522 | G156: =+E156*E$185 -> 29012.533 | H156: =+G156+F156 -> 58792.055 | I156: 5 | K156: =+I156*$F$1 -> 17 | L156: =+I156*$K$186 -> 37224.402 | M156: =+K156*$K$185 -> 36342.245 | N156: =+M156+L156 -> 73566.648 | O156: 4 | Q156: =+O156*$F$1 -> 13.6 | R156: =+O156*$Q$186 -> 29804.325 | S156: =+Q156*$Q$185 -> 29575.313 | T156: =+S156+R156 -> 59379.639 | U156: 3 | V156: =+U156*$F$1 -> 10.2 | W156: =+U156*$V$186 -> 22353.244 | X156: =+V156*$V$185 -> 20998.228 | Y156: =+X156+W156 -> 43351.472 | Z156: 3 | AA156: =+Z156*$F$1 -> 10.2 | AB156: =+Z156*$AB$186 -> 23229.475 | AC156: =+AA156*$AB$185 -> 21581.614 | AD156: =+AC156+AB156 -> 44811.089 | AE156: 3 | AF156: =+AE156*$F$1 -> 10.2 | AG156: =+AE156*$AF$186 -> 23229.475 | AH156: =+AF156*$AF$185 -> 22587.6 | AI156: =+AH156+AG156 -> 45817.075 | AJ156: 4 | AK156: =+AJ156*$F$1 -> 13.6 | AM156: =+AJ156*$AK$186 -> 31837.748 | AN156: =+AK156*$AK$185 -> 27896.989 | AO156: =+AN156+AM156 -> 59734.737 | AP156: 3 | AQ156: =+AP156*$F$1 -> 10.2 | AS156: =+AP156*$AQ$186 -> 23878.311 | AT156: =+AQ156*$AQ$185 -> 20166.171 | AU156: =+AT156+AS156 -> 44044.482 | AV156: 4 | AW156: =+AV156*$F$1 -> 13.6 | AY156: =+AV156*$AW$186 -> 31895.591 | AZ156: =+AW156*$AW$185 -> 27269.039 | BA156: =+AZ156+AY156 -> 59164.63 | BB156: 1 | BC156: =+BB156*$F$1 -> 3.4 | BD156: =+BB156*$BC$186 -> 7973.8978 | BE156: =+BC156*$BC$185 -> 6622.2372 | BF156: =+BE156+BD156 -> 14596.135 | BG156: 2 | BH156: =+BG156*$F$1 -> 6.8 | BI156: =+BG156*$BH$186 -> 15982.234 | BJ156: =+BH156*$BH$185 -> 14289.513 | BK156: =+BJ156+BI156 -> 30271.747 | BL156: 5 | BM156: =+BL156*$F$1 -> 17 | BN156: =+BL156*$BM$186 -> 39955.584 | BO156: =+BM156*$BM$185 -> 36012.02 | BP156: =+BO156+BN156 -> 75967.604
A157: 2018 TORRE A | B157: 504 | C157: 12 | E157: =+C157*$F$1 -> 40.8 | F157: =+C157*$E$186 -> 89338.565 | G157: =+E157*E$185 -> 87037.6 | H157: =+G157+F157 -> 176376.17 | I157: 10 | K157: =+I157*$F$1 -> 34 | L157: =+I157*$K$186 -> 74448.804 | M157: =+K157*$K$185 -> 72684.491 | N157: =+M157+L157 -> 147133.3 | O157: 10 | Q157: =+O157*$F$1 -> 34 | R157: =+O157*$Q$186 -> 74510.814 | S157: =+Q157*$Q$185 -> 73938.284 | T157: =+S157+R157 -> 148449.1 | U157: 7 | V157: =+U157*$F$1 -> 23.8 | W157: =+U157*$V$186 -> 52157.57 | X157: =+V157*$V$185 -> 48995.866 | Y157: =+X157+W157 -> 101153.44 | Z157: 9 | AA157: =+Z157*$F$1 -> 30.6 | AB157: =+Z157*$AB$186 -> 69688.426 | AC157: =+AA157*$AB$185 -> 64744.842 | AD157: =+AC157+AB157 -> 134433.27 | AE157: 10 | AF157: =+AE157*$F$1 -> 34 | AG157: =+AE157*$AF$186 -> 77431.585 | AH157: =+AF157*$AF$185 -> 75291.999 | AI157: =+AH157+AG157 -> 152723.58 | AJ157: 11 | AK157: =+AJ157*$F$1 -> 37.4 | AM157: =+AJ157*$AK$186 -> 87553.807 | AN157: =+AK157*$AK$185 -> 76716.72 | AO157: =+AN157+AM157 -> 164270.53 | AP157: 7 | AQ157: =+AP157*$F$1 -> 23.8 | AS157: =+AP157*$AQ$186 -> 55716.059 | AT157: =+AQ157*$AQ$185 -> 47054.399 | AU157: =+AT157+AS157 -> 102770.46 | AV157: 14 | AW157: =+AV157*$F$1 -> 47.6 | AY157: =+AV157*$AW$186 -> 111634.57 | AZ157: =+AW157*$AW$185 -> 95441.635 | BA157: =+AZ157+AY157 -> 207076.21 | BB157: 12 | BC157: =+BB157*$F$1 -> 40.8 | BD157: =+BB157*$BC$186 -> 95686.774 | BE157: =+BC157*$BC$185 -> 79466.847 | BF157: =+BE157+BD157 -> 175153.62 | BG157: 8 | BH157: =+BG157*$F$1 -> 27.2 | BI157: =+BG157*$BH$186 -> 63928.935 | BJ157: =+BH157*$BH$185 -> 57158.053 | BK157: =+BJ157+BI157 -> 121086.99 | BL157: 14 | BM157: =+BL157*$F$1 -> 47.6 | BN157: =+BL157*$BM$186 -> 111875.64 | BO157: =+BM157*$BM$185 -> 100833.66 | BP157: =+BO157+BN157 -> 212709.29
... A181: 2018 TORRE A | B181: 1302 | C181: 13 | E181: =+C181*$F$1 -> 44.2 | F181: =+C181*$E$186 -> 96783.446 | G181: =+E181*E$185 -> 94290.734 | H181: =+G181+F181 -> 191074.18 | I181: 11 | K181: =+I181*$F$1 -> 37.4 | L181: =+I181*$K$186 -> 81893.685 | M181: =+K181*$K$185 -> 79952.94 | N181: =+M181+L181 -> 161846.62 | O181: 11 | Q181: =+O181*$F$1 -> 37.4 | R181: =+O181*$Q$186 -> 81961.895 | S181: =+Q181*$Q$185 -> 81332.112 | T181: =+S181+R181 -> 163294.01 | U181: 10 | V181: =+U181*$F$1 -> 34 | W181: =+U181*$V$186 -> 74510.814 | X181: =+V181*$V$185 -> 69994.094 | Y181: =+X181+W181 -> 144504.91 | Z181: 11 | AA181: =+Z181*$F$1 -> 37.4 | AB181: =+Z181*$AB$186 -> 85174.743 | AC181: =+AA181*$AB$185 -> 79132.584 | AD181: =+AC181+AB181 -> 164307.33 | AE181: 12 | AF181: =+AE181*$F$1 -> 40.8 | AG181: =+AE181*$AF$186 -> 92917.902 | AH181: =+AF181*$AF$185 -> 90350.399 | AI181: =+AH181+AG181 -> 183268.3 | AJ181: 11 | AK181: =+AJ181*$F$1 -> 37.4 | AM181: =+AJ181*$AK$186 -> 87553.807 | AN181: =+AK181*$AK$185 -> 76716.72 | AO181: =+AN181+AM181 -> 164270.53 | AP181: 6 | AQ181: =+AP181*$F$1 -> 20.4 | AS181: =+AP181*$AQ$186 -> 47756.622 | AT181: =+AQ181*$AQ$185 -> 40332.342 | AU181: =+AT181+AS181 -> 88088.963 | AV181: 15 | AW181: =+AV181*$F$1 -> 51 | AY181: =+AV181*$AW$186 -> 119608.47 | AZ181: =+AW181*$AW$185 -> 102258.9 | BA181: =+AZ181+AY181 -> 221867.36 | BB181: 14 | BC181: =+BB181*$F$1 -> 47.6 | BD181: =+BB181*$BC$186 -> 111634.57 | BE181: =+BC181*$BC$185 -> 92711.321 | BF181: =+BE181+BD181 -> 204345.89 | BG181: 11 | BH181: =+BG181*$F$1 -> 37.4 | BI181: =+BG181*$BH$186 -> 87902.286 | BJ181: =+BH181*$BH$185 -> 78592.323 | BK181: =+BJ181+BI181 -> 166494.61 | BL181: 17 | BM181: =+BL181*$F$1 -> 57.8 | BN181: =+BL181*$BM$186 -> 135848.99 | BO181: =+BM181*$BM$185 -> 122440.87 | BP181: =+BO181+BN181 -> 258289.85
A182: 2018 TORRE A | C182: =SUM(C145:C181) -> 231 | E182: =SUM(E145:E181) -> 785.4 | F182: =SUM(F145:F181) -> 1719767.4 | G182: =SUM(G145:G181) -> 1675473.8 | H182: =SUM(H145:H181) -> 3395241.2 | I182: =SUM(I145:I181) -> 215 | K182: =SUM(K145:K181) -> 731 | L182: =SUM(L145:L181) -> 1600649.3 | M182: =SUM(M145:M181) -> 1562716.6 | N182: =SUM(N145:N181) -> 3163365.8 | O182: =SUM(O145:O181) -> 219 | Q182: =SUM(Q145:Q181) -> 744.6 | R182: =SUM(R145:R181) -> 1631786.8 | S182: =SUM(S145:S181) -> 1619248.4 | T182: =SUM(T145:T181) -> 3251035.2 | U182: =SUM(U145:U181) -> 187 | V182: =SUM(V145:V181) -> 635.8 | W182: =SUM(W145:W181) -> 1393352.2 | X182: =SUM(X145:X181) -> 1308889.6 | ... AK182: =SUM(AK145:AK181) -> 717.4 | AM182: =SUM(AM145:AM181) -> 1679441.2 | AN182: =SUM(AN145:AN181) -> 1471566.2 | AO182: =SUM(AO145:AO181) -> 3151007.4 | AP182: =SUM(AP145:AP181) -> 184 | AQ182: =SUM(AQ145:AQ181) -> 625.6 | AS182: =SUM(AS145:AS181) -> 1464536.4 | AT182: =SUM(AT145:AT181) -> 1236858.5 | AU182: =SUM(AU145:AU181) -> 2701394.9 | AV182: =SUM(AV145:AV181) -> 234 | AW182: =SUM(AW145:AW181) -> 795.6 | AY182: =SUM(AY145:AY181) -> 1865892.1 | AZ182: =SUM(AZ145:AZ181) -> 1595238.8 | BA182: =SUM(BA145:BA181) -> 3461130.9 | BB182: =SUM(BB145:BB181) -> 235 | BC182: =SUM(BC145:BC181) -> 799 | BD182: =SUM(BD145:BD181) -> 1873866 | BE182: =SUM(BE145:BE181) -> 1556225.7 | BF182: =SUM(BF145:BF181) -> 3430091.7 | ... BP182: =SUM(BP145:BP181) -> 3919928.4
A183: 2018 TORRE A
A184: 2018 TORRE A | C184: ENERO DE 2018 | I184: FEBRERO DE 2018 | O184: MARZO DE 2018 | U184: ABRIL DE 2018 | AA184: MAYO DE 2018 | AE184: JUNIO DE 2018 | AJ184: JULIO DE 2018 | AP184: AGOSTO DE 2018 | AV184: SEPTIEMBRE DE 2018 | BB184: OCTUBRE DE 2018 | BG184: NOVIEMBRE DE 2018 | BL184: DICIEMBRE DE 2018
A185: 2018 TORRE A | C185: VR M3 GAS | E185: =+'Vr M3 DE GAS'!$F$73 -> 2133.2745 | I185: VR M3 GAS | K185: =+'Vr M3 DE GAS'!$O$62 -> 2137.7791 | O185: VR M3 GAS | Q185: =+'Vr M3 DE GAS'!$O$63 -> 2174.6554 | U185: VR M3 GAS | V185: =+'Vr M3 DE GAS'!$O$64 -> 2058.6498 | AA185: VR M3 GAS | AB185: =+'Vr M3 DE GAS'!$O$65 -> 2115.8445 | AE185: VR M3 GAS | AF185: =+'Vr M3 DE GAS'!$O$66 -> 2214.4706 | AJ185: VR M3 GAS | AK185: =+'Vr M3 DE GAS'!$O$67 -> 2051.2492 | AP185: VR M3 GAS | AQ185: =+'Vr M3 DE GAS'!$O$68 -> 1977.0756 | AV185: VR M3 GAS | AW185: =+'Vr M3 DE GAS'!$O$69 -> 2005.0764 | BB185: VR M3 GAS | BC185: =+'Vr M3 DE GAS'!$O$70 -> 1947.7168 | BG185: VR M3 GAS | BH185: =+'Vr M3 DE GAS'!$O$71 -> 2101.399 | BL185: VR M3 GAS | BM185: =+'Vr M3 DE GAS'!$O$72 -> 2118.3541
A186: 2018 TORRE A | C186: VR M3 AGUA | E186: =+'Vr M3 DE AGUA'!$N$10 -> 7444.8804 | I186: VR M3 AGUA | K186: =+'Vr M3 DE AGUA'!$N$10 -> 7444.8804 | O186: VR M3 AGUA | Q186: =+'Vr M3 DE AGUA'!$N$11 -> 7451.0814 | U186: VR M3 AGUA | V186: =+'Vr M3 DE AGUA'!$N$11 -> 7451.0814 | AA186: VR M3 AGUA | AB186: =+'Vr M3 DE AGUA'!$N$12 -> 7743.1585 | AE186: VR M3 AGUA | AF186: =+'Vr M3 DE AGUA'!$N$12 -> 7743.1585 | AJ186: VR M3 AGUA | AK186: =+'Vr M3 DE AGUA'!$N$13 -> 7959.437 | AP186: VR M3 AGUA | AQ186: =+'Vr M3 DE AGUA'!$N$13 -> 7959.437 | AV186: VR M3 AGUA | AW186: =+'Vr M3 DE AGUA'!$N$14 -> 7973.8978 | BB186: VR M3 AGUA | BC186: =+'Vr M3 DE AGUA'!$N$14 -> 7973.8978 | BG186: VR M3 AGUA | BH186: =+'Vr M3 DE AGUA'!$N$15 -> 7991.1169 | BL186: VR M3 AGUA | BM186: =+'Vr M3 DE AGUA'!$N$15 -> 7991.1169
B190: AÑO 2018
B191: TORRE B
C192: ENERO | I192: FEBRERO | O192: MARZO | U192: ABRIL | Z192: MAYO | AE192: JUNIO | AJ192: JULIO | AP192: AGOSTO | AV192: SEPTIEMBRE | BB192: OCTUBRE | BG192: NOVIEMBRE | BL192: DICIEMBRE
C194: AGUA | E194: GAS | F194: $ AGUA | G194: $GAS | H194: $ TOTAL | I194: AGUA | K194: GAS | L194: $ AGUA | M194: $GAS | N194: $ TOTAL | O194: AGUA | Q194: GAS | R194: $ AGUA | S194: $GAS | T194: $ TOTAL | U194: AGUA | V194: GAS | W194: $ AGUA | X194: $GAS | Y194: $ TOTAL | Z194: AGUA | AA194: GAS | AB194: $ AGUA | AC194: $GAS | AD194: $ TOTAL | AE194: AGUA | AF194: GAS | AG194: $ AGUA | AH194: $GAS | AI194: $ TOTAL | AJ194: AGUA | AK194: GAS | AM194: $ AGUA | AN194: $GAS | AO194: $ TOTAL | AP194: AGUA | AQ194: GAS | AS194: $ AGUA | AT194: $GAS | AU194: $ TOTAL | AV194: AGUA | AW194: GAS | AY194: $ AGUA | AZ194: $GAS | BA194: $ TOTAL | BB194: AGUA | BC194: GAS | BD194: $ AGUA | BE194: $GAS | BF194: $ TOTAL | BG194: AGUA | BH194: GAS | BI194: $ AGUA | BJ194: $GAS | BK194: $ TOTAL | BL194: AGUA | BM194: GAS | BN194: $ AGUA | BO194: $GAS | BP194: $ TOTAL
A195: 2018 TORRE B | B195: 201 | C195: 6 | E195: =+C195*$F$1 -> 20.4 | F195: =+C195*$E$231 -> 44669.283 | G195: =+E195*$E$230 -> 43518.8 | H195: =+G195+F195 -> 88188.083 | I195: 8 | K195: =+I195*$F$1 -> 27.2 | L195: =+I195*$K$231 -> 59559.043 | M195: =+K195*$K$230 -> 58147.593 | N195: =+M195+L195 -> 117706.64 | O195: 0 | Q195: =+O195*$F$1 -> 0 | R195: =+O195*$Q$231 -> 0 | S195: =+Q195*$Q$230 -> 0 | T195: =+S195+R195 -> 0 | U195: 0 | V195: =+U195*$F$1 -> 0 | W195: =+U195*$V$231 -> 0 | X195: =+V195*$V$230 -> 0 | Y195: =+X195+W195 -> 0 | Z195: 0 | AA195: =+Z195*$F$1 -> 0 | AB195: =+Z195*$AB$231 -> 0 | AC195: =+AA195*$AB$230 -> 0 | AD195: =+AC195+AB195 -> 0 | AE195: 0 | AF195: =+AE195*$F$1 -> 0 | AG195: =+AE195*$AF$231 -> 0 | AH195: =+AF195*$AF$230 -> 0 | AI195: =+AH195+AG195 -> 0 | AJ195: 1 | AK195: =+AJ195*$F$1 -> 3.4 | AM195: =+AJ195*$AK$231 -> 7959.437 | AN195: =+AK195*$AK$230 -> 6974.2473 | AO195: =+AN195+AM195 -> 14933.684 | AP195: 5 | AQ195: =+AP195*$F$1 -> 17 | AS195: =+AP195*$AQ$231 -> 39797.185 | AT195: =+AQ195*$AQ$230 -> 33610.285 | AU195: =+AT195+AS195 -> 73407.47 | AV195: 6 | AW195: =+AV195*$F$1 -> 20.4 | AY195: =+AV195*$AW$231 -> 47843.387 | AZ195: =+AW195*$AW$230 -> 40903.558 | BA195: =+AZ195+AY195 -> 88746.945 | BB195: 5 | BC195: =+BB195*$F$1 -> 17 | BD195: =+BB195*$BC$231 -> 39869.489 | BE195: =+BC195*$BC$230 -> 33111.186 | BF195: =+BE195+BD195 -> 72980.675 | BG195: 6 | BH195: =+BG195*$F$1 -> 20.4 | BI195: =+BG195*$BH$231 -> 47946.701 | BJ195: =+BH195*$BH$230 -> 42868.54 | BK195: =+BJ195+BI195 -> 90815.241 | BL195: 6 | BM195: =+BL195*$F$1 -> 20.4 | BN195: =+BL195*$BM$231 -> 47946.701 | BO195: =+BM195*$BM$230 -> 43214.424 | BP195: =+BO195+BN195 -> 91161.125
A196: 2018 TORRE B | B196: 202 | C196: 4 | E196: =+C196*$F$1 -> 13.6 | F196: =+C196*$E$231 -> 29779.522 | G196: =+E196*$E$230 -> 29012.533 | H196: =+G196+F196 -> 58792.055 | I196: 6 | K196: =+I196*$F$1 -> 20.4 | L196: =+I196*$K$231 -> 44669.283 | M196: =+K196*$K$230 -> 43610.695 | N196: =+M196+L196 -> 88279.977 | O196: 5 | Q196: =+O196*$F$1 -> 17 | R196: =+O196*$Q$231 -> 37255.407 | S196: =+Q196*$Q$230 -> 36969.142 | T196: =+S196+R196 -> 74224.549 | U196: 6 | V196: =+U196*$F$1 -> 20.4 | W196: =+U196*$V$231 -> 44706.488 | X196: =+V196*$V$230 -> 41996.457 | Y196: =+X196+W196 -> 86702.945 | Z196: 6 | AA196: =+Z196*$F$1 -> 20.4 | AB196: =+Z196*$AB$231 -> 46458.951 | AC196: =+AA196*$AB$230 -> 43163.228 | AD196: =+AC196+AB196 -> 89622.179 | AE196: 5 | AF196: =+AE196*$F$1 -> 17 | AG196: =+AE196*$AF$231 -> 38715.792 | AH196: =+AF196*$AF$230 -> 37645.999 | AI196: =+AH196+AG196 -> 76361.792 | AJ196: 6 | AK196: =+AJ196*$F$1 -> 20.4 | AM196: =+AJ196*$AK$231 -> 47756.622 | AN196: =+AK196*$AK$230 -> 41845.484 | AO196: =+AN196+AM196 -> 89602.106 | AP196: 3 | AQ196: =+AP196*$F$1 -> 10.2 | AS196: =+AP196*$AQ$231 -> 23878.311 | AT196: =+AQ196*$AQ$230 -> 20166.171 | AU196: =+AT196+AS196 -> 44044.482 | AV196: 5 | AW196: =+AV196*$F$1 -> 17 | AY196: =+AV196*$AW$231 -> 39869.489 | AZ196: =+AW196*$AW$230 -> 34086.298 | BA196: =+AZ196+AY196 -> 73955.788 | BB196: 5 | BC196: =+BB196*$F$1 -> 17 | BD196: =+BB196*$BC$231 -> 39869.489 | BE196: =+BC196*$BC$230 -> 33111.186 | BF196: =+BE196+BD196 -> 72980.675 | BG196: 4 | BH196: =+BG196*$F$1 -> 13.6 | BI196: =+BG196*$BH$231 -> 31964.468 | BJ196: =+BH196*$BH$230 -> 28579.026 | BK196: =+BJ196+BI196 -> 60543.494 | BL196: 6 | BM196: =+BL196*$F$1 -> 20.4 | BN196: =+BL196*$BM$231 -> 47946.701 | BO196: =+BM196*$BM$230 -> 43214.424 | BP196: =+BO196+BN196 -> 91161.125
A197: 2018 TORRE B | B197: 203 | C197: 6 | E197: =+C197*$F$1 -> 20.4 | F197: =+C197*$E$231 -> 44669.283 | G197: =+E197*$E$230 -> 43518.8 | H197: =+G197+F197 -> 88188.083 | I197: 7 | K197: =+I197*$F$1 -> 23.8 | L197: =+I197*$K$231 -> 52114.163 | M197: =+K197*$K$230 -> 50879.144 | N197: =+M197+L197 -> 102993.31 | O197: 4 | Q197: =+O197*$F$1 -> 13.6 | R197: =+O197*$Q$231 -> 29804.325 | S197: =+Q197*$Q$230 -> 29575.313 | T197: =+S197+R197 -> 59379.639 | U197: 6 | V197: =+U197*$F$1 -> 20.4 | W197: =+U197*$V$231 -> 44706.488 | X197: =+V197*$V$230 -> 41996.457 | Y197: =+X197+W197 -> 86702.945 | Z197: 4 | AA197: =+Z197*$F$1 -> 13.6 | AB197: =+Z197*$AB$231 -> 30972.634 | AC197: =+AA197*$AB$230 -> 28775.485 | AD197: =+AC197+AB197 -> 59748.119 | AE197: 4 | AF197: =+AE197*$F$1 -> 13.6 | AG197: =+AE197*$AF$231 -> 30972.634 | AH197: =+AF197*$AF$230 -> 30116.8 | AI197: =+AH197+AG197 -> 61089.433 | AJ197: 6 | AK197: =+AJ197*$F$1 -> 20.4 | AM197: =+AJ197*$AK$231 -> 47756.622 | AN197: =+AK197*$AK$230 -> 41845.484 | AO197: =+AN197+AM197 -> 89602.106 | AP197: 3 | AQ197: =+AP197*$F$1 -> 10.2 | AS197: =+AP197*$AQ$231 -> 23878.311 | AT197: =+AQ197*$AQ$230 -> 20166.171 | AU197: =+AT197+AS197 -> 44044.482 | AV197: 5 | AW197: =+AV197*$F$1 -> 17 | AY197: =+AV197*$AW$231 -> 39869.489 | AZ197: =+AW197*$AW$230 -> 34086.298 | BA197: =+AZ197+AY197 -> 73955.788 | BB197: 5 | BC197: =+BB197*$F$1 -> 17 | BD197: =+BB197*$BC$231 -> 39869.489 | BE197: =+BC197*$BC$230 -> 33111.186 | BF197: =+BE197+BD197 -> 72980.675 | BG197: 3 | BH197: =+BG197*$F$1 -> 10.2 | BI197: =+BG197*$BH$231 -> 23973.351 | BJ197: =+BH197*$BH$230 -> 21434.27 | BK197: =+BJ197+BI197 -> 45407.62 | BL197: 6 | BM197: =+BL197*$F$1 -> 20.4 | BN197: =+BL197*$BM$231 -> 47946.701 | BO197: =+BM197*$BM$230 -> 43214.424 | BP197: =+BO197+BN197 -> 91161.125
A198: 2018 TORRE B | B198: 204 | C198: 0 | E198: =+C198*$F$1 -> 0 | F198: =+C198*$E$231 -> 0 | G198: =+E198*$E$230 -> 0 | H198: =+G198+F198 -> 0 | I198: 0 | K198: =+I198*$F$1 -> 0 | L198: =+I198*$K$231 -> 0 | M198: =+K198*$K$230 -> 0 | N198: =+M198+L198 -> 0 | O198: 1 | Q198: =+O198*$F$1 -> 3.4 | R198: =+O198*$Q$231 -> 7451.0814 | S198: =+Q198*$Q$230 -> 7393.8284 | T198: =+S198+R198 -> 14844.91 | U198: 0 | V198: =+U198*$F$1 -> 0 | W198: =+U198*$V$231 -> 0 | X198: =+V198*$V$230 -> 0 | Y198: =+X198+W198 -> 0 | Z198: 1 | AA198: =+Z198*$F$1 -> 3.4 | AB198: =+Z198*$AB$231 -> 7743.1585 | AC198: =+AA198*$AB$230 -> 7193.8713 | AD198: =+AC198+AB198 -> 14937.03 | AE198: 0 | AF198: =+AE198*$F$1 -> 0 | AG198: =+AE198*$AF$231 -> 0 | AH198: =+AF198*$AF$230 -> 0 | AI198: =+AH198+AG198 -> 0 | AJ198: 1 | AK198: =+AJ198*$F$1 -> 3.4 | AM198: =+AJ198*$AK$231 -> 7959.437 | AN198: =+AK198*$AK$230 -> 6974.2473 | AO198: =+AN198+AM198 -> 14933.684 | AP198: 0 | AQ198: =+AP198*$F$1 -> 0 | AS198: =+AP198*$AQ$231 -> 0 | AT198: =+AQ198*$AQ$230 -> 0 | AU198: =+AT198+AS198 -> 0 | AV198: 0 | AW198: =+AV198*$F$1 -> 0 | AY198: =+AV198*$AW$231 -> 0 | AZ198: =+AW198*$AW$230 -> 0 | BA198: =+AZ198+AY198 -> 0 | BB198: 1 | BC198: =+BB198*$F$1 -> 3.4 | BD198: =+BB198*$BC$231 -> 7973.8978 | BE198: =+BC198*$BC$230 -> 6622.2372 | BF198: =+BE198+BD198 -> 14596.135 | BG198: 0 | BH198: =+BG198*$F$1 -> 0 | BI198: =+BG198*$BH$231 -> 0 | BJ198: =+BH198*$BH$230 -> 0 | BK198: =+BJ198+BI198 -> 0 | BL198: 0 | BM198: =+BL198*$F$1 -> 0 | BN198: =+BL198*$BM$231 -> 0 | BO198: =+BM198*$BM$230 -> 0 | BP198: =+BO198+BN198 -> 0
A199: 2018 TORRE B | B199: 301 | C199: 8 | E199: =+C199*$F$1 -> 27.2 | F199: =+C199*$E$231 -> 59559.043 | G199: =+E199*$E$230 -> 58025.067 | H199: =+G199+F199 -> 117584.11 | I199: 11 | K199: =+I199*$F$1 -> 37.4 | L199: =+I199*$K$231 -> 81893.685 | M199: =+K199*$K$230 -> 79952.94 | N199: =+M199+L199 -> 161846.62 | O199: 11 | Q199: =+O199*$F$1 -> 37.4 | R199: =+O199*$Q$231 -> 81961.895 | S199: =+Q199*$Q$230 -> 81332.112 | T199: =+S199+R199 -> 163294.01 | U199: 13 | V199: =+U199*$F$1 -> 44.2 | W199: =+U199*$V$231 -> 96864.058 | X199: =+V199*$V$230 -> 90992.323 | Y199: =+X199+W199 -> 187856.38 | Z199: 10 | AA199: =+Z199*$F$1 -> 34 | AB199: =+Z199*$AB$231 -> 77431.585 | AC199: =+AA199*$AB$230 -> 71938.713 | AD199: =+AC199+AB199 -> 149370.3 | AE199: 9 | AF199: =+AE199*$F$1 -> 30.6 | AG199: =+AE199*$AF$231 -> 69688.426 | AH199: =+AF199*$AF$230 -> 67762.799 | AI199: =+AH199+AG199 -> 137451.23 | AJ199: 12 | AK199: =+AJ199*$F$1 -> 40.8 | AM199: =+AJ199*$AK$231 -> 95513.244 | AN199: =+AK199*$AK$230 -> 83690.968 | AO199: =+AN199+AM199 -> 179204.21 | AP199: 10 | AQ199: =+AP199*$F$1 -> 34 | AS199: =+AP199*$AQ$231 -> 79594.37 | AT199: =+AQ199*$AQ$230 -> 67220.569 | AU199: =+AT199+AS199 -> 146814.94 | AV199: 12 | AW199: =+AV199*$F$1 -> 40.8 | AY199: =+AV199*$AW$231 -> 95686.774 | AZ199: =+AW199*$AW$230 -> 81807.116 | BA199: =+AZ199+AY199 -> 177493.89 | BB199: 13 | BC199: =+BB199*$F$1 -> 44.2 | BD199: =+BB199*$BC$231 -> 103660.67 | BE199: =+BC199*$BC$230 -> 86089.084 | BF199: =+BE199+BD199 -> 189749.76 | BG199: 10 | BH199: =+BG199*$F$1 -> 34 | BI199: =+BG199*$BH$231 -> 79911.169 | BJ199: =+BH199*$BH$230 -> 71447.566 | BK199: =+BJ199+BI199 -> 151358.73 | BL199: 16 | BM199: =+BL199*$F$1 -> 54.4 | BN199: =+BL199*$BM$231 -> 127857.87 | BO199: =+BM199*$BM$230 -> 115238.46 | BP199: =+BO199+BN199 -> 243096.33
A200: 2018 TORRE B | B200: 302 | C200: 0 | E200: =+C200*$F$1 -> 0 | F200: =+C200*$E$231 -> 0 | G200: =+E200*$E$230 -> 0 | H200: =+G200+F200 -> 0 | I200: 0 | K200: =+I200*$F$1 -> 0 | L200: =+I200*$K$231 -> 0 | M200: =+K200*$K$230 -> 0 | N200: =+M200+L200 -> 0 | O200: 0 | Q200: =+O200*$F$1 -> 0 | R200: =+O200*$Q$231 -> 0 | S200: =+Q200*$Q$230 -> 0 | T200: =+S200+R200 -> 0 | U200: 0 | V200: =+U200*$F$1 -> 0 | W200: =+U200*$V$231 -> 0 | X200: =+V200*$V$230 -> 0 | Y200: =+X200+W200 -> 0 | Z200: 0 | AA200: =+Z200*$F$1 -> 0 | AB200: =+Z200*$AB$231 -> 0 | AC200: =+AA200*$AB$230 -> 0 | AD200: =+AC200+AB200 -> 0 | AE200: 0 | AF200: =+AE200*$F$1 -> 0 | AG200: =+AE200*$AF$231 -> 0 | AH200: =+AF200*$AF$230 -> 0 | AI200: =+AH200+AG200 -> 0 | AJ200: 0 | AK200: =+AJ200*$F$1 -> 0 | AM200: =+AJ200*$AK$231 -> 0 | AN200: =+AK200*$AK$230 -> 0 | AO200: =+AN200+AM200 -> 0 | AP200: 0 | AQ200: =+AP200*$F$1 -> 0 | AS200: =+AP200*$AQ$231 -> 0 | AT200: =+AQ200*$AQ$230 -> 0 | AU200: =+AT200+AS200 -> 0 | AV200: 0 | AW200: =+AV200*$F$1 -> 0 | AY200: =+AV200*$AW$231 -> 0 | AZ200: =+AW200*$AW$230 -> 0 | BA200: =+AZ200+AY200 -> 0 | BB200: 0 | BC200: =+BB200*$F$1 -> 0 | BD200: =+BB200*$BC$231 -> 0 | BE200: =+BC200*$BC$230 -> 0 | BF200: =+BE200+BD200 -> 0 | BG200: 0 | BH200: =+BG200*$F$1 -> 0 | BI200: =+BG200*$BH$231 -> 0 | BJ200: =+BH200*$BH$230 -> 0 | BK200: =+BJ200+BI200 -> 0 | BL200: 2 | BM200: =+BL200*$F$1 -> 6.8 | BN200: =+BL200*$BM$231 -> 15982.234 | BO200: =+BM200*$BM$230 -> 14404.808 | BP200: =+BO200+BN200 -> 30387.042
...

Sheet DETERMINACIÓN M3 GAS
A2: 2022 | N2: 2023 | AA2: 2024 | AN2: 2025
B5: LECTURAS INSTALACION MEDIDORES COBRO CALDERAS | O5: LECTURAS INSTALACION MEDIDORES COBRO CALDERAS | AB5: LECTURAS INSTALACION MEDIDORES COBRO CALDERAS | AO5: LECTURAS INSTALACION MEDIDORES COBRO CALDERAS
B6: FECHAS | C6: MEDIDOR RED AGUA EEAB | D6: NUEVO MEDIDOR AGUA ZONAS COMUNES M3 | E6: NUEVO MEDIDOR AGUA DUCHAS M3 | F6: NUEVO MEDIDOR GAS ZONAS HUMEDAS M3 | O6: FECHAS | P6: MEDIDOR RED AGUA EEAB | Q6: NUEVO MEDIDOR AGUA ZONAS COMUNES M3 | R6: NUEVO MEDIDOR AGUA DUCHAS M3 | S6: NUEVO MEDIDOR GAS ZONAS HUMEDAS M3 | AB6: FECHAS | AC6: MEDIDOR RED AGUA EEAB | AD6: NUEVO MEDIDOR AGUA ZONAS COMUNES M3 | AE6: NUEVO MEDIDOR AGUA DUCHAS M3 | AF6: NUEVO MEDIDOR GAS ZONAS HUMEDAS M3 | AO6: FECHAS | AP6: MEDIDOR RED AGUA EEAB | AQ6: NUEVO MEDIDOR AGUA ZONAS COMUNES M3 | AR6: NUEVO MEDIDOR AGUA DUCHAS M3 | AS6: NUEVO MEDIDOR GAS ZONAS HUMEDAS M3
B7: 44541 | C7: 118462 | D7: 2.4227 | E7: 0 | F7: 45.011 | O7: 44886 | P7: 125187 | Q7: 601.3755 | R7: 63 | S7: 10446.908 | AB7: 45279 | AC7: 132044 | AD7: 1317.03 | AE7: 131 | AF7: 22604.798 | AO7: 45678 | AP7: 139194 | AQ7: 1960.4629 | AR7: 183 | AS7: 36363.821
B8: 44542 | C8: 118481 | D8: 3.034 | E8: 0 | F8: 79.153 | O8: 44887 | P8: 125210 | Q8: 602.6786 | R8: 63 | S8: 10485.826 | AB8: 45280 | AC8: 132063 | AD8: 1318.58 | AE8: 131 | AF8: 22630.995 | AO8: 45679 | AP8: 139212 | AQ8: 1961.7774 | AR8: 183 | AS8: 36416.302
B9: 44543 | C9: 118506 | D9: 5.0895 | E9: 0 | F9: 85.002 | O9: 44888 | P9: 125218 | Q9: 603.9089 | R9: 63 | S9: 10513.251 | U9: 21 DE NOVIEMBRE A DICIEMBRE 19 | AB9: 45281 | AC9: 132083 | AD9: 1319.95 | AE9: 131 | AF9: 22684.374 | AH9: 19 DE DICIEMBRE A ENERO 20 | AO9: 45680 | AP9: 139231 | AQ9: 1964.0417 | AR9: 183 | AS9: 36416.312 | AU9: 21 DE ENERO A FEBRERO 19
B10: 44544 | C10: 118531 | D10: 6.8829 | E10: 0 | F10: 139.141 | O10: 44889 | P10: 125243 | Q10: 604.8829 | R10: 63 | S10: 10552.575 | U10: TORRES | V10: TORRES | W10: AREAS COMUNES | X10: CALDERAS TORRES | AB10: 45282 | AC10: 132101 | AD10: 1322 | AE10: 131 | AF10: 22740.362 | AH10: TORRES | AI10: TORRES | AJ10: AREAS COMUNES | AK10: CALDERAS TORRES | AO10: 45681 | AP10: 139249 | AQ10: 1965.2826 | AR10: 183 | AS10: 36487.641 | AU10: TORRES | AV10: TORRES | AW10: AREAS COMUNES | AX10: CALDERAS TORRES
B11: 44545 | C11: 118555 | D11: 8.4556 | E11: 0 | F11: 178.329 | O11: 44890 | P11: 125272 | Q11: 607.5774 | R11: 64 | S11: 10587.837 | U11: GAS TORRE A | V11: =+'Vr M3 DE GAS'!AV18 -> 2122 | W11: =+S35-S7 -> 1031.711 | X11: =+V11-W11 -> 1090.289 | Y11: =+X11-K324 -> -229.136 | Z11: =+Y11/K324 -> -0.17366353 | AB11: 45283 | AC11: 132117 | AD11: 1323.23 | AE11: 131 | AF11: 22751.153 | AH11: GAS TORRE A | AI11: ='Vr M3 DE GAS'!BN7 -> 1729 | AJ11: =+AF39-AF7 -> 849.131 | AK11: =+AI11-AJ11 -> 879.869 | AL11: =+AK11-Z324 -> 879.869 | AM11: =+AL11/Y383 -> 1.048298 | AO11: 45682 | AP11: 139263 | AQ11: 1966.2089 | AR11: 183 | AS11: 36540.855 | AU11: GAS TORRE A | AV11: ='Vr M3 DE GAS'!BV8 -> 1968 | AW11: =+AS36-AS7 -> 1082.294 | AX11: =+AV11-AW11 -> 885.706 | AY11: =+AX11-AM324 -> 885.706 | AZ11: =+AY11/AL383 -> 0.95152386
B12: 44546 | C12: 118575 | D12: 9.9401 | E12: 0 | F12: 219.451 | O12: 44891 | P12: 125294 | Q12: 608.6983 | R12: 64 | S12: 10622.268 | U12: GAS TORRE B | V12: =+'Vr M3 DE GAS'!AV36 -> 1383 | X12: =+V12-W12 -> 1383 | Y12: =+X12-K325 -> -172 | Z12: =+Y12/K325 -> -0.11061093 | AB12: 45284 | AC12: 132130 | AD12: 1323.81 | AE12: 131 | AF12: 22765.59 | AH12: GAS TORRE B | AI12: ='Vr M3 DE GAS'!BN25 -> 1077 | AK12: =+AI12-AJ12 -> 1077 | AL12: =+AK12-Z325 -> 1077 | AM12: =+AL12/Y384 -> 1.0385728 | AO12: 45683 | AP12: 139276 | AQ12: 1967.0829 | AR12: 184 | AS12: 36576.872 | AU12: GAS TORRE B | AV12: ='Vr M3 DE GAS'!BV26 -> 908 | AX12: =+AV12-AW12 -> 908 | AY12: =+AX12-AM325 -> 908 | AZ12: =+AY12/AL384 -> 1.0835322
B13: 44547 | C13: 118597 | D13: 10.6154 | E13: 0 | F13: 244.966 | O13: 44892 | P13: 125314 | Q13: 609.7777 | R13: 64 | S13: 10662.612 | U13: GAS TORRE C | V13: =+'Vr M3 DE GAS'!AV54 -> 1371 | X13: =+V13-W13 -> 1371 | Y13: =+X13-K326 -> -205 | Z13: =+Y13/K326 -> -0.13007614 | AB13: 45285 | AC13: 132140 | AD13: 1324.29 | AE13: 131 | AF13: 22787.967 | AH13: GAS TORRE C | AI13: ='Vr M3 DE GAS'!BN43 -> 1221 | AK13: =+AI13-AJ13 -> 1221 | AL13: =+AK13-Z326 -> 1221 | AM13: =+AL13/Y385 -> 1.1009919 | AO13: 45684 | AP13: 139295 | AQ13: 1970.0809 | AR13: 184 | AS13: 36585.624 | AU13: GAS TORRE C | AV13: ='Vr M3 DE GAS'!BV44 -> 810 | AX13: =+AV13-AW13 -> 810 | AY13: =+AX13-AM326 -> 810 | AZ13: =+AY13/AL385 -> 0.97944377
B14: 44548 | C14: 118621 | D14: 13.3267 | E14: 0 | F14: 292.638 | O14: 44893 | P14: 125343 | Q14: 612.25 | R14: 64 | S14: 10685.358 | AB14: 45286 | AC14: 132155 | AD14: 1326.08 | AE14: 131 | AF14: 22827.756 | AO14: 45685 | AP14: 139313 | AQ14: 1971.642 | AR14: 184 | AS14: 36612.483
B15: 44549 | C15: 118635 | D15: 14.1891 | E15: 0 | F15: 348.914 | O15: 44894 | P15: 125367 | Q15: 613.6895 | R15: 64 | S15: 10715.619 | U15: TOTAL EDIFICIO | V15: =SUM(V11:V14) -> 4876 | W15: =+W11 -> 1031.711 | X15: =SUM(X11:X14) -> 3844.289 | Y15: =+X15-K328 -> -606.136 | Z15: =+Y15/K328 -> -0.13619733 | AB15: 45287 | AC15: 132169 | AD15: 1328.59 | AE15: 131 | AF15: 22869.339 | AH15: TOTAL EDIFICIO | AI15: =SUM(AI11:AI14) -> 4027 | AJ15: =+AJ11 -> 849.131 | AK15: =SUM(AK11:AK14) -> 3177.869 | AL15: =+AK15-Z328 -> 3177.869 | AM15: =+AL15/X387 -> 1.0644947 | AO15: 45686 | AP15: 139332 | AQ15: 1974.3663 | AR15: 184 | AS15: 36685.713 | AU15: TOTAL EDIFICIO | AV15: =SUM(AV11:AV14) -> 3686 | AW15: =+AW11 -> 1082.294 | AX15: =SUM(AX11:AX14) -> 2603.706 | AY15: =+AX1-AM328 -> 0 | AZ15: =+AY15/AK387 -> 0
B16: 44550 | C16: 118655 | D16: 16.6413 | E16: 0 | F16: 354.542 | H16: ANALISIS PARA GAS A PAGAR EN FEBRERO | O16: 44895 | P16: 125392 | Q16: 614.9698 | R16: 64 | S16: 10752.461 | AB16: 45288 | AC16: 132182 | AD16: 1329.54 | AE16: 131 | AF16: 22884.108 | AO16: 45687 | AP16: 139348 | AQ16: 1975.4131 | AR16: 184 | AS16: 36708.914
B17: 44551 | C17: 118676 | D17: 18.661 | E17: 0 | F17: 396.057 | H17: 18 DIC A 21 DE ENERO | O17: 44896 | P17: 125420 | Q17: 615.968 | R17: 64 | S17: 10785.894 | AB17: 45289 | AC17: 132194 | AD17: 1330.26 | AE17: 131 | AF17: 22909.595 | AO17: 45688 | AP17: 139367 | AQ17: 1977.5527 | AR17: 185 | AS17: 36714.816
B18: 44552 | C18: 118695 | D18: 20.2081 | E18: 0 | F18: 432.577 | I18: TORRES | J18: AREAS COMUNES | K18: TORRES | O18: 44897 | P18: 125470 | Q18: 620.2113 | R18: 64 | S18: 10906.983 | U18: AGUA | AB18: 45290 | AC18: 132204 | AD18: 1331.91 | AE18: 131 | AF18: 22925.323 | AH18: AGUA | AO18: 45689 | AP18: 139383 | AQ18: 1978.444 | AR18: 185 | AS18: 36746.749 | AU18: AGUA
B19: 44553 | C19: 118710 | D19: 21.7313 | E19: 1 | F19: 460.224 | H19: TORRE A | I19: =+'Vr M3 DE GAS'!AV7 -> 2307 | J19: =+F48-F14 -> 1284.202 | K19: =+I19-J19 -> 1022.798 | O19: 44898 | P19: 125475 | Q19: 620.5943 | R19: 65 | S19: 10906.985 | AB19: 45291 | AC19: 132213 | AD19: 1332.5 | AE19: 131 | AF19: 22925.369 | AO19: 45690 | AP19: 139397 | AQ19: 1978.8266 | AR19: 185 | AS19: 39779.466
B20: 44554 | C20: 118725 | D20: 22.2733 | E20: 1 | F20: 493.064 | H20: TORRE B | I20: =+'Vr M3 DE GAS'!AV25 -> 1079 | K20: =+I20-J20 -> 1079 | O20: 44899 | P20: 125491 | Q20: 621.8484 | R20: 65 | S20: 10949.421 | U20: TOTAL CALLEJA | V20: =+P35-P7 -> 654 | AB20: 45292 | AC20: 132218 | AD20: 1332.6608 | AE20: 131 | AF20: 22925.372 | AH20: TOTAL CALLEJA | AI20: =+AC39-AC7 -> 456 | AO20: 45691 | AP20: 139419 | AQ20: 1982.5028 | AR20: 185 | AS20: 36779.486 | AU20: TOTAL CALLEJA | AV20: =+AP36-AP7 -> 511
B21: 44555 | C21: 118734 | D21: 22.6903 | E21: 1 | F21: 521.05 | H21: TORRE C | I21: =+'Vr M3 DE GAS'!AV43 -> 1339 | K21: =+I21-J21 -> 1339 | O21: 44900 | P21: 125519 | Q21: 624.1462 | R21: 65 | S21: 10984.678 | U21: AREAS COMUNES | V21: =+Q35-Q7 -> 43.0667 | AB21: 45293 | AC21: 132227 | AD21: 1333.9341 | AE21: 131 | AF21: 22978.77 | AH21: AREAS COMUNES | AI21: =+AD39-AD7 -> 40.0947 | AO21: 45692 | AP21: 139431 | AQ21: 1983.974 | AR21: 185 | AS21: 36836.739 | AU21: AREAS COMUNES | AV21: =+AQ36-AQ7 -> 47.7836
B22: 44556 | C22: 118745 | D22: 24.1576 | E22: 1 | F22: 579.153 | O22: 44901 | P22: 125543 | Q22: 625.2522 | R22: 65 | S22: 11010.497 | U22: APARTAMENTOS | V22: =+V20-V21 -> 610.9333 | AB22: 45294 | AC22: 132237 | AD22: 1334.5338 | AE22: 131 | AF22: 23012.847 | AH22: APARTAMENTOS | AI22: =+AI20-AI21 -> 415.9053 | AO22: 45693 | AP22: 139459 | AQ22: 1986.5423 | AR22: 185 | AS22: 36877.205 | AU22: APARTAMENTOS | AV22: =+AV20-AV21 -> 463.2164
B23: 44557 | C23: 118762 | D23: 27.133 | E23: 2 | F23: 580.414 | I23: =SUM(I19:I22) -> 4725 | K23: =+K19+K20+K21 -> 3440.798 | O23: 44902 | P23: 125569 | Q23: 626.9417 | R23: 65 | S23: 11051.8 | AB23: 45295 | AC23: 132247 | AD23: 1335.2617 | AE23: 131 | AF23: 23049.066 | AO23: 45694 | AP23: 139476 | AQ23: 1987.74 | AR23: 185 | AS23: 36894.36
B24: 44558 | C24: 118777 | D24: 29.7512 | E24: 2 | F24: 644.272 | O24: 44903 | P24: 125586 | Q24: 627.5712 | R24: 66 | S24: 11095.042 | AB24: 45296 | AC24: 132259 | AD24: 1337.0141 | AE24: 131 | AF24: 23070.798 | AO24: 45695 | AP24: 139496 | AQ24: 1989.7745 | AR24: 185 | AS24: 36921.906
B25: 44559 | C25: 118789 | D25: 30.5447 | E25: 2 | F25: 682.621 | O25: 44904 | P25: 125609 | Q25: 629.2467 | R25: 66 | S25: 11133.708 | U25: SE CONSUMIERON | V25: =+V22 -> 610.9333 | W25: DE AGUA CALIENTE | Y25: =+V25-I338 -> 58.2199 | Z25: =+Y25/I338 -> 0.1053347 | AB25: 45297 | AC25: 132268 | AD25: 1337.6614 | AE25: 131 | AF25: 23090.685 | AH25: SE CONSUMIERON | AI25: =+AI22 -> 415.9053 | AJ25: DE AGUA CALIENTE | AL25: =AI25/V397-100% -> -0.17150339 | AO25: 45696 | AP25: 139511 | AQ25: 1990.536 | AR25: 186 | AS25: 36982.803 | AU25: SE CONSUMIERON | AV25: =+AV22 -> 463.2164 | AW25: DE AGUA CALIENTE | AY25: =AV25/AI397-1 -> -0.010221368
B26: 44560 | C26: 118801 | D26: 31.426 | E26: 3 | F26: 727.28 | H26: CONSUMO DE AGUA ENTRE EL 21 DE ENERO Y EL 18 DE FEBRERO | O26: 44905 | P26: 125628 | Q26: 630.2533 | R26: 66 | S26: 11167.212 | AB26: 45298 | AC26: 132279 | AD26: 1338.0929 | AE26: 131 | AF26: 23090.772 | AO26: 45697 | AP26: 139525 | AQ26: 1990.6969 | AR26: 186 | AS26: 37040.125
B27: 44561 | C27: 118809 | D27: 34.2909 | E27: 3 | F27: 747.082 | O27: 44906 | P27: 125646 | Q27: 630.9788 | R27: 66 | S27: 11231.902 | U27: SE CONSUMIO DE GAS | V27: =+X15 -> 3844.289 | W27: M3 EN CALDERAS | Y27: =+V27-I340 -> -606.136 | Z27: =+Y27/I340 -> -0.13619733 | AB27: 45299 | AC27: 132293 | AD27: 1338.3377 | AE27: 131 | AF27: 23152.989 | AH27: SE CONSUMIO DE GAS | AI27: =+AK15 -> 3177.869 | AJ27: M3 EN CALDERAS | AL27: =AI27/V399-100% -> 0.064494691 | AO27: 45698 | AP27: 139545 | AQ27: 1993.5854 | AR27: 186 | AS27: 37050.288 | AU27: SE CONSUMIO DE GAS | AV27: =+AX15 -> 2603.706 | AW27: M3 EN CALDERAS | AY27: =AV27/AI399-1 -> 0.0030344834
B28: 44562 | C28: 118824 | D28: 34.8801 | E28: 3 | F28: 792.934 | H28: TOTAL CALLEJA | I28: =+C48-C14 -> 577 | O28: 44907 | P28: 125673 | Q28: 633.4956 | R28: 66 | S28: 11264.519 | AB28: 45300 | AC28: 132307 | AD28: 1340.2743 | AE28: 131 | AF28: 23157.448 | AO28: 45699 | AP28: 139562 | AQ28: 1994.4859 | AR28: 186 | AS28: 37064.816
B29: 44563 | C29: 118836 | D29: 38.4873 | E29: 3 | F29: 812.753 | H29: AREAS COMUNES | I29: =+D48-D14 -> 75.8283 | O29: 44908 | P29: 125700 | Q29: 635.1252 | R29: 67 | S29: 11281.02 | U29: SE REQUIERIO | V29: =+V27/V25 -> 6.2924856 | W29: M3 DE GAS PARA CALENTAR 1 M3 DE AGUA | AB29: 45301 | AC29: 132323 | AD29: 1341.1288 | AE29: 131 | AF29: 23203.473 | AH29: SE REQUIERIO | AI29: =+AI27/AI25 -> 7.6408476 | AJ29: M3 DE GAS PARA CALENTAR 1 M3 DE AGUA | AO29: 45700 | AP29: 139581 | AQ29: 1996.47 | AR29: 186 | AS29: 37147.822 | AU29: SE REQUIERIO | AV29: =+AV27/AV25 -> 5.6209279 | AW29: M3 DE GAS PARA CALENTAR 1 M3 DE AGUA
B30: 44564 | C30: 118849 | D30: 39.5116 | E30: 3 | F30: 843.103 | H30: APARTAMENTOS | I30: =+I28-I29 -> 501.1717 | O30: 44909 | P30: 125725 | Q30: 636.7384 | R30: 67 | S30: 11323.808 | AB30: 45302 | AC30: 132342 | AD30: 1342.4597 | AE30: 131 | AF30: 23245.002 | AO30: 45701 | AP30: 139599 | AQ30: 1997.8749 | AR30: 186 | AS30: 37193.721
B31: 44565 | C31: 118862 | D31: 41.433 | E31: 3 | F31: 877 | O31: 44910 | P31: 125751 | Q31: 638.4419 | R31: 67 | S31: 11370.328 | AB31: 45303 | AC31: 132361 | AD31: 1345.4893 | AE31: 132 | AF31: 23265.322 | AO31: 45702 | AP31: 139621 | AQ31: 2001.4149 | AR31: 187 | AS31: 37288.912
B32: 44566 | C32: 118891 | D32: 54.8007 | E32: 3 | F32: 925.548 | O32: 44911 | P32: 125778 | Q32: 640.4033 | R32: 67 | S32: 11400.502 | AB32: 45304 | AC32: 132376 | AD32: 1345.8289 | AE32: 132 | AF32: 23297.636 | AO32: 45703 | AP32: 139636 | AQ32: 2002.3015 | AR32: 187 | AS32: 37335.397
B33: 44567 | C33: 118907 | D33: 57.7752 | E33: 3 | F33: 964.967 | H33: SE CONSUMIERON | I33: =+I30 -> 501.1717 | J33: DE AGUA CALIENTE | O33: 44912 | P33: 125801 | Q33: 641.7631 | R33: 68 | S33: 11437.736 | AB33: 45305 | AC33: 132390 | AD33: 1346.2573 | AE33: 132 | AF33: 23325.355 | AO33: 45704 | AP33: 139650 | AQ33: 2003.2219 | AR33: 187 | AS33: 37353.338
B34: 44568 | C34: 118922 | D34: 58.9161 | E34: 3 | F34: 992.413 | O34: 44913 | P34: 125816 | Q34: 642.6565 | R34: 68 | S34: 11464.317 | AB34: 45306 | AC34: 132409 | AD34: 1348.2404 | AE34: 132 | AF34: 23335.712 | AO34: 45705 | AP34: 139670 | AQ34: 2004.7356 | AR34: 187 | AS34: 37353.345
B35: 44569 | C35: 118935 | D35: 60.6397 | E35: 4 | F35: 1060.098 | H35: SE CONSUMIO DE GAS | I35: =+K23 -> 3440.798 | J35: EN CALDERAS | O35: 44914 | P35: 125841 | Q35: 644.4422 | R35: 68 | S35: 11478.619 | AB35: 45307 | AC35: 132426 | AD35: 1349.2912 | AE35: 132 | AF35: 23373.279 | AO35: 45706 | AP35: 139688 | AQ35: 2006.7369 | AR35: 187 | AS35: 37442.282
B36: 44570 | C36: 118948 | D36: 62.6325 | E36: 4 | F36: 1093.259 | O36: 44915 | P36: 125865 | Q36: 646.9105 | R36: 68 | S36: 11520.85 | AB36: 45308 | AC36: 132444 | AD36: 1351.7347 | AE36: 132 | AF36: 23403.903 | AO36: 45707 | AP36: 139705 | AQ36: 2008.2465 | AR36: 187 | AS36: 37446.115
B37: 44571 | C37: 118966 | D37: 62.7136 | E37: 4 | F37: 1175.226 | H37: SE REQUIERIO | I37: =+I35/I33 -> 6.8655074 | J37: M3 DE GAS PARA CALENTAR 1 M3 DE ACAUA | O37: 44916 | P37: 125888 | Q37: 647.8818 | R37: 68 | S37: 11544.809 | U37: 19 DCIIEMBRE A 20 DE ENERO | AB37: 45309 | AC37: 132462 | AD37: 1353.2787 | AE37: 132 | AF37: 23423.818 | AH37: 20 DE ENERO A 20 DE FEBRERO | AO37: 45708 | AP37: 139723 | AQ37: 2009.649 | AR37: 188 | AS37: 37538.974 | AU37: 19 DE FEBRERO A MARZO 19
B38: 44572 | C38: 118990 | D38: 68.3458 | E38: 5 | F38: 1196.555 | O38: 44917 | P38: 125909 | Q38: 648.8375 | R38: 69 | S38: 11574.544 | U38: TORRES | V38: TORRES | W38: AREAS COMUNES | X38: CALDERAS TORRES | AB38: 45310 | AC38: 132481 | AD38: 1355.4263 | AE38: 132 | AF38: 23453.711 | AH38: TORRES | AI38: TORRES | AJ38: AREAS COMUNES | AK38: CALDERAS TORRES | AO38: 45709 | AP38: 139747 | AQ38: 2014.7247 | AR38: 188 | AS38: 37566.752 | AU38: TORRES | AV38: TORRES | AW38: ZONAS HUMEDAS | AX38: CALDERAS TORRES
B39: 44573 | C39: 119010 | D39: 69.8943 | E39: 5 | F39: 1233.961 | O39: 44918 | P39: 125932 | Q39: 650.0267 | R39: 69 | S39: 11610.155 | U39: GAS TORRE A | V39: =+'Vr M3 DE GAS'!BE7 -> 1912 | W39: =+S67-S35 -> 956.135 | X39: =+V39-W39 -> 955.865 | Y39: =+X39-X11 -> -134.424 | AB39: 45311 | AC39: 132500 | AD39: 1357.1247 | AE39: 132 | AF39: 23453.929 | AH39: GAS TORRE A | AI39: =+'Vr M3 DE GAS'!BN8 -> 1738 | AJ39: =+AF70-AF39 -> 776.487 | AK39: =+AI39-AJ39 -> 961.513 | AL39: =+AK39-AK11 -> 81.644 | AO39: 45710 | AP39: 139766 | AQ39: 2016.5342 | AR39: 188 | AS39: 37585.241 | AU39: GAS TORRE A | AV39: =+'Vr M3 DE GAS'!BV9 -> 1735 | AW39: =+AS70-AS39 -> 1062.519 | AX39: =+AV39-AW39 -> 672.481 | AY39: =+AX39-AX11 -> -213.225
B40: 44574 | C40: 119020 | D40: 71.7333 | E40: 5 | F40: 1280.8 | O40: 44919 | P40: 125950 | Q40: 651.9128 | R40: 69 | S40: 11642.975 | U40: GAS TORRE B | V40: =+'Vr M3 DE GAS'!BE25 -> 1365 | X40: =+V40-W40 -> 1365 | Y40: =+X40-X12 -> -18 | AB40: 45312 | AC40: 132511 | AD40: 1357.5114 | AE40: 132 | AF40: 23511.655 | AH40: GAS TORRE B | AI40: =+'Vr M3 DE GAS'!BN26 -> 1327 | AK40: =+AI40-AJ40 -> 1327 | AL40: =+AK40-AK12 -> 250 | AO40: 45711 | AP40: 139780 | AQ40: 2017.1428 | AR40: 188 | AS40: 37624.525 | AU40: GAS TORRE B | AV40: =+'Vr M3 DE GAS'!BV27 -> 897 | AX40: =+AV40-AW40 -> 897 | AY40: =+AX40-AX12 -> -11
B41: 44575 | C41: 119050 | D41: 74.3675 | E41: 5 | F41: 1335.07 | O41: 44920 | P41: 125962 | Q41: 652.4276 | R41: 69 | S41: 11666.977 | U41: GAS TORRE C | V41: =+'Vr M3 DE GAS'!BE43 -> 1361 | X41: =+V41-W41 -> 1361 | Y41: =+X41-X13 -> -10 | AB41: 45313 | AC41: 132531 | AD41: 1359.848 | AE41: 132 | AF41: 23511.702 | AH41: GAS TORRE C | AI41: =+'Vr M3 DE GAS'!BN44 -> 1353 | AK41: =+AI41-AJ41 -> 1353 | AL41: =+AK41-AK13 -> 132 | AO41: 45712 | AP41: 139801 | AQ41: 2019.955 | AR41: 188 | AS41: 37624.529 | AU41: GAS TORRE C | AV41: =+'Vr M3 DE GAS'!BV45 -> 823 | AX41: =+AV41-AW41 -> 823 | AY41: =+AX41-AX13 -> 13
B42: 44576 | C42: 119069 | D42: 76.202 | E42: 6 | F42: 1384.023 | O42: 44921 | P42: 125980 | Q42: 654.3384 | R42: 70 | S42: 11691.982 | AB42: 45314 | AC42: 132550 | AD42: 1361.5217 | AE42: 132 | AF42: 23571.849 | AO42: 45713 | AP42: 139819 | AQ42: 2021.2861 | AR42: 188 | AS42: 37630.053
B43: 44577 | C43: 119087 | D43: 77.5026 | E43: 6 | F43: 1436.447 | O43: 44922 | P43: 125996 | Q43: 655.5697 | R43: 70 | S43: 11724.591 | U43: TOTAL EDIFICIO | V43: =SUM(V39:V42) -> 4638 | W43: =+W39 -> 956.135 | X43: =SUM(X39:X42) -> 3681.865 | Y43: =+X43-X15 -> -162.424 | AB43: 45315 | AC43: 132569 | AD43: 1363.1217 | AE43: 132 | AF43: 23572.237 | AH43: TOTAL EDIFICIO | AI43: =SUM(AI39:AI42) -> 4418 | AJ43: =+AJ39 -> 776.487 | AK43: =SUM(AK39:AK42) -> 3641.513 | AL43: =+AK43-AK15 -> 463.644 | AO43: 45714 | AP43: 139837 | AQ43: 2023.0487 | AR43: 188 | AS43: 37692.758 | AU43: TOTAL EDIFICIO | AV43: =SUM(AV39:AV42) -> 3455 | AW43: =+AW39 -> 1062.519 | AX43: =SUM(AX39:AX42) -> 2392.481 | AY43: =+AX43-AX15 -> -211.225
B44: 44578 | C44: 119107 | D44: 78.6593 | E44: 6 | F44: 1458.74 | O44: 44923 | P44: 126012 | Q44: 656.5742 | R44: 70 | S44: 11750.29 | AB44: 45316 | AC44: 132596 | AD44: 1371.5939 | AE44: 132 | AF44: 23617.166 | AO44: 45715 | AP44: 139857 | AQ44: 2024.772 | AR44: 188 | AS44: 37727.882
B45: 44579 | C45: 119116 | D45: 79.5432 | E45: 6 | F45: 1464.21 | O45: 44924 | P45: 126026 | Q45: 657.6014 | R45: 70 | S45: 11780.963 | AB45: 45317 | AC45: 132623 | AD45: 1381.7231 | AE45: 132 | AF45: 23629.37 | AO45: 45716 | AP45: =AP44+20 -> 139877 | AQ45: 2026.4953 | AR45: 188 | AS45: 37763.006
B46: 44580 | C46: 119149 | D46: 80.7762 | E46: 6 | F46: 1517.615 | O46: 44925 | P46: 126038 | Q46: 660.0935 | R46: 71 | S46: 11819.756 | U46: AGUA | AB46: 45318 | AC46: 132643 | AD46: 1385.3074 | AE46: 132 | AF46: 23657.288 | AH46: AGUA | AO46: 45717 | AP46: 139894 | AQ46: 2027.8471 | AR46: 188 | AS46: 37773.203 | AU46: AGUA
B47: 44581 | C47: 119171 | D47: 82.8612 | E47: 6 | F47: 1545.201 | O47: 44926 | P47: 126048 | Q47: 660.6131 | R47: 71 | S47: 11836.809 | AB47: 45319 | AC47: 132662 | AD47: 1390.1186 | AE47: 134 | AF47: 23657.644 | AO47: 45718 | AP47: 139909 | AQ47: 2028.5022 | AR47: 188 | AS47: 37773.216
B48: 44582 | C48: 119198 | D48: 89.155 | E48: 6 | F48: 1576.84 | O48: 44927 | P48: 126052 | Q48: 660.9367 | R48: 71 | S48: 11860.752 | U48: TOTAL CALLEJA | V48: =+P67-P35 -> 561 | AB48: 45320 | AC48: 132681 | AD48: 1393.2034 | AE48: 134 | AF48: 23657.766 | AH48: TOTAL CALLEJA | AI48: =+AC70-AC39 -> 559 | AO48: 45719 | AP48: 139929 | AQ48: 2030.5016 | AR48: 188 | AS48: 37825.373 | AU48: TOTAL CALLEJA | AV48: =+AP64-AP36 -> 516
B49: 44583 | C49: 119219 | D49: 92.704 | E49: 6 | F49: 1601.717 | O49: 44928 | P49: 126060 | Q49: 661.5406 | R49: 71 | S49: 11874.957 | U49: AREAS COMUNES | V49: =+Q67-Q35 -> 43.9077 | AB49: 45321 | AC49: 132698 | AD49: 1395.0959 | AE49: 135 | AF49: 23713.037 | AH49: AREAS COMUNES | AI49: =+AD70-AD39 -> 72.5231 | AO49: 45720 | AP49: 139951 | AQ49: 2033.1155 | AR49: 188 | AS49: 37861.777 | AU49: AREAS COMUNES | AV49: =+AQ64-AQ36 -> 55.5522
B50: 44584 | C50: 119224 | D50: 93.0491 | E50: 7 | F50: 1610.654 | H50: ANALISIS PARA GAS A PAGAR EN MARZO | O50: 44929 | P50: 126076 | Q50: 662.6735 | R50: 71 | S50: 11913.556 | U50: APARTAMENTOS | V50: =+V48-V49 -> 517.0923 | AB50: 45322 | AC50: 132724 | AD50: 1403.8818 | AE50: 135 | AF50: 23724.028 | AH50: APARTAMENTOS | AI50: =+AI48-AI49 -> 486.4769 | AO50: 45721 | AP50: 139972 | AQ50: 2035.0783 | AR50: 188 | AS50: 37913.192 | AU50: APARTAMENTOS | AV50: =+AV48-AV49 -> 460.4478
B51: 44585 | C51: 119229 | D51: 93.5701 | E51: 7 | F51: 1618.432 | H51: 21 ENERO A 18 DE FEBERERO | O51: 44930 | P51: 126088 | Q51: 663.6216 | R51: 71 | S51: 11938.987 | AB51: 45323 | AC51: 132741 | AD51: 1405.4017 | AE51: 135 | AF51: 23750.851 | AO51: 45722 | AP51: 139994 | AQ51: 2041.2465 | AR51: 188 | AS51: 37954.978
B52: 44586 | C52: 119232 | D52: 93.6105 | E52: 7 | F52: 1625.654 | I52: TORRES | J52: AREAS COMUNES | K52: TORRES | O52: 44931 | P52: 126100 | Q52: 664.5023 | R52: 72 | S52: 11973.611 | AB52: 45324 | AC52: 132757 | AD52: 1406.1824 | AE52: 135 | AF52: 23750.859 | AO52: 45723 | AP52: 140016 | AQ52: 2042.9899 | AR52: 188 | AS52: 37986.016
B53: 44587 | C53: 119236 | D53: 93.715 | E53: 7 | F53: 1630.472 | H53: TORRE A | I53: 1669 | J53: =+F76-F48 -> 721.62 | K53: =+I53-J53 -> 947.38 | O53: 44932 | P53: 126114 | Q53: 665.8808 | R53: 72 | S53: 12006.197 | U53: SE CONSUMIERON | V53: =+V50 -> 517.0923 | W53: DE AGUA CALIENTE | Y53: =+V53-V25 -> -93.841 | AB53: 45325 | AC53: 132773 | AD53: 1407.2376 | AE53: 135 | AF53: 23750.866 | AH53: SE CONSUMIERON | AI53: =+AI50 -> 486.4769 | AJ53: DE AGUA CALIENTE | AL53: =+AI53-AI25 -> 70.5716 | AO53: 45724 | AP53: 140032 | AQ53: 2044.7319 | AR53: 190 | AS53: 38026.75 | AU53: SE CONSUMIERON | AV53: =+AV50 -> 460.4478 | AW53: DE AGUA CALIENTE | AY53: =+AV53-AV25 -> -2.7686
B54: 44588 | C54: 119324 | D54: 102.2591 | E54: 8 | F54: 1753.181 | H54: TORRE B | I54: 1259 | K54: =+I54-J54 -> 1259 | O54: 44933 | P54: 126127 | Q54: 667.1718 | R54: 72 | S54: 12045.216 | AB54: 45326 | AC54: 132787 | AD54: 1407.8886 | AE54: 135 | AF54: 23750.873 | AO54: 45725 | AP54: 140044 | AQ54: 2045.0893 | AR54: 190 | AS54: 38051.681
B55: 44589 | C55: 119345 | D55: 103.6239 | E55: 8 | F55: 1776.244 | H55: TORRE C | I55: 1058 | K55: =+I55-J55 -> 1058 | O55: 44934 | P55: 126139 | Q55: 667.9351 | R55: 72 | S55: 12098.324 | U55: SE CONSUMIO DE GAS | V55: =+X43 -> 3681.865 | W55: M3 EN CALDERAS | Y55: =+V55-V27 -> -162.424 | AB55: 45327 | AC55: 132806 | AD55: 1408.8803 | AE55: 135 | AF55: 23750.881 | AH55: SE CONSUMIO DE GAS | AI55: =+AK43 -> 3641.513 | AJ55: M3 EN CALDERAS | AL55: =+AI55-AI27 -> 463.644 | AO55: 45726 | AP55: 140062 | AQ55: 2046.7928 | AR55: 190 | AS55: 38086.683 | AU55: SE CONSUMIO DE GAS | AV55: =+AX43 -> 2392.481 | AW55: M3 EN CALDERAS | AY55: =+AV55-AV27 -> -211.225
B56: 44590 | C56: 119366 | D56: 106.2379 | E56: 8 | F56: 1803.807 | O56: 44935 | P56: 126152 | Q56: 669.1613 | R56: 72 | S56: 12135.914 | AB56: 45328 | AC56: 132825 | AD56: 1409.954 | AE56: 135 | AF56: 23750.889 | AO56: 45727 | AP56: 140082 | AQ56: 2048.8999 | AR56: 190 | AS56: 38131.152
B57: 44591 | C57: 119399 | D57: 109.6192 | E57: 9 | F57: 1847.893 | H57: TOTAL EDIFICIO | K57: =SUM(K53:K56) -> 3264.38 | O57: 44936 | P57: 126174 | Q57: 672.9299 | R57: 72 | S57: 12157.312 | U57: SE REQUIERIO | V57: =+V55/V53 -> 7.1203246 | W57: M3 DE GAS PARA CALENTAR 1 M3 DE AGUA | AB57: 45329 | AC57: 132842 | AD57: 1410.6783 | AE57: 135 | AF57: 23787.948 | AH57: SE REQUIERIO | AI57: =+AI55/AI53 -> 7.4854798 | AJ57: M3 DE GAS PARA CALENTAR 1 M3 DE AGUA | AO57: 45728 | AP57: 140100 | AQ57: 2050.9625 | AR57: 190 | AS57: 38165.601 | AU57: SE REQUIERIO | AV57: =+AV55/AV53 -> 5.1959875 | AW57: M3 DE GAS PARA CALENTAR 1 M3 DE AGUA
B58: 44592 | C58: 119405 | D58: 111.0299 | E58: 9 | F58: 1851.217 | I58: =SUM(I53:I57) -> 3986 | O58: 44937 | P58: 126194 | Q58: 673.7866 | R58: 72 | S58: 12196.871 | AB58: 45330 | AC58: 132862 | AD58: 1413.9518 | AE58: 135 | AF58: 23864.674 | AO58: 45729 | AP58: 140119 | AQ58: 2052.3622 | AR58: 190 | AS58: 38190.423
B59: 44593 | C59: 119429 | D59: 113.1275 | E59: 9 | F59: 1876.011 | O59: 44938 | P59: 126216 | Q59: 674.9206 | R59: 72 | S59: 12230.969 | AB59: 45331 | AC59: 132880 | AD59: 1415.0168 | AE59: 135 | AF59: 23909.919 | AO59: 45730 | AP59: 140140 | AQ59: 2055.8169 | AR59: 191 | AS59: 38227.849
B60: 44594 | C60: 119451 | D60: 114.0837 | E60: 9 | F60: 1895.936 | H60: CONSUMO DE AGUA ENTRE EL 21 DE ENERO Y EL 18 DE FEBRERO | O60: 44939 | P60: 126235 | Q60: 676.1499 | R60: 72 | S60: 12235.67 | AB60: 45332 | AC60: 132895 | AD60: 1416.001 | AE60: 135 | AF60: 23925.249 | AO60: 45731 | AP60: 140156 | AQ60: 2057.7601 | AR60: 191 | AS60: 38271.217
B61: 44595 | C61: 119474 | D61: 116.7684 | E61: 9 | F61: 1919.483 | O61: 44940 | P61: 126255 | Q61: 678.6993 | R61: 72 | S61: 12296.966 | AB61: 45333 | AC61: 132907 | AD61: 1416.4696 | AE61: 135 | AF61: 23943.346 | AO61: 45732 | AP61: 140168 | AQ61: 2058.8269 | AR61: 191 | AS61: 38314.251
B62: 44596 | C62: 119495 | D62: 118.6347 | E62: 9 | F62: 1953.703 | H62: TOTAL CALLEJA | I62: =+C76-C48 -> 569 | O62: 44941 | P62: 126273 | Q62: 679.5088 | R62: 72 | S62: 12367.796 | AB62: 45334 | AC62: 132927 | AD62: 1418.3041 | AE62: 135 | AF62: 23967.044 | AO62: 45733 | AP62: 140188 | AQ62: 2060.49 | AR62: 191 | AS62: 38320.97
B63: 44597 | C63: 119514 | D63: 119.7699 | E63: 10 | F63: 1977.628 | H63: AREAS COMUNES | I63: =+D76-D48 -> 48.5329 | O63: 44942 | P63: 126300 | Q63: 682.4603 | R63: 73 | S63: 12368.127 | AB63: 45335 | AC63: 132943 | AD63: 1420.164 | AE63: 135 | AF63: 24016.7 | AO63: 45734 | AP63: =AP62+20 -> 140208 | AQ63: 2061.3254 | AR63: 191 | AS63: 38332.141
B64: 44598 | C64: 119529 | D64: 120.1965 | E64: 10 | F64: 2003.586 | H64: APARTAMENTOS | I64: =+I62-I63 -> 520.4671 | O64: 44943 | P64: 126325 | Q64: 684.0556 | R64: 73 | S64: 12408.64 | AB64: 45336 | AC64: 132960 | AD64: 1421.1477 | AE64: 135 | AF64: 24059.336 | AO64: 45735 | AP64: 140221 | AQ64: 2063.7987 | AR64: 191 | AS64: 38410.585
B65: 44599 | C65: 119550 | D65: 121.3723 | E65: 10 | F65: 2024.144 | O65: 44944 | P65: 126351 | Q65: 686.0896 | R65: 73 | S65: 12434.725 | AB65: 45337 | AC65: 132978 | AD65: 1423.7855 | AE65: 135 | AF65: 24096.578 | AO65: 45736 | AP65: 140240 | AQ65: 2066.1584 | AR65: 191 | AS65: 38466.243
B66: 44600 | C66: 119571 | D66: 122.4964 | E66: 10 | F66: 2047.201 | O66: 44945 | P66: 126376 | Q66: 687.45 | R66: 73 | S66: 12434.739 | AB66: 45338 | AC66: 132994 | AD66: 1424.4482 | AE66: 136 | AF66: 24150.414 | AO66: 45737 | AP66: 140258 | AQ66: 2068.846 | AR66: 192 | AS66: 38504.987
B67: 44601 | C67: 119592 | D67: 123.4528 | E67: 11 | F67: 2061.398 | H67: SE CONSUMIERON | I67: =+I64 -> 520.4671 | J67: DE AGUA CALIENTE | O67: 44946 | P67: 126402 | Q67: 688.3499 | R67: 73 | S67: 12434.754 | AB67: 45339 | AC67: 133012 | AD67: 1425.9111 | AE67: 136 | AF67: 24170.838 | AO67: 45738 | AP67: 140270 | AQ67: 2071.1191 | AR67: 193 | AS67: 38545.83
B68: 44602 | C68: 119613 | D68: 124.8703 | E68: 11 | F68: 2095.601 | O68: 44947 | P68: 126424 | Q68: 689.4121 | R68: 73 | S68: 12443.251 | AB68: 45340 | AC68: 133026 | AD68: 1426.4086 | AE68: 136 | AF68: 24191.936 | AO68: 45739 | AP68: 140275 | AQ68: 2073.1873 | AR68: 193 | AS68: 38596.054
B69: 44603 | C69: 119631 | D69: 125.5398 | E69: 11 | F69: 2123.258 | H69: SE CONSUMIO DE GAS | I69: =+K57 -> 3264.38 | J69: EN CALDERAS | O69: 44948 | P69: 126444 | Q69: 690.2412 | R69: 73 | S69: 12460.208 | U69: 20 DE ENERO A 18 DE FEBRERO | AB69: 45341 | AC69: 133041 | AD69: 1428.6568 | AE69: 136 | AF69: 24191.944 | AH69: 20 DE FEBRERO A 18 DE MARZO | AO69: 45740 | AP69: 140287 | AQ69: 2073.1584 | AR69: 193 | AS69: 38647.757 | AU69: 19 DE MARZO A ABRIL 21
B70: 44604 | C70: 119649 | D70: 127.8704 | E70: 11 | F70: 2148.247 | O70: 44949 | P70: 126470 | Q70: 691.655 | R70: 73 | S70: 12503.591 | U70: TORRES | V70: TORRES | W70: AREAS COMUNES | X70: CALDERAS TORRES | AB70: 45342 | AC70: 133059 | AD70: 1429.6478 | AE70: 136 | AF70: 24230.416 | AH70: TORRES | AI70: TORRES | AJ70: AREAS COMUNES | AK70: CALDERAS TORRES | AO70: 45741 | AP70: 140305 | AQ70: 2074.1121 | AR70: 193 | AS70: 38647.76 | AU70: TORRES | AV70: TORRES | AW70: AREAS COMUNES | AX70: CALDERAS TORRES
B71: 44605 | C71: 119666 | D71: 129.7539 | E71: 11 | F71: 2176.014 | H71: SE REQUIERIO | I71: =+I69/I67 -> 6.2720199 | J71: M3 DE GAS PARA CALENTAR 1 M3 DE ACAUA | O71: 44950 | P71: 126497 | Q71: 692.6968 | R71: 73 | S71: 12538.134 | U71: GAS TORRE A | V71: =+'Vr M3 DE GAS'!BE8 -> 2357 | W71: =+S96-S67 -> 972.934 | X71: =+V71-W71 -> 1384.066 | Y71: =+X71-#REF! -> #REF! | AB71: 45343 | AC71: 133076 | AD71: 1430.55 | AE71: 136 | AF71: 24265.169 | AH71: GAS TORRE A | AI71: =+'Vr M3 DE GAS'!BN9 -> 1533 | AJ71: =+AF97-AF70 -> 708.118 | AK71: =+AI71-AJ71 -> 824.882 | AL71: =+AK71-AK39 -> -136.631 | AO71: 45742 | AP71: 140323 | AQ71: 2076.7914 | AR71: 193 | AS71: 38699.654 | AU71: GAS TORRE A | AV71: =+'Vr M3 DE GAS'!BV10 -> 2077 | AW71: =+AS97-AS64 -> 1127.519 | AX71: =+AV71-AW71 -> 949.481 | AY71: =+AX71-AX39 -> 277
B72: 44606 | C72: 119688 | D72: 133.1653 | E72: 12 | F72: 2198.501 | O72: 44951 | P72: 126522 | Q72: 693.8661 | R72: 74 | S72: 12576.687 | U72: GAS TORRE B | V72: =+'Vr M3 DE GAS'!BE26 -> 1282 | X72: =+V72-W72 -> 1282 | Y72: =+X72-#REF! -> #REF! | AB72: 45344 | AC72: 133096 | AD72: 1434.753 | AE72: 136 | AF72: 24296.214 | AH72: GAS TORRE B | AI72: =+'Vr M3 DE GAS'!BN27 -> 1122 | AK72: =+AI72-AJ72 -> 1122 | AL72: =+AK72-AK40 -> -205 | AO72: 45743 | AP72: 140339 | AQ72: 2078.9534 | AR72: 193 | AS72: 38719.005 | AU72: GAS TORRE B | AV72: =+'Vr M3 DE GAS'!BV28 -> 1039 | AX72: =+AV72-AW72 -> 1039 | AY72: =+AX72-AX40 -> 142
B73: 44607 | C73: 119708 | D73: 134.3823 | E73: 12 | F73: 2223.421 | O73: 44952 | P73: 126549 | Q73: 696.3861 | R73: 74 | S73: 12630.31 | U73: GAS TORRE C | V73: =+'Vr M3 DE GAS'!BE44 -> 1439 | X73: =+V73-W73 -> 1439 | Y73: =+X73-#REF! -> #REF! | AB73: 45345 | AC73: 133115 | AD73: 1437.9085 | AE73: 137 | AF73: 24312.097 | AH73: GAS TORRE C | AI73: =+'Vr M3 DE GAS'!BN45 -> 1149 | AK73: =+AI73-AJ73 -> 1149 | AL73: =+AK73-AK41 -> -204 | AO73: 45744 | AP73: 140359 | AQ73: 2080.9169 | AR73: 193 | AS73: 38773.317 | AU73: GAS TORRE C | AV73: =+'Vr M3 DE GAS'!BV46 -> 907 | AX73: =+AV73-AW73 -> 907 | AY73: =+AX73-AX41 -> 84
B74: 44608 | C74: 119727 | D74: 135.5076 | E74: 12 | F74: 2248.407 | O74: 44953 | P74: 126574 | Q74: 697.7517 | R74: 74 | S74: 12668.129 | AB74: 45346 | AC74: 133130 | AD74: 1438.4488 | AE74: 137 | AF74: 24349.908 | AO74: 45745 | AP74: 140374 | AQ74: 2082.3012 | AR74: 194 | AS74: 38815.331
B75: 44609 | C75: 119748 | D75: 136.8865 | E75: 12 | F75: 2274.617 | O75: 44954 | P75: 126597 | Q75: 699.8765 | R75: 74 | S75: 12704.371 | U75: TOTAL EDIFICIO | V75: =SUM(V71:V74) -> 5078 | W75: =+W71 -> 972.934 | X75: =SUM(X71:X74) -> 4105.066 | Y75: =+X75-#REF! -> #REF! | AB75: 45347 | AC75: 133140 | AD75: 1438.7026 | AE75: 137 | AF75: 24350.343 | AH75: TOTAL EDIFICIO | AI75: =SUM(AI71:AI74) -> 3804 | AJ75: =+AJ71 -> 708.118 | AK75: =SUM(AK71:AK74) -> 3095.882 | AL75: =+AK75-AK43 -> -545.631 | AO75: 45746 | AP75: 140387 | AQ75: 2083.2785 | AR75: 194 | AS75: 38865.828 | AU75: TOTAL EDIFICIO | AV75: =SUM(AV71:AV74) -> 4023 | AW75: =+AW71 -> 1127.519 | AX75: =SUM(AX71:AX74) -> 2895.481 | AY75: =+AX75-AX43 -> 503
B76: 44610 | C76: 119767 | D76: 137.6879 | E76: 13 | F76: 2298.46 | O76: 44955 | P76: 126617 | Q76: 700.4634 | R76: 74 | S76: 12740.881 | AB76: 45348 | AC76: 133169 | AD76: 1441.2231 | AE76: 137 | AF76: 24350.961 | AO76: 45747 | AP76: 140406 | AQ76: 2085.0479 | AR76: 194 | AS76: 38881.204
B77: 44611 | C77: 119784 | D77: 138.7472 | E77: 13 | F77: 2323.49 | O77: 44956 | P77: 126638 | Q77: 702.6342 | R77: 74 | S77: 12762.854 | AB77: 45349 | AC77: 133175 | AD77: 1442.1633 | AE77: 137 | AF77: 24404.596 | AO77: 45748 | AP77: 140424 | AQ77: 2087.83 | AR77: 194 | AS77: 38907.731
B78: 44612 | C78: 119798 | D78: 139.4928 | E78: 14 | F78: 2350.976 | O78: 44957 | P78: 126669 | Q78: 704.8165 | R78: 74 | S78: 12804.879 | U78: AGUA | AB78: 45350 | AC78: 133190 | AD78: 1442.8577 | AE78: 137 | AF78: 24444.77 | AH78: AGUA | AO78: 45749 | AP78: 140442 | AQ78: 2089.5605 | AR78: 194 | AS78: 38952.997 | AU78: AGUA
B79: 44613 | C79: 119818 | D79: 141.4007 | E79: 14 | F79: 2370.025 | H79: ANALISIS PARA GAS A PAGAR EN MARZO | O79: 44958 | P79: 126692 | Q79: 706.3878 | R79: 75 | S79: 12835.042 | AB79: 45351 | AC79: 133207 | AD79: 1443.9644 | AE79: 138 | AF79: 24481.901 | AO79: 45750 | AP79: 140460 | AQ79: 2091.7495 | AR79: 194 | AS79: 39002.411
B80: 44614 | C80: 119839 | D80: 142.6959 | E80: 14 | F80: 2392.475 | H80: 18 DE FEBERERO a 18 MARZO | O80: 44959 | P80: 126717 | Q80: 707.945 | R80: 75 | S80: 12876.646 | U80: TOTAL CALLEJA | V80: =+P96-P67 -> 679 | AB80: 45352 | AC80: 133225 | AD80: 1445.2025 | AE80: 138 | AF80: 24522.629 | AH80: TOTAL CALLEJA | AI80: =+AC97-AC70 -> 454 | AO80: 45751 | AP80: 140480 | AQ80: 2094.6596 | AR80: 195 | AS80: 39021.321 | AU80: TOTAL CALLEJA | AV80: =+AP97-AP64 -> 495
B81: 44615 | C81: 119858 | D81: 143.2529 | E81: 15 | F81: 2416.917 | I81: TORRES | J81: AREAS COMUNES | K81: TORRES | O81: 44960 | P81: 126741 | Q81: 710.1655 | R81: 75 | S81: 12902.442 | U81: AREAS COMUNES | V81: =+Q96-Q67 -> 47.5904 | AB81: 45353 | AC81: 133239 | AD81: 1446.4493 | AE81: 138 | AF81: 24534.953 | AH81: AREAS COMUNES | AI81: =+AD97-AD70 -> 40.4993 | AO81: 45752 | AP81: 140495 | AQ81: 2095.7051 | AR81: 195 | AS81: 39036.325 | AU81: AREAS COMUNES | AV81: =+AQ97-AQ64 -> 58.296
B82: 44616 | C82: 119875 | D82: 144.1454 | E82: 15 | F82: 2439.135 | H82: TORRE A | I82: =+'Vr M3 DE GAS'!AV9 -> 1668 | J82: =+F104-F76 -> 700.978 | K82: =+I82-J82 -> 967.022 | O82: 44961 | P82: 126752 | Q82: 711.052 | R82: 75 | S82: 12921.53 | U82: APARTAMENTOS | V82: =+V80-V81 -> 631.4096 | AB82: 45354 | AC82: 133251 | AD82: 1446.7651 | AE82: 138 | AF82: 24554.962 | AH82: APARTAMENTOS | AI82: =+AI80-AI81 -> 413.5007 | AO82: 45753 | AP82: 140512 | AQ82: 2097.7159 | AR82: 195 | AS82: 39061.765 | AU82: APARTAMENTOS | AV82: =+AV80-AV81 -> 436.704
B83: 44617 | C83: 119896 | D83: 146.8601 | E83: 15 | F83: 2463.932 | H83: TORRE B | I83: =+'Vr M3 DE GAS'!AV27 -> 1262 | K83: =+I83-J83 -> 1262 | O83: 44962 | P83: 126764 | Q83: 711.4643 | R83: 75 | S83: 12943.673 | AB83: 45355 | AC83: 133270 | AD83: 1449.1031 | AE83: 138 | AF83: 24554.97 | AO83: 45754 | AP83: 140520 | AQ83: 2098.7244 | AR83: 195 | AS83: 39086.864
B84: 44618 | C84: 119916 | D84: 149.9924 | E84: 15 | F84: 2490.338 | H84: TORRE C | I84: =+'Vr M3 DE GAS'!AV45 -> 1019 | K84: =+I84-J84 -> 1019 | O84: 44963 | P84: 126810 | Q84: 715.3147 | R84: 75 | S84: 12991.678 | AB84: 45356 | AC84: 133286 | AD84: 1449.9229 | AE84: 138 | AF84: 24578.368 | AO84: 45755 | AP84: 140591 | AQ84: 2101.1888 | AR84: 196 | AS84: 39132.569
B85: 44619 | C85: 119933 | D85: 150.4567 | E85: 16 | F85: 2514.959 | O85: 44964 | P85: 126833 | Q85: 716.794 | R85: 75 | S85: 13036.155 | U85: SE CONSUMIERON | V85: =+V82 -> 631.4096 | W85: DE AGUA CALIENTE | Y85: =+V85-CF268 -> 631.4096 | AB85: 45357 | AC85: 133302 | AD85: 1450.767 | AE85: 138 | AF85: 24623.648 | AH85: SE CONSUMIERON | AI85: =+AI82 -> 413.5007 | AJ85: DE AGUA CALIENTE | AL85: =+AI85-AI53 -> -72.9762 | AO85: 45756 | AP85: 140564 | AQ85: 2102.9351 | AR85: 196 | AS85: 39156.487 | AU85: SE CONSUMIERON | AV85: =+AV82 -> 436.704 | AW85: DE AGUA CALIENTE | AY85: =+AV85-AV53 -> -23.7438
B86: 44620 | C86: 119971 | D86: 152.3696 | E86: 16 | F86: 2554.838 | H86: TOTAL EDIFICIO | K86: =SUM(K82:K85) -> 3248.022 | O86: 44965 | P86: 126858 | Q86: 717.89 | R86: 75 | S86: 13078.629 | AB86: 45358 | AC86: 133320 | AD86: 1451.8707 | AE86: 138 | AF86: 24646.729 | AO86: 45757 | AP86: 140581 | AQ86: 2104.8699 | AR86: 196 | AS86: 39209.242
B87: 44621 | C87: 119977 | D87: 152.7062 | E87: 17 | F87: 2558.473 | I87: =SUM(I82:I86) -> 3949 | O87: 44966 | P87: 126880 | Q87: 718.8776 | R87: 76 | S87: 13114.233 | U87: SE CONSUMIO DE GAS | V87: =+X75 -> 4105.066 | W87: M3 EN CALDERAS | Y87: =+V87-CF270 -> 4105.066 | AB87: 45359 | AC87: 133338 | AD87: 1452.8664 | AE87: 138 | AF87: 24654.173 | AH87: SE CONSUMIO DE GAS | AI87: =+AK75 -> 3095.882 | AJ87: M3 EN CALDERAS | AL87: =+AI87-AI55 -> -545.631 | AO87: 45758 | AP87: 140600 | AQ87: 2107.4841 | AR87: 196 | AS87: 39237.628 | AU87: SE CONSUMIO DE GAS | AV87: =+AX75 -> 2895.481 | AW87: M3 EN CALDERAS | AY87: =+AV87-AV55 -> 503
B88: 44622 | C88: 119998 | D88: 153.597 | E88: 17 | F88: 2585.223 | O88: 44967 | P88: 126905 | Q88: 720.3416 | R88: 76 | S88: 13153.55 | AB88: 45360 | AC88: 133353 | AD88: 1454.6063 | AE88: 138 | AF88: 24662.863 | AO88: 45759 | AP88: 140613 | AQ88: 2108.8079 | AR88: 196 | AS88: 39281.05
B89: 44623 | C89: 120019 | D89: 155.6536 | E89: 17 | F89: 2612.946 | H89: CONSUMO DE AGUA ENTRE EL 21 DE ENERO Y EL 18 DE FEBRERO | O89: 44968 | P89: 126928 | Q89: 723.419 | R89: 76 | S89: 13204.876 | U89: SE REQUIERIO | V89: =+V87/V85 -> 6.5014311 | W89: M3 DE GAS PARA CALENTAR 1 M3 DE AGUA | AB89: 45361 | AC89: 133367 | AD89: 1455.1696 | AE89: 138 | AF89: 24694.29 | AH89: SE REQUIERIO | AI89: =+AI87/AI85 -> 7.4870055 | AJ89: M3 DE GAS PARA CALENTAR 1 M3 DE AGUA | AO89: 45760 | AP89: 140624 | AQ89: 2109.749 | AR89: 196 | AS89: 39310.031 | AU89: SE REQUIERIO | AV89: =+AV87/AV85 -> 6.6303057 | AW89: M3 DE GAS PARA CALENTAR 1 M3 DE AGUA
B90: 44624 | C90: 120039 | D90: 156.4222 | E90: 18 | F90: 2636.109 | O90: 44969 | P90: 126945 | Q90: 724.0554 | R90: 76 | S90: 13235.977 | AB90: 45362 | AC90: 133385 | AD90: 1456.2853 | AE90: 138 | AF90: 24694.297 | AO90: 45761 | AP90: 140639 | AQ90: 2112.099 | AR90: 196 | AS90: 39326.765
B91: 44625 | C91: 120057 | D91: 157.5535 | E91: 18 | F91: 2662.966 | H91: TOTAL CALLEJA | I91: =+C104-C76 -> 558 | O91: 44970 | P91: 126968 | Q91: 726.8387 | R91: 76 | S91: 13236.986 | AB91: 45363 | AC91: 133403 | AD91: 1457.9983 | AE91: 138 | AF91: 24752.642 | AO91: 45762 | AP91: 140653 | AQ91: 2114.3209 | AR91: 197 | AS91: 39359.74
B92: 44626 | C92: 120072 | D92: 158.1068 | E92: 18 | F92: 2690.467 | H92: AREAS COMUNES | I92: =+D104-D76 -> 34.792 | O92: 44971 | P92: 126991 | Q92: 728.4594 | R92: 77 | S92: 13268.728 | AB92: 45364 | AC92: 133424 | AD92: 1461.0645 | AE92: 138 | AF92: 24805.958 | AO92: 45763 | AP92: 140666 | AQ92: 2116.2593 | AR92: 197 | AS92: 39387.762
B93: 44627 | C93: 120093 | D93: 159.1432 | E93: 19 | F93: 2708.819 | H93: APARTAMENTOS | I93: =+I91-I92 -> 523.208 | O93: 44972 | P93: 127015 | Q93: 730.3217 | R93: 77 | S93: 13317.19 | AB93: 45365 | AC93: 133443 | AD93: 1464.6753 | AE93: 138 | AF93: 24833.573 | AO93: 45764 | AP93: 140674 | AQ93: 2117.3306 | AR93: 197 | AS93: 39426.45
B94: 44628 | C94: 120114 | D94: 160.0488 | E94: 19 | F94: 2732.265 | O94: 44973 | P94: 127037 | Q94: 733.2476 | R94: 77 | S94: 13356.234 | AB94: 45366 | AC94: 133463 | AD94: 1465.4924 | AE94: 138 | AF94: 24865.591 | AO94: 45765 | AP94: 140681 | AQ94: 2118.0256 | AR94: 197 | AS94: 39460.304
B95: 44629 | C95: 120137 | D95: 162.0405 | E95: 19 | F95: 2762.562 | O95: 44974 | P95: 127062 | Q95: 734.5021 | R95: 78 | S95: 13365.583 | AB95: 45367 | AC95: 133481 | AD95: 1466.9409 | AE95: 138 | AF95: 24901.98 | AO95: 45766 | AP95: 140689 | AQ95: 2119.1959 | AR95: 197 | AS95: 39497.593
B96: 44630 | C96: 120158 | D96: 163.4272 | E96: 20 | F96: 2793.164 | H96: SE CONSUMIERON | I96: =+I93 -> 523.208 | J96: DE AGUA CALIENTE | O96: 44975 | P96: 127081 | Q96: 735.9403 | R96: 78 | S96: 13407.688 | AB96: 45368 | AC96: 133493 | AD96: 1467.3587 | AE96: 138 | AF96: 24938.528 | AO96: 45767 | AP96: 140699 | AQ96: 2119.9395 | AR96: 197 | AS96: 39528.672
B97: 44631 | C97: 120183 | D97: 164.239 | E97: 20 | F97: 2820.007 | O97: 44976 | P97: 127100 | Q97: 736.6529 | R97: 78 | S97: 13442.656 | AB97: 45369 | AC97: 133513 | AD97: 1470.1471 | AE97: 139 | AF97: 24938.534 | AO97: 45768 | AP97: 140716 | AQ97: 2122.0947 | AR97: 197 | AS97: 39538.104
B98: 44632 | C98: 120202 | D98: 165.3862 | E98: 20 | F98: 2846.288 | H98: SE CONSUMIO DE GAS | I98: =+K86 -> 3248.022 | J98: EN CALDERAS | O98: 44977 | P98: 127126 | Q98: 739.7165 | R98: 78 | S98: 13448.179 | U98: 18 DE FEBRERO A 19 DE MARZO | AB98: 45370 | AC98: 133532 | AD98: 1471.209 | AE98: 139 | AF98: 24988.956 | AH98: 18 DE MARZO A 18 DE ABRIL | AO98: 45769 | AP98: 140733 | AQ98: 2123.997 | AR98: 197 | AS98: 39567.96 | AU98: ABRIL 21 A MAYO 20
B99: 44633 | C99: 120220 | D99: 166.4822 | E99: 21 | F99: 2872.236 | O99: 44978 | P99: 127148 | Q99: 740.7399 | R99: 78 | S99: 13489.49 | U99: TORRES | V99: TORRES | W99: AREAS COMUNES | X99: CALDERAS TORRES | AB99: 45371 | AC99: 133550 | AD99: 1472.1549 | AE99: 139 | AF99: 25003.643 | AH99: TORRES | AI99: TORRES | AJ99: AREAS COMUNES | AK99: CALDERAS TORRES | AO99: 45770 | AP99: 140753 | AQ99: 2126.5569 | AR99: 197 | AS99: 39625.78 | AU99: TORRES | AV99: TORRES | AW99: AREAS COMUNES | AX99: CALDERAS TORRES
B100: 44634 | C100: 120243 | D100: 169.1962 | E100: 21 | F100: 2892.681 | H100: SE REQUIERIO | I100: =+I98/I96 -> 6.2078982 | J100: M3 DE GAS PARA CALENTAR 1 M3 DE ACAUA | O100: 44979 | P100: 127174 | Q100: 742.2794 | R100: 78 | S100: 13527.978 | U100: GAS TORRE A | V100: =+'Vr M3 DE GAS'!BE9 -> 2290 | W100: =+S123-S96 -> 1013.208 | X100: =+V100-W100 -> 1276.792 | Y100: =+X100-CH254 -> 1276.792 | AB100: 45372 | AC100: 133569 | AD100: 1473.8071 | AE100: 139 | AF100: 25033.542 | AH100: GAS TORRE A | AI100: =+'Vr M3 DE GAS'!BN10 -> 1788 | AJ100: =+AF128-AF97 -> 866.83 | AK100: =+AI100-AJ100 -> 921.17 | AL100: =+AK100-AK71 -> 96.288 | AO100: 45771 | AP100: 140773 | AQ100: 2128.5926 | AR100: 197 | AS100: 39666.321 | AU100: GAS TORRE A | AV100: =+'Vr M3 DE GAS'!BV11 -> 1799 | AW100: =+AS126-AS97 -> 981.949 | AX100: =+AV100-AW100 -> 817.051 | AY100: =+AX100-AX71 -> -132.43
B101: 44635 | C101: 120263 | D101: 170.2156 | E101: 21 | F101: 2917.965 | O101: 44980 | P101: 127196 | Q101: 743.5025 | R101: 79 | S101: 13566.648 | U101: GAS TORRE B | V101: =+'Vr M3 DE GAS'!BE27 -> 1410 | X101: =+V101-W101 -> 1410 | Y101: =+X101-CH255 -> 1410 | AB101: 45373 | AC101: 133590 | AD101: 1475.283 | AE101: 140 | AF101: 25073.049 | AH101: GAS TORRE B | AI101: =+'Vr M3 DE GAS'!BN28 -> 1147 | AK101: =+AI101-AJ101 -> 1147 | AL101: =+AK101-AK72 -> 25 | AO101: 45772 | AP101: 140790 | AQ101: 2129.8238 | AR101: 198 | AS101: 39694.666 | AU101: GAS TORRE B | AV101: =+'Vr M3 DE GAS'!BV29 -> 1050 | AX101: =+AV101-AW101 -> 1050 | AY101: =+AX101-AX72 -> 11
B102: 44636 | C102: 120283 | D102: 170.8389 | E102: 21 | F102: 2945.484 | O102: 44981 | P102: 127224 | Q102: 745.7175 | R102: 79 | S102: 13605.572 | U102: GAS TORRE C | V102: =+'Vr M3 DE GAS'!BE45 -> 1480 | X102: =+V102-W102 -> 1480 | Y102: =+X102-CH256 -> 1480 | AB102: 45374 | AC102: 133613 | AD102: 1480.7911 | AE102: 140 | AF102: 25109.115 | AH102: GAS TORRE C | AI102: =+'Vr M3 DE GAS'!BN46 -> 1192 | AK102: =+AI102-AJ102 -> 1192 | AL102: =+AK102-AK73 -> 43 | AO102: 45773 | AP102: 140808 | AQ102: 2131.26 | AR102: 198 | AS102: 39734.961 | AU102: GAS TORRE C | AV102: =+'Vr M3 DE GAS'!BV47 -> 850 | AX102: =+AV102-AW102 -> 850 | AY102: =+AX102-AX73 -> -57
B103: 44637 | C103: 120304 | D103: 171.4809 | E103: 21 | F103: 2972.19 | O103: 44982 | P103: 127244 | Q103: 747.1102 | R103: 79 | S103: 13621.656 | AB103: 45375 | AC103: 133627 | AD103: 1481.2128 | AE103: 140 | AF103: 25136.968 | AO103: 45774 | AP103: 140822 | AQ103: 2132.0315 | AR103: 199 | AS103: 39779.233
...

Sheet Hoja3
E9: ENERO | F9: FEBRERO | G9: MARZO | H9: ABRIL | I9: MAYO | J9: JUNIO | K9: JULIO | L9: AGOSTO | M9: SEPTIEMBRE | N9: OCTUBRE
D12: AGUA CONTADOR EAAB | E12: 605 | F12: 548 | G12: 623 | H12: 533 | I12: 576 | J12: 644 | K12: 523 | L12: 641 | M12: 665 | N12: 577
D13: AGUA CONTADOR ZONAS COMUNES | E13: 78.2474 | F13: 39.5787 | G13: 39.8208 | H13: 45.99 | I13: 52.983 | J13: 41.1062 | K13: 54.9611 | L13: 46.2417 | M13: 50.4149 | N13: 53.3517
D14: DIEFERENCIA APTOS AGUA CALIENTE | E14: =+E12-E13 -> 526.7526 | F14: =+F12-F13 -> 508.4213 | G14: =+G12-G13 -> 583.1792 | H14: =+H12-H13 -> 487.01 | I14: =+I12-I13 -> 523.017 | J14: =+J12-J13 -> 602.8938 | K14: =+K12-K13 -> 468.0389 | L14: =+L12-L13 -> 594.7583 | ... N14: =+N12-N13 -> 523.6483
D15: AGUA CONTADORES APTOS | E15: 506 | F15: 511 | G15: 553 | H15: 489 | I15: 508 | J15: 496 | K15: 442 | L15: 481 | M15: 488 | N15: 469
D16: CONTADOR DUCHAC PISICINA | E16: 6 | F16: 8 | G16: 8 | H16: 8 | I16: 6 | J16: 4 | K16: 4 | L16: 5 | M16: 6 | N16: 3
D17: TOTAL AGUA CALIENTE | E17: =+E15+E16 -> 512 | F17: =+F16+F15 -> 519 | G17: =+G15+G16 -> 561 | H17: =+H16+H15 -> 497 | I17: =+I16+I15 -> 514 | J17: =+J16+J15 -> 500 | K17: =+K16+K15 -> 446 | L17: =+L16+L15 -> 486 | M17: =+M16+M15 -> 494 | N17: =+N16+N15 -> 472
D19: DIFERENCIA | E19: =+E14-E17 -> 14.7526 | F19: =+F14-F17 -> -10.5787 | G19: =+G14-G17 -> 22.1792 | H19: =+H14-H17 -> -9.99 | I19: =+I14-I17 -> 9.017 | J19: =+J14-J17 -> 102.8938 | K19: =+K14-K17 -> 22.0389 | L19: =+L14-L17 -> 108.7583 | ... N19: =+N14-N17 -> 51.6483

Sheet Vr M3 DE AGUA
A1: ACUEDUCTO Y ALCANTARILLADO
A2: CONSUMOS
A3: MES | C3: CONS ANT | D3: CONS ACT | E3: DIF | F3: M3 ACUEDUCTO | G3: ACUEDUCTO | H3: M3 ALCANTARI | I3: ALCANTARILLADO | J3: OTROS COBROS | K3: ACUEDUCTO MAS ALCANTARILLAD | L3: SE PAGO | M3: a pagar en | N3: COSTO M3 | O3: Aplicar en
A4: Sep-27 / Nov-25 /2016 | C4: 1450 | D4: 1457 | E4: =+D4-C4 -> 7 | F4: 3432.77 | G4: 5028860 | H4: 3695.14 | I4: 5398016 | K4: =+I4+G4 -> 10426876 | L4: 10426880 | M4: 42705 | N4: =+L4/D4 -> 7156.4036 | O4: Enero 2017 y Febrero 2017 | P4: =+L4-K4 -> 4
A5: Nov-26 / Ene-25/ 2017 | C5: 1457 | D5: 1021 | E5: =+D5-C5 -> -436 | F5: 3432.77 | G5: 3532173 | H5: 3695.14 | I5: 3786935 | K5: =+I5+G5 -> 7319108 | L5: 7319110 | M5: 42767 | N5: =+L5/D5 -> 7168.57 | O5: Marzo 2017 y Abril 2017 | P5: =+L5-K5 -> 2
A6: Ene-26/ Mar-27/2017 | C6: 1021 | D6: 967 | E6: =+D6-C6 -> -54 | F6: 3488.72 | G6: 3506013 | H6: 3753.69 | I6: 3756854 | K6: =+I6+G6 -> 7262867 | L6: 7262870 | M6: 42826 | N6: =+L6/D6 -> 7510.7239 | O6: Mayo 2017 - Junio 2017 | P6: =+L6-K6 -> 3
A7: Mar-28/ May-25/2017 | C7: 967 | D7: 1055 | E7: =+D7-C7 -> 88 | F7: 3559.17 | G7: 3783248 | H7: 3827.41 | I7: 4052639 | K7: =+I7+G7 -> 7835887 | L7: 7835890 | M7: 42887 | N7: =+L7/D7 -> 7427.3839 | O7: Julio 2017 - Agosto 2017 | P7: =+L7-K7 -> 3
A8: May-26/ Jul-25/2017 | C8: 1055 | D8: 1051 | E8: =+D8-C8 -> -4 | F8: 3559.17 | G8: 3769011 | H8: 3827.41 | I8: 4037329 | K8: =+I8+G8 -> 7806340 | L8: 7806340 | M8: 42948 | N8: =+L8/D8 -> 7427.5357 | O8: Septim 2017 - Octubre 2017 | P8: =+L8-K8 -> 0
A9: Jul-26/ Sep-25/2017 | C9: 1051 | D9: 1280 | E9: =+D9-C9 -> 229 | F9: 3561.2 | G9: 4586656 | H9: 3833.11 | I9: 4921107 | K9: =+I9+G9 -> 9507763 | L9: 9507760 | M9: 43009 | N9: =+L9/D9 -> 7427.9375 | O9: Noviem 2017 - Diciembre 2017 | P9: =+L9-K9 -> -3
A10: Sep-24/ Nov-22/2017 | C10: 1280 | D10: 1129 | E10: =+D10-C10 -> -151 | F10: 3564.46 | G10: 4052599 | H10: 3842.29 | I10: 4352667 | K10: =+I10+G10 -> 8405266 | L10: 8405270 | M10: 43070 | N10: =+L10/D10 -> 7444.8804 | O10: Enero 2018 y Febrero 2018 | P10: =+L10-K10 -> 4
A11: Nov-23/ Ene-20/2018 | C11: 1129 | D11: 971 | E11: =+D11-C11 -> -158 | F11: 3564.46 | G11: 3489414 | H11: 3842.29 | I11: 3745585 | K11: =+I11+G11 -> 7234999 | L11: 7235000 | M11: 43132 | N11: =+L11/D11 -> 7451.0814 | O11: Marzo 2018 y Abril 2018 | P11: =+L11-K11 -> 1
A12: Ene-21/ Mar-21/2018 | C12: 971 | D12: 915 | E12: =+D12-C12 -> -56 | F12: 3792.4 | G12: 3498528 | H12: 3903.32 | I12: 3586466 | K12: =+I12+G12 -> 7084994 | L12: 7084990 | M12: 43191 | N12: =+L12/D12 -> 7743.1585 | O12: Mayo 2018 - Junio 2018 | P12: =+L12-K12 -> -4
A13: Mar-22/ May-21/2018 | C13: 915 | D13: 817 | E13: =+D13-C13 -> -98 | F13: 3916.2 | G13: 3228593 | H13: 3989 | I13: 3274269 | K13: =+I13+G13 -> 6502862 | L13: 6502860 | M13: 43252 | N13: =+L13/D13 -> 7959.437 | O13: Julio 2018 - Agosto 2018 | P13: =+L13-K13 -> -2
A14: May-22/ Jul-19/2018 | C14: 817 | D14: 744 | E14: =+D14-C14 -> -73 | F14: 3919.82 | G14: 2945406 | H14: 3994.51 | I14: 2987172 | K14: =+I14+G14 -> 5932578 | L14: 5932580 | M14: 43313 | N14: =+L14/D14 -> 7973.8978 | O14: Septim 2018 - Octubre 2018 | P14: =+L14-K14 -> 2
A15: Jul-20/ Sep-17/2018 | C15: 744 | D15: 770 | E15: =+D15-C15 -> 26 | F15: 3927.45 | G15: 3053195 | H15: 4006.11 | I15: 3099960 | K15: =+I15+G15 -> 6153155 | L15: 6153160 | M15: 43374 | N15: =+L15/D15 -> 7991.1169 | O15: Noviem 2018 - Diciembre 2018 | P15: =+L15-K15 -> 5
... A19: Mar-17/ May16/2019 | C19: 781 | D19: 669 | E19: =+D19-C19 -> -112 | F19: 4045.52 | G19: 2736386 | H19: 4123.01 | I19: 2774011 | K19: =+I19+G19 -> 5510397 | L19: 5510400 | M19: 43617 | N19: =+L19/D19 -> 8236.7713 | O19: Julio 2019 - Agosto 2019 | P19: =+L19-K19 -> 3
A20: May 17/ Julio13/2019 | C20: 669 | D20: 811 | E20: 142 | F20: 4082.4279 | G20: 3310849 | H20: 4142.3896 | I20: 3359478 | K20: 6670327 | L20: 6327181 | M20: 43678 | N20: =+L20/D20 -> 7801.7028 | O20: Septiembre 2019- Octubre 2019 | P20: =+L20-K20 -> -343146
A21: julio 14/19 Sep 11/19 | C21: 811 | D21: 754 | E21: =+D21-C21 -> -57 | F21: =+G21/D21 -> 4085.2268 | G21: 3080261 | H21: =+I21/D21 -> 4143.5305 | I21: 3124222 | K21: =+I21+G21 -> 6204483 | L21: 6204480 | M21: 43739 | N21: =+L21/D21 -> 8228.7533 | O21: Noviembre 2019 - Diciembre 2019 | P21: =+L21-K21 -> -3
A22: Sep 12/19 Nov 9/19 | C22: 754 | D22: 1604 | E22: =+D22-C22 -> 850 | F22: =+G22/D22 -> 4064.2251 | G22: 6519017 | H22: =+I22/D22 -> 4131.0411 | I22: 6626190 | K22: =+I22+G22 -> 13145207 | L22: 13145210 | M22: 43800 | N22: =+L22/D22 -> 8195.2681 | O22: Enero 2020 -Febrero 2020 | P22: =+L22-K22 -> 3
A23: Nov 10/19 Enero 9/20 | C23: 1604 | D23: 1022 | E23: =+D23-C23 -> -582 | F23: =+G23/D23 -> 4105.7378 | G23: 4196064 | H23: =+I23/D23 -> 4105.7378 | I23: 4196064 | K23: =+I23+G23 -> 8392128 | L23: 8392130 | M23: 43862 | N23: =+L23/D23 -> 8211.4775 | O23: Marzo 2020 - Abril 2020 | P23: =+L23-K23 -> 2
A24: Enero 10/20 Marzo 9/20 | C24: 1022 | D24: 1286 | E24: =+D24-C24 -> 264 | F24: =+G24/D24 -> 4068.8375 | G24: 5232525 | H24: =+I24/D24 -> 4133.4611 | I24: 5315631 | K24: =+I24+G24 -> 10548156 | L24: 10548160 | M24: 43922 | N24: =+L24/D24 -> 8202.3017 | O24: Mayo 2020 - Junio 2020 | P24: =+L24-K24 -> 4
A25: Marzo 10/20 Mayo 8/20 | C25: 1286 | D25: 1308 | E25: =+D25-C25 -> 22 | F25: =+G25/D25 -> 4068.4465 | G25: 5321528 | H25: =+I25/D25 -> 4133.2561 | I25: 5406299 | K25: =+I25+G25 -> 10727827 | L25: 10727830 | M25: 43983 | N25: =+L25/D25 -> 8201.7049 | O25: Julio 2020 - Agosto 2020 | P25: =+L25-K25 -> 3
A26: Mayo 9/20 Julio 7/20 | C26: 1308 | D26: 1317 | E26: =+D26-C26 -> 9 | F26: =+G26/D26 -> 4068.2901 | G26: 5357938 | H26: =+I26/D26 -> 4133.1739 | I26: 5443390 | K26: =+I26+G26 -> 10801328 | L26: 10801330 | M26: 44044 | N26: =+L26/D26 -> 8201.4655 | O26: Septiebre - Octubre 2020 | P26: =+L26-K26 -> 2
A27: Jul 8/20 Sept 4/20 | C27: 1317 | D27: 1388 | E27: =+D27-C27 -> 71 | F27: =+G27/D27 -> 4067.1268 | G27: 5645172 | H27: =+I27/D27 -> 4132.5634 | I27: 5735998 | K27: =+I27+G27 -> 11381170 | L27: 11381170 | M27: 43739 | N27: =+L27/D27 -> 8199.6902 | O27: Nov iembre - Diciembre 2020 | P27: =+L27-K27 -> 0
A28: Sep 5/20 Nov 4 2020 | C28: 1388 | D28: 1350 | E28: =+D28-C28 -> -38 | F28: =+G28/D28 -> 4067.7341 | G28: 5491441 | H28: =+I28/D28 -> 4132.8822 | I28: 5579391 | K28: =+I28+G28 -> 11070832 | L28: 11070830 | M28: 44166 | N28: =+L28/D28 -> 8200.6148 | O28: Enero 2021 - Febrero 2021 | P28: =+L28-K28 -> -2
A29: Nov 5/2020 Enero 2/2021 | C29: 1350 | D29: 1100 | E29: =+D29-C29 -> -250 | F29: =+G29/D29 -> 4072.7736 | G29: 4480051 | H29: =+I29/D29 -> 4135.5282 | I29: 4549081 | K29: =+I29+G29 -> 9029132 | L29: 9029130 | M29: 44228 | N29: =+L29/D29 -> 8208.3 | O29: Marzo 2021 - Abril 2021 | P29: =+L29-K29 -> -2
A30: Enero 3/21 Marzo 3 21 | C30: 1100 | D30: 1226 | E30: =+D30-C30 -> 126 | F30: =+G30/D30 -> 4142.2741 | G30: 5078428 | H30: =+I30/D30 -> 4185.5334 | I30: 5131464 | K30: =+I30+G30 -> 10209892 | L30: 10404882 | M30: 44287 | N30: =+L30/D30 -> 8486.8532 | O30: 44317 | P30: =+L30-K30 -> 194990
A31: Marzo 4/21 Mayo3/21 | C31: 1226 | D31: 1409 | E31: =+D31-C31 -> 183 | F31: =+G31/D31 -> 4206.6402 | G31: 5927156 | H31: =+I31/D31 -> 4231.9716 | I31: 5962848 | J31: =+L31-G31-I31 -> 195088 | K31: =+G31+I31+J31 -> 12085092 | L31: 12085092 | M31: 44348 | N31: =+L31/D31 -> 8577.0703 | O31: Junio - Julio 21 | P31: =+L31-K31 -> 0
A32: Mayo 4/21 Jul/1/21 | C32: 1409 | D32: 1278 | E32: =+D32-C32 -> -131 | F32: =+G32/D32 -> 4208.7966 | G32: 5378842 | H32: =+I32/D32 -> 4232.9851 | I32: 5409755 | J32: 194995 | K32: =+G32+I32+J32 -> 10983592 | L32: =+J32+I32+G32 -> 10983592 | M32: 44409 | N32: =+L32/D32 -> 8594.3599 | O32: Agosto - Septiembre | P32: =+L32-K32 -> 0
A33: Julio 2/Agosto 30 | C33: 1278 | D33: 1247 | E33: =+D33-C33 -> -31 | F33: =+G33/D33 -> 4259.4924 | G33: 5311587 | H33: =+I33/D33 -> 4269.1877 | I33: 5323677 | J33: 194992 | K33: =+G33+I33+J33 -> 10830256 | L33: 10830552 | M33: 44440 | N33: =+L33/D33 -> 8685.2863 | O33: Octubre - Noviembre | P33: =+L33-K33 -> 296
A34: Agosto 31/Octubre 28 | C34: 1247 | D34: 1391 | E34: =+D34-C34 -> 144 | F34: =+G34/D34 -> 4312.2854 | G34: 5998389 | H34: =+I34/D34 -> 4313.2495 | I34: 5999730 | J34: 194993 | K34: =+I34+G34 -> 11998119 | L34: =+K34+J34 -> 12193112 | M34: 44501 | N34: =+L34/D34 -> 8765.7168 | O34: Diciembre - Enero | P34: =+L34-K34 -> 194993
P35: =+L35-K35 -> 0
A36: Octubre 29/Diciembre 28 | C36: =+D34 -> 1391 | D36: 1329 | E36: =+D36-C36 -> -62 | F36: =+G36/D36 -> 4313.611 | G36: 5732789 | H36: =+I36/D36 -> 4313.8051 | I36: 5733047 | J36: 194996 | K36: =+I36+G36 -> 11465836 | L36: =+K36+J36 -> 11660832 | M36: 44562 | N36: =+L36/D36 -> 8774.14 | O36: Febrero - Marzo | P36: =+L36-K36 -> 194996
A37: Diciembre 29 /Febrero 25 | C37: 1329 | D37: 1118 | E37: =+D37-C37 -> -211 | F37: =+G37/D37 -> 4314.8962 | G37: 4824054 | H37: =+I37/D37 -> 4434.4311 | I37: 4957694 | J37: 194994 | K37: =+I37+G37 -> 9781748 | L37: =+K37+J37 -> 9976742 | M37: 44621 | N37: =+L37/D37 -> 8923.7406 | O37: Abril - Mayo | P37: =+L37-K37 -> 194994
A38: Febrero 26 / Abril 26 2022 | C38: =+D37 -> 1118 | D38: 1139 | E38: =+D38-C38 -> 21 | F38: =+G38/D38 -> 4451.7155 | G38: 5070504 | H38: =+I38/D38 -> 4746.9148 | I38: 5406736 | J38: 194992 | K38: =+I38+G38 -> 10477240 | L38: =+K38+J38 -> 10672232 | M38: 44682 | N38: =+L38/D38 -> 9369.8262 | O38: Junio - Julio | P38: =+L38-K38 -> 194992
A39: Abril 27 / Junio 24 | C39: =+D38 -> 1139 | D39: 1181 | E39: =+D39-C39 -> 42 | F39: =+G39/D39 -> 4594.5292 | G39: 5426139 | H39: =+I39/D39 -> 4896.9475 | I39: 5783295 | J39: 194990 | K39: =+I39+G39 -> 11209434 | L39: =+K39+J39 -> 11404424 | M39: 44743 | N39: =+L39/D39 -> 9656.5826 | O39: Agosto - Septiembre | P39: =+L39-K39 -> 194990
A40: Jun 25 /Agost 23 | C40: =+D39 -> 1181 | D40: 1125 | E40: =+D40-C40 -> -56 | F40: =+G40/D40 -> 4645.5938 | G40: 5226293 | H40: =+I40/D40 -> 4919.704 | I40: 5534667 | K40: =+I40+G40 -> 10760960 | L40: =+K40+J40 -> 10760960 | M40: 44805 | N40: =+L40/D40 -> 9565.2978 | O40: Octubre - Noviembre | P40: =+L40-K40 -> 0
A41: Agosto 24/ oct 21 | C41: =+D40 -> 1125 | D41: 1222 | E41: =+D41-C41 -> 97 | F41: =+G41/D41 -> 4728.7398 | G41: 5778520 | H41: =+I41/D41 -> 5004.329 | I41: 6115290 | K41: =+I41+G41 -> 11893810 | L41: =+K41+J41 -> 11893810 | M41: 44866 | N41: =+L41/D41 -> 9733.0687 | O41: Diciembre - Enero | P41: =+L41-K41 -> 0
A42: Oct 22 / Dic 21 | C42: =+D41 -> 1222 | D42: 1265 | E42: =+D42-C42 -> 43 | F42: =+G42/D42 -> 4727.7739 | G42: 5980634 | H42: =+I42/D42 -> 5003.8277 | I42: 6329842 | J42: 4 | K42: =+I42+G42 -> 12310476 | L42: =+K42+J42 -> 12310480 | M42: 44927 | N42: =+L42/D42 -> 9731.6047 | O42: Febrero - Marzo | P42: =+L42-K42 -> 4
A43: Dic 22/Feb 20 | C43: =+D42 -> 1265 | D43: 1290 | E43: =+D43-C43 -> 25 | F43: =+G43/D43 -> 4832.0264 | G43: 6233314 | H43: =+I43/D43 -> 4883.914 | I43: 6300249 | J43: -3 | K43: =+I43+G43 -> 12533563 | L43: =+K43+J43 -> 12533560 | M43: 44986 | N43: =+L43/D43 -> 9715.938 | O43: Abril - Mayo | P43: =+L43-K43 -> -3
A44: Feb 21/abril 20 | C44: =+D43 -> 1290 | D44: 1279 | E44: =+D44-C44 -> -11 | F44: =+G44/D44 -> 5043.4926 | G44: 6450627 | H44: =+I44/D44 -> 5042.8241 | I44: 6449772 | J44: 1 | K44: =+I44+G44 -> 12900399 | L44: =+K44+J44 -> 12900400 | M44: 45047 | N44: =+L44/D44 -> 10086.317 | O44: Junio - Julio | P44: =+L44-K44 -> 1
A45: Abril 21/ Junio 20 | C45: =+D44 -> 1279 | D45: 1197 | E45: =+D45-C45 -> -82 | F45: =+G45/D45 -> 5131.66 | G45: 6142597 | H45: =+I45/D45 -> 5131.66 | I45: 6142597 | J45: -4 | K45: =+I45+G45 -> 12285194 | L45: =+K45+J45 -> 12285190 | M45: 45108 | N45: =+L45/D45 -> 10263.317 | O45: Agosto - Septiembre | P45: =+L45-K45 -> -4
A46: Junio 21/ Agosto 18 | C46: =+D45 -> 1197 | D46: 742 | E46: =+D46-C46 -> -455 | F46: =+G46/D46 -> 5272.8571 | G46: 3912460 | H46: =+I46/D46 -> 5257.4057 | I46: 3900995 | J46: 5 | K46: =+I46+G46 -> 7813455 | L46: =+K46+J46 -> 7813460 | M46: 45170 | N46: =+L46/D46 -> 10530.27 | O46: Octubre - Noviembre | P46: =+L46-K46 -> 5
A47: Agosto 19/ Oct18 | C47: =+D46 -> 742 | D47: 887 | E47: =+D47-C47 -> 145 | F47: =+G47/D47 -> 5146.5941 | G47: 4565029 | H47: =+I47/D47 -> 5235.1364 | I47: 4643566 | J47: 5 | K47: =+I47+G47 -> 9208595 | L47: =+K47+J47 -> 9208600 | M47: 45170 | N47: =+L47/D47 -> 10381.736 | O47: Diciembre - Enero | P47: =+L47-K47 -> 5
A48: Oct 19 / Dic 16 | C48: 887 | D48: 799 | E48: =+D48-C48 -> -88 | F48: =+G48/D48 -> 5126.1202 | G48: 4095770 | H48: =+I48/D48 -> 5313.612 | I48: 4245576 | J48: 4 | K48: =+I48+G48 -> 8341346 | L48: =+K48+J48 -> 8341350 | M48: 45292 | N48: =+L48/D48 -> 10439.737 | O48: Frbrero - Marzo | P48: =+L48-K48 -> 4
A49: Dic 17 / Feb 14 | C49: 799 | D49: 939 | E49: =+D49-C49 -> 140 | F49: =+G49/D49 -> 5241.8349 | G49: 4922083 | H49: =+I49/D49 -> 5435.2907 | I49: 5103738 | J49: 1 | K49: =+I49+G49 -> 10025821 | L49: =+K49+J49 -> 10025822 | M49: 45352 | N49: =+L49/D49 -> 10677.127 | O49: Abril - Mayo | P49: =+L49-K49 -> 1
A50: Feb 15 / Abr 15 | C50: 939 | D50: 1092 | E50: =+D50-C50 -> 153 | F50: =+G50/D50 -> 5276.8571 | G50: 5762328 | H50: =+I50/D50 -> 5473.9753 | I50: 5977581 | J50: 1 | K50: =+I50+G50 -> 11739909 | L50: =+K50+J50 -> 11739910 | M50: 45413 | N50: =+L50/D50 -> 10750.833 | O50: Junio - Julio | P50: =+L50-K50 -> 1
A51: Abr 16 / Jun 13 | C51: =D50 -> 1092 | D51: 1104 | E51: =+D51-C51 -> 12 | F51: =+G51/D51 -> 5313.3496 | G51: 5865938 | H51: =+I51/D51 -> 5514.202 | I51: 6087679 | J51: 3 | K51: =+I51+G51 -> 11953617 | L51: =+K51+J51 -> 11953620 | M51: 45505 | N51: =+L51/D51 -> 10827.554 | O51: Agosto - Septiembre | P51: =+L51-K51 -> 3
A52: Jun 14 / Ago 13 | C52: =D51 -> 1104 | D52: 1159 | E52: =+D52-C52 -> 55 | F52: =+G52/D52 -> 5442.1165 | G52: 6307413 | H52: =+I52/D52 -> 5647.5513 | I52: 6545512 | J52: 5 | K52: =+I52+G52 -> 12852925 | L52: =+K52+J52 -> 12852930 | M52: 45536 | N52: =+L52/D52 -> 11089.672 | O52: Octubre - Noviembre | P52: =+L52-K52 -> 5
A53: Ago 14 / Oct 11 | C53: =D52 -> 1159 | D53: 1203 | E53: =+D53-C53 -> 44 | F53: =+G53/D53 -> 5436.527 | G53: 6540142 | H53: =+I53/D53 -> 5638.9626 | I53: 6783672 | J53: 4 | K53: =+I53+G53 -> 13323814 | L53: =+K53+J53 -> 13323818 | M53: 45597 | N53: =+L53/D53 -> 11075.493 | O53: Diciembre - Enero | P53: =+L53-K53 -> 4
A54: Oct 12 / Dic 11 | C54: =D53 -> 1203 | D54: 1047 | E54: =+D54-C54 -> -156 | F54: =+G54/D54 -> 5476.0973 | G54: 5733473.8 | H54: =+I54/D54 -> 5679.9828 | I54: 5946942 | J54: 4 | K54: =+I54+G54 -> 11680416 | L54: =+K54+J54 -> 11680420 | M54: 45658 | N54: =+L54/D54 -> 11156.084 | O54: Febrero - Marzo | P54: =+L54-K54 -> 4
A55: Dic 12 / Feb 8 | C55: =D54 -> 1047 | D55: 977 | E55: =+D55-C55 -> -70 | F55: =+G55/D55 -> 5496.647 | G55: 5370224.1 | H55: =+I55/D55 -> 5701.8595 | I55: 5570716.8 | J55: 2 | K55: =+I55+G55 -> 10940941 | L55: =+K55+J55 -> 10940943 | M55: 45717 | N55: =+L55/D55 -> 11198.509 | O55: Abril - Mayo | P55: =+L55-K55 -> 2
A56: Feb 9 / Abril 10 | C56: =+D55 -> 977 | D56: 1080 | E56: =+D56-C56 -> 103 | F56: =+G56/D56 -> 5225.6963 | G56: 5643752 | H56: =+I56/D56 -> 5421.2778 | I56: 5854980 | J56: 2 | K56: =+I56+G56 -> 11498732 | L56: 11498730 | M56: 45778 | N56: =+L56/D56 -> 10646.972 | O56: Junio - Julio | P56: =+L56-K56 -> -2
A57: Abril 10 / Junio 07 | C57: 1080 | D57: 977 | E57: =+D57-C57 -> -103 | F57: =+G57/D57 -> 5679.8536 | G57: 5549217 | H57: =+I57/D57 -> 5888.6929 | I57: 5753253 | K57: =+I57+G57 -> 11302470 | L57: =+K57 -> 11302470 | M57: 45839 | N57: =+L57/D57 -> 11568.547 | O57: Agosto y Septiembre

Sheet Vr M3 DE GAS
BC2: 2023 | BK2: 2024 | BS2: 2025
A4: TORRE A | J4: TORRE A | S4: TORRE A | AB4: TORRE A | AK4: TORRE A | AT4: TORRE A | BC4: TORRE A | BL4: TORRE A | BT4: TORRE A
A5: AÑO 2017 | J5: AÑO 2018 | S5: AÑO 2019 | AB5: AÑO 2020 | AK5: AÑO 2021 | AT5: AÑO 2022 | BC5: AÑO 2023 | BL5: AÑO 2024 | BT5: AÑO 2025
A6: MES | B6: CONS. ANTE | C6: CONSU ACT | D6: DIF | E6: M3 | F6: TOTAL | J6: MES | K6: CONS. ANTE | L6: CONSU ACT | M6: DIF | N6: M3 | O6: TOTAL | S6: MES | T6: CONS. ANTE | U6: CONSU ACT | V6: DIF | W6: M3 | X6: TOTAL | AB6: MES | AC6: CONS. ANTE | AD6: CONSU ACT | AE6: DIF | AF6: M3 | AG6: TOTAL | AK6: MES | AL6: CONS. ANTE | AM6: CONSU ACT | AN6: DIF | AO6: M3 | AP6: TOTAL | AT6: MES | AU6: CONS. ANTE | AV6: CONSU ACT | AW6: DIF | AX6: M3 | AY6: TOTAL | BC6: MES | BD6: CONS. ANTE | BE6: CONSU ACT | BF6: DIF | BG6: M3 | BH6: TOTAL | BL6: MES | BM6: CONS. ANTE | BN6: CONSU ACT | BO6: DIF | BP6: M3 | BQ6: TOTAL | BT6: MES | BU6: CONS. ANTE | BV6: CONSU ACT | BW6: DIF | BX6: M3 | BY6: TOTAL
A7: Enero | B7: 1076 | C7: 1066 | D7: =+C7-B7 -> -10 | E7: =+F7/C7 -> 1935.4878 | F7: 2063230 | G7: =+F7/C7 -> 1935.4878 | J7: Enero | K7: 1047 | L7: 1071 | M7: =+L7-K7 -> 24 | N7: =+O7/L7 -> 2064.93 | O7: 2211540 | P7: =+O7/L7 -> 2064.93 | S7: Enero | T7: 946 | U7: 930 | V7: =+U7-T7 -> -16 | W7: =+X7/U7 -> 2094.6774 | X7: 1948050 | Y7: =+X7/U7 -> 2094.6774 | AB7: Enero | AC7: 863 | AD7: 792 | AE7: =+AD7-AC7 -> -71 | AF7: =+AG7/AD7 -> 1970.4672 | AG7: 1560610 | AH7: =+AG7/AD7 -> 1970.4672 | AK7: Enero | AL7: 769 | AM7: 927 | AN7: =+AM7-AL7 -> 158 | AO7: =+AP7/AM7 -> 2054.3474 | AP7: 1904380 | AQ7: =+AP7/AM7 -> 2054.3474 | AT7: Enero | AU7: =+AM18 -> 2064 | AV7: 2307 | AW7: =+AV7-AU7 -> 243 | AX7: =+AY7/AV7 -> 2384.6511 | AY7: 5501390 | AZ7: =+AY7/AV7 -> 2384.6511 | BC7: Enero | BD7: =+AV18 -> 2122 | BE7: 1912 | BF7: =+BE7-BD7 -> -210 | BG7: =+BH7/BE7 -> 3060.0262 | BH7: 5850770 | BI7: =+BH7/BE7 -> 3060.0262 | BL7: Enero | BM7: =+BE18 -> 1245 | BN7: 1729 | BO7: =+BN7-BM7 -> 484 | BP7: =+BQ7/BN7 -> 2673.7189 | BQ7: 4622860 | BR7: =+BQ7/BN7 -> 2673.7189 | BT7: Enero | BU7: =+BN18 -> 1687 | BV7: 2135 | BW7: =+BV7-BU7 -> 448 | BX7: =+BY7/BV7 -> 2978.1827 | BY7: 6358420 | BZ7: =+BY7/BV7 -> 2978.1827
A8: Febrero | B8: 1066 | C8: 1130 | D8: =+C8-B8 -> 64 | E8: =+F8/C8 -> 2107.8496 | F8: 2381870 | G8: =+F8/C8 -> 2107.8496 | J8: Febrero | K8: 1071 | L8: 1126 | M8: =+L8-K8 -> 55 | N8: =+O8/L8 -> 2073.1972 | O8: 2334420 | P8: =+O8/L8 -> 2073.1972 | S8: Febrero | T8: 930 | U8: 1042 | V8: =+U8-T8 -> 112 | W8: =+X8/U8 -> 2071.4012 | X8: 2158400 | Y8: =+X8/U8 -> 2071.4012 | AB8: Febrero | AC8: 792 | AD8: 871 | AE8: =+AD8-AC8 -> 79 | AF8: =+AG8/AD8 -> 2195.3387 | AG8: 1912140 | AH8: =+AG8/AD8 -> 2195.3387 | AK8: Febrero | AL8: 927 | AM8: 914 | AN8: =+AM8-AL8 -> -13 | AO8: =+AP8/AM8 -> 2076.674 | AP8: 1898080 | AQ8: =+AP8/AM8 -> 2076.674 | AT8: Febrero | AU8: =+AV7 -> 2307 | AV8: 1669 | AW8: =+AV8-AU8 -> -638 | AX8: =+AY8/AV8 -> 2493.2954 | AY8: 4161310 | AZ8: =+AY8/AV8 -> 2493.2954 | BC8: Febrero | BD8: =+BE7 -> 1912 | BE8: 2357 | BF8: =+BE8-BD8 -> 445 | BG8: =+BH8/BE8 -> 3076.7713 | BH8: 7251950 | BI8: =+BH8/BE8 -> 3076.7713 | BL8: Febrero | BM8: =+BN7 -> 1729 | BN8: 1738 | BO8: =+BN8-BM8 -> 9 | BP8: =+BQ8/BN8 -> 2876.0932 | BQ8: 4998650 | BR8: =+BQ8/BN8 -> 2876.0932 | BT8: Febrero | BU8: =+BV7 -> 2135 | BV8: 1968 | BW8: =+BV8-BU8 -> -167 | BX8: =+BY8/BV8 -> 4047.5203 | BY8: 7965520 | BZ8: =+BY8/BV8 -> 4047.5203
A9: Marzo | B9: 1130 | C9: 1085 | D9: =+C9-B9 -> -45 | E9: =+F9/C9 -> 2243.8894 | F9: 2434620 | G9: =+F9/C9 -> 2243.8894 | J9: Marzo | K9: 1126 | L9: 1418 | M9: =+L9-K9 -> 292 | N9: =+O9/L9 -> 1953.5755 | O9: 2770170 | P9: =+O9/L9 -> 1953.5755 | S9: Marzo | T9: 1042 | U9: 975 | V9: =+U9-T9 -> -67 | W9: =+X9/U9 -> 2155.159 | X9: 2101280 | Y9: =+X9/U9 -> 2155.159 | AB9: Marzo | AC9: 871 | AD9: 839 | AE9: =+AD9-AC9 -> -32 | AF9: =+AG9/AD9 -> 2292.0739 | AG9: 1923050 | AH9: =+AG9/AD9 -> 2292.0739 | AK9: Marzo | AL9: 914 | AM9: 905 | AN9: =+AM9-AL9 -> -9 | AO9: =+AP9/AM9 -> 2201.0718 | AP9: 1991970 | AQ9: =+AP9/AM9 -> 2201.0718 | AT9: Marzo | AU9: =+AV8 -> 1669 | AV9: 1668 | AW9: =+AV9-AU9 -> -1 | AX9: =+AY9/AV9 -> 2256.7686 | AY9: 3764290 | AZ9: =+AY9/AV9 -> 2256.7686 | BC9: Marzo | BD9: =+BE8 -> 2357 | BE9: 2290 | BF9: =+BE9-BD9 -> -67 | BG9: =+BH9/BE9 -> 3292.0655 | BH9: 7538830 | BI9: =+BH9/BE9 -> 3292.0655 | BL9: Marzo | BM9: =+BN8 -> 1738 | BN9: 1533 | BO9: =+BN9-BM9 -> -205 | BP9: =+BQ9/BN9 -> 3056.4318 | BQ9: 4685510 | BR9: =+BQ9/BN9 -> 3056.4318 | BT9: Marzo | BU9: =+BV8 -> 1968 | BV9: 1735 | BW9: =+BV9-BU9 -> -233 | BX9: =+BY9/BV9 -> 3446.9395 | BY9: 5980440 | BZ9: =+BY9/BV9 -> 3446.9395
A10: Abril | B10: 1085 | C10: 1087 | D10: =+C10-B10 -> 2 | E10: =+F10/C10 -> 1961.1684 | F10: 2131790 | G10: =+F10/C10 -> 1961.1684 | J10: Abril | K10: 1418 | L10: 2471 | M10: =+L10-K10 -> 1053 | N10: =+O10/L10 -> 2016.9931 | O10: 4983990 | P10: =+O10/L10 -> 2016.9931 | S10: Abril | T10: 975 | U10: 993 | V10: =+U10-T10 -> 18 | W10: =+X10/U10 -> 1994.3303 | X10: 1980370 | Y10: =+X10/U10 -> 1994.3303 | AB10: Abril | AC10: 839 | AD10: 919 | AE10: =+AD10-AC10 -> 80 | AF10: =+AG10/AD10 -> 2294.7552 | AG10: 2108880 | AH10: =+AG10/AD10 -> 2294.7552 | AK10: Abril | AL10: 905 | AM10: 918 | AN10: =+AM10-AL10 -> 13 | AO10: =+AP10/AM10 -> 2242.6688 | AP10: 2058770 | AQ10: =+AP10/AM10 -> 2242.6688 | AT10: Abril | AU10: =+AV9 -> 1668 | AV10: 1897 | AW10: =+AV10-AU10 -> 229 | AX10: =+AY10/AV10 -> 2610.2952 | AY10: 4951730 | AZ10: =+AY10/AV10 -> 2610.2952 | BC10: Abril | BD10: =+BE9 -> 2290 | BE10: 2633 | BF10: =+BE10-BD10 -> 343 | BG10: =+BH10/BE10 -> 3082.4763 | BH10: 8116160 | BI10: =+BH10/BE10 -> 3082.4763 | BL10: Abril | BM10: =+BN9 -> 1533 | BN10: 1788 | BO10: =+BN10-BM10 -> 255 | BP10: =+BQ10/BN10 -> 2755.151 | BQ10: 4926210 | BR10: =+BQ10/BN10 -> 2755.151 | BT10: Abril | BU10: =+BV9 -> 1735 | BV10: 2077 | BW10: =+BV10-BU10 -> 342 | BX10: =+BY10/BV10 -> 3537.4386 | BY10: 7347260 | BZ10: =+BY10/BV10 -> 3537.4386
A11: Mayo | B11: 1087 | C11: 1163 | D11: =+C11-B11 -> 76 | E11: =+F11/C11 -> 2008.994 | F11: 2336460 | G11: =+F11/C11 -> 2008.994 | J11: Mayo | K11: 2471 | L11: 1695 | M11: =+L11-K11 -> -776 | N11: =+O11/L11 -> 2111.9882 | O11: 3579820 | P11: =+O11/L11 -> 2111.9882 | S11: Mayo | T11: 993 | U11: 1084 | V11: =+U11-T11 -> 91 | W11: =+X11/U11 -> 2076.3192 | X11: 2250730 | Y11: =+X11/U11 -> 2076.3192 | AB11: Mayo | AC11: 919 | AD11: 814 | AE11: =+AD11-AC11 -> -105 | AF11: =+AG11/AD11 -> 2417.3096 | AG11: 1967690 | AH11: =+AG11/AD11 -> 2417.3096 | AK11: Mayo | AL11: 918 | AM11: 1998 | AN11: =+AM11-AL11 -> 1080 | AO11: =+AP11/AM11 -> 2214.2543 | AP11: 4424080 | AQ11: =+AP11/AM11 -> 2214.2543 | AT11: Mayo | AU11: =+AV10 -> 1897 | AV11: 1784 | AW11: =+AV11-AU11 -> -113 | AX11: =+AY11/AV11 -> 2526.463 | AY11: 4507210 | AZ11: =+AY11/AV11 -> 2526.463 | BC11: Mayo | BD11: =+BE10 -> 2633 | BE11: 2143 | BF11: =+BE11-BD11 -> -490 | BG11: =+BH11/BE11 -> 2716.8969 | BH11: 5822310 | BI11: =+BH11/BE11 -> 2716.8969 | BL11: Mayo | BM11: =+BN10 -> 1788 | BN11: 1995 | BO11: =+BN11-BM11 -> 207 | BP11: =+BQ11/BN11 -> 2665.3684 | BQ11: 5317410 | BR11: =+BQ11/BN11 -> 2665.3684 | BT11: Mayo | BU11: =+BV10 -> 2077 | BV11: 1799 | BW11: =+BV11-BU11 -> -278 | BX11: =+BY11/BV11 -> 3476.4091 | BY11: 6254060 | BZ11: =+BY11/BV11 -> 3476.4091
A12: Junio | B12: 1163 | C12: 1114 | D12: =+C12-B12 -> -49 | E12: =+F12/C12 -> 2053.1329 | F12: 2287190 | G12: =+F12/C12 -> 2053.1329 | J12: Junio | K12: 1695 | L12: 1471 | M12: =+L12-K12 -> -224 | N12: =+O12/L12 -> 1956.295 | O12: 2877710 | P12: =+O12/L12 -> 1956.295 | S12: Junio | T12: 1084 | U12: 1175 | V12: =+U12-T12 -> 91 | W12: =+X12/U12 -> 2085.9149 | X12: 2450950 | Y12: =+X12/U12 -> 2085.9149 | AB12: Junio | AC12: 814 | AD12: 812 | AE12: =+AD12-AC12 -> -2 | AF12: =+AG12/AD12 -> 2331.5025 | AG12: 1893180 | AH12: =+AG12/AD12 -> 2331.5025 | AK12: Junio | AL12: 1998 | AM12: 1930 | AN12: =+AM12-AL12 -> -68 | AO12: =+AP12/AM12 -> 2224.5803 | AP12: 4293440 | AQ12: =+AP12/AM12 -> 2224.5803 | AT12: Junio | AU12: =+AV11 -> 1784 | AV12: 1733 | AW12: =+AV12-AU12 -> -51 | AX12: =+AY12/AV12 -> 2694.0969 | AY12: 4668870 | AZ12: =+AY12/AV12 -> 2694.0969 | BC12: Junio | BD12: =+BE11 -> 2143 | BE12: 2057 | BF12: =+BE12-BD12 -> -86 | BG12: =+BH12/BE12 -> 3010.2285 | BH12: 6192040 | BI12: =+BH12/BE12 -> 3010.2285 | BL12: Junio | BM12: =+BN11 -> 1995 | BN12: 1855 | BO12: =+BN12-BM12 -> -140 | BP12: =+BQ12/BN12 -> 2687.4232 | BQ12: 4985170 | BR12: =+BQ12/BN12 -> 2687.4232 | BT12: Junio | BU12: =+BV11 -> 1799 | BV12: 1963 | BW12: =+BV12-BU12 -> 164 | BX12: =+BY12/BV12 -> 3459.19 | BY12: 6790390 | BZ12: =+BY12/BV12 -> 3459.19
A13: Julio | B13: 1114 | C13: 1128 | D13: =+C13-B13 -> 14 | E13: =+F13/C13 -> 1965.7358 | F13: 2217350 | G13: =+F13/C13 -> 1965.7358 | J13: Julio | K13: 1471 | L13: 561 | M13: =+L13-K13 -> -910 | N13: =+O13/L13 -> 1889.5722 | O13: 1060050 | P13: =+O13/L13 -> 1889.5722 | S13: Julio | T13: 1175 | U13: 1003 | V13: =+U13-T13 -> -172 | W13: =+X13/U13 -> 2127.7966 | X13: 2134180 | Y13: =+X13/U13 -> 2127.7966 | AB13: Julio | AC13: 812 | AD13: 899 | AE13: =+AD13-AC13 -> 87 | AF13: =+AG13/AD13 -> 2250.7786 | AG13: 2023450 | AH13: =+AG13/AD13 -> 2250.7786 | AK13: Julio | AL13: 1930 | AM13: 1935 | AN13: =+AM13-AL13 -> 5 | AO13: =+AP13/AM13 -> 2285.9948 | AP13: 4423400 | AQ13: =+AP13/AM13 -> 2285.9948 | AT13: Julio | AU13: =+AV12 -> 1733 | AV13: 2354 | AW13: =+AV13-AU13 -> 621 | AX13: =+AY13/AV13 -> 2541.4826 | AY13: 5982650 | AZ13: =+AY13/AV13 -> 2541.4826 | BC13: Julio | BD13: =+BE12 -> 2057 | BE13: 2288 | BF13: =+BE13-BD13 -> 231 | BG13: =+BH13/BE13 -> 2902.854 | BH13: 6641730 | BI13: =+BH13/BE13 -> 2902.854 | BL13: Julio | BM13: =+BN12 -> 1855 | BN13: 2129 | BO13: =+BN13-BM13 -> 274 | BP13: =+BQ13/BN13 -> 2710.8736 | BQ13: 5771450 | BR13: =+BQ13/BN13 -> 2710.8736 | BT13: Julio | BU13: =+BV12 -> 1963 | BV13: 1757 | BW13: =+BV13-BU13 -> -206 | BX13: =+BY13/BV13 -> 3254.8947 | BY13: 5718850 | BZ13: =+BY13/BV13 -> 3254.8947
A14: Agosto | B14: 1128 | C14: 1100 | D14: =+C14-B14 -> -28 | E14: =+F14/C14 -> 2188.2273 | F14: 2407050 | G14: =+F14/C14 -> 2188.2273 | J14: Agosto | K14: 561 | L14: 1061 | M14: =+L14-K14 -> 500 | N14: =+O14/L14 -> 1914.0245 | O14: 2030780 | P14: =+O14/L14 -> 1914.0245 | S14: Agosto | T14: 1003 | U14: 1215 | V14: =+U14-T14 -> 212 | W14: =+X14/U14 -> 2101.9342 | X14: 2553850 | Y14: =+X14/U14 -> 2101.9342 | AB14: Agosto | AC14: 899 | AD14: 1124 | AE14: =+AD14-AC14 -> 225 | AF14: =+AG14/AD14 -> 2226.3612 | AG14: 2502430 | AH14: =+AG14/AD14 -> 2226.3612 | AK14: Agosto | AL14: 1935 | AM14: 2214 | AN14: =+AM14-AL14 -> 279 | AO14: =+AP14/AM14 -> 2325.3162 | AP14: 5148250 | AQ14: =+AP14/AM14 -> 2325.3162 | AT14: Agosto | AU14: =+AV13 -> 2354 | AV14: 2216 | AW14: =+AV14-AU14 -> -138 | AX14: =+AY14/AV14 -> 2649.7338 | AY14: 5871810 | AZ14: =+AY14/AV14 -> 2649.7338 | BC14: Agosto | BD14: =+BE13 -> 2288 | BE14: 2125 | BF14: =+BE14-BD14 -> -163 | BG14: =+BH14/BE14 -> 2964.4047 | BH14: 6299360 | BI14: =+BH14/BE14 -> 2964.4047 | BL14: Agosto | BM14: =+BN13 -> 2129 | BN14: 2448 | BO14: =+BN14-BM14 -> 319 | BP14: =+BQ14/BN14 -> 2918.2394 | BQ14: 7143850 | BR14: =+BQ14/BN14 -> 2918.2394 | BT14: Agosto | BU14: =+BV13 -> 1757 | BV14: 2343 | BW14: =+BV14-BU14 -> 586 | BX14: =+BY14/BV14 -> 3323.6876 | BY14: 7787400 | BZ14: =+BY14/BV14 -> 3323.6876
A15: Septiembre | B15: 1100 | C15: 1030 | D15: =+C15-B15 -> -70 | E15: =+F15/C15 -> 2139.5825 | F15: 2203770 | G15: =+F15/C15 -> 2139.5825 | J15: Septiembre | K15: 1061 | L15: 1091 | M15: =+L15-K15 -> 30 | N15: =+O15/L15 -> 1858.7901 | O15: 2027940 | P15: =+O15/L15 -> 1858.7901 | S15: Septiembre | T15: 1215 | U15: 1056 | V15: =+U15-T15 -> -159 | W15: =+X15/U15 -> 1957.7841 | X15: 2067420 | Y15: =+X15/U15 -> 1957.7841 | AB15: Septiembre | AC15: 1124 | AD15: 903 | AE15: =+AD15-AC15 -> -221 | AF15: =+AG15/AD15 -> 2139.856 | AG15: 1932290 | AH15: =+AG15/AD15 -> 2139.856 | AK15: Septiembre | AL15: 2214 | AM15: 1993 | AN15: =+AM15-AL15 -> -221 | AO15: =+AP15/AM15 -> 2241.716 | AP15: 4467740 | AQ15: =+AP15/AM15 -> 2241.716 | AT15: Septiembre | AU15: =+AV14 -> 2216 | AV15: 2573 | AW15: =+AV15-AU15 -> 357 | AX15: =+AY15/AV15 -> 2835.1846 | AY15: 7294930 | AZ15: =+AY15/AV15 -> 2835.1846 | BC15: Septiembre | BD15: =+BE14 -> 2125 | BE15: 2018 | BF15: =+BE15-BD15 -> -107 | BG15: =+BH15/BE15 -> 2809.1873 | BH15: 5668940 | BI15: =+BH15/BE15 -> 2809.1873 | BL15: Septiembre | BM15: =+BN14 -> 2448 | BN15: 2149 | BO15: =+BN15-BM15 -> -299 | BP15: =+BQ15/BN15 -> 2770.8469 | BQ15: 5954550 | BR15: =+BQ15/BN15 -> 2770.8469 | BT15: Septiembre | BU15: =+BV14 -> 2343 | BW15: =+BV15-BU15 -> -2343 | BX15: =+BY15/BV15 -> #DIV/0! | BZ15: =+BY15/BV15 -> #DIV/0!
A16: Octubre | B16: 1030 | C16: 1132 | D16: =+C16-B16 -> 102 | E16: =+F16/C16 -> 2040.3357 | F16: 2309660 | G16: =+F16/C16 -> 2040.3357 | J16: Octubre | K16: 1091 | L16: 1018 | M16: =+L16-K16 -> -73 | N16: =+O16/L16 -> 2004.6562 | O16: 2040740 | P16: =+O16/L16 -> 2004.6562 | S16: Octubre | T16: 1056 | U16: 1010 | V16: =+U16-T16 -> -46 | W16: =+X16/U16 -> 2063.8119 | X16: 2084450 | Y16: =+X16/U16 -> 2063.8119 | AB16: Octubre | AC16: 903 | AD16: 1037 | AE16: =+AD16-AC16 -> 134 | AF16: =+AG16/AD16 -> 2181.3115 | AG16: 2262020 | AH16: =+AG16/AD16 -> 2181.3115 | AK16: Octubre | AL16: 1993 | AM16: 2340 | AN16: =+AM16-AL16 -> 347 | AO16: =+AP16/AM16 -> 2151.9786 | AP16: 5035630 | AQ16: =+AP16/AM16 -> 2151.9786 | AT16: Octubre | AU16: =+AV15 -> 2573 | AV16: 2381 | AW16: =+AV16-AU16 -> -192 | AX16: =+AY16/AV16 -> 2800.168 | AY16: 6667200 | AZ16: =+AY16/AV16 -> 2800.168 | BC16: Octubre | BD16: =+BE15 -> 2018 | BE16: 1971 | BF16: =+BE16-BD16 -> -47 | BG16: =+BH16/BE16 -> 2842.0751 | BH16: 5601730 | BI16: =+BH16/BE16 -> 2842.0751 | BL16: Octubre | BM16: =+BN15 -> 2149 | BN16: 1937 | BO16: =+BN16-BM16 -> -212 | BP16: =+BQ16/BN16 -> 2702.6278 | BQ16: 5234990 | BR16: =+BQ16/BN16 -> 2702.6278 | BT16: Octubre | BU16: =+BV15 -> 0 | BW16: =+BV16-BU16 -> 0 | BX16: =+BY16/BV16 -> #DIV/0! | BZ16: =+BY16/BV16 -> #DIV/0!
A17: Noviembre | B17: 1132 | C17: 1243 | D17: =+C17-B17 -> 111 | E17: =+F17/C17 -> 2055.535 | F17: 2555030 | G17: =+F17/C17 -> 2055.535 | J17: Noviembre | K17: 1018 | L17: 1088 | M17: =+L17-K17 -> 70 | N17: =+O17/L17 -> 2021.0294 | O17: 2198880 | P17: =+O17/L17 -> 2021.0294 | S17: Noviembre | T17: 1010 | U17: 1140 | V17: =+U17-T17 -> 130 | W17: =+X17/U17 -> 2160.9825 | X17: 2463520 | Y17: =+X17/U17 -> 2160.9825 | AB17: Noviembre | AC17: 1037 | AD17: 1089 | AE17: =+AD17-AC17 -> 52 | AF17: =+AG17/AD17 -> 2208.3563 | AG17: 2404900 | AH17: =+AG17/AD17 -> 2208.3563 | AK17: Noviembre | AL17: 2340 | AM17: 2282 | AN17: =+AM17-AL17 -> -58 | AO17: =+AP17/AM17 -> 2287.0947 | AP17: 5219150 | AQ17: =+AP17/AM17 -> 2287.0947 | AT17: Noviembre | AU17: =+AV16 -> 2381 | AV17: 2239 | AW17: =+AV17-AU17 -> -142 | AX17: =+AY17/AV17 -> 2891.7374 | AY17: 6474600 | AZ17: =+AY17/AV17 -> 2891.7374 | BC17: Noviembre | BD17: =+BE16 -> 1971 | BE17: 881 | BF17: =+BE17-BD17 -> -1090 | BG17: =+BH17/BE17 -> 2796.9807 | BH17: 2464140 | BI17: =+BH17/BE17 -> 2796.9807 | BL17: Noviembre | BM17: =+BN16 -> 1937 | BN17: 2064 | BO17: =+BN17-BM17 -> 127 | BP17: =+BQ17/BN17 -> 2837.311 | BQ17: 5856210 | BR17: =+BQ17/BN17 -> 2837.311 | BT17: Noviembre | BU17: =+BV16 -> 0 | BW17: =+BV17-BU17 -> 0 | BX17: =+BY17/BV17 -> #DIV/0! | BZ17: =+BY17/BV17 -> #DIV/0!
A18: Diciembre | B18: 1243 | C18: 1047 | D18: =+C18-B18 -> -196 | E18: =+F18/C18 -> 2035.1098 | F18: 2130760 | G18: =+F18/C18 -> 2035.1098 | J18: Diciembre | K18: 1088 | L18: 946 | M18: =+L18-K18 -> -142 | N18: =+O18/L18 -> 2072.0719 | O18: 1960180 | P18: =+O18/L18 -> 2072.0719 | S18: Diciembre | T18: 1140 | U18: 863 | V18: =+U18-T18 -> -277 | W18: =+X18/U18 -> 2081.518 | X18: 1796350 | Y18: =+X18/U18 -> 2081.518 | AB18: Diciembre | AC18: 1089 | AD18: 769 | AE18: =+AD18-AC18 -> -320 | AF18: =+AG18/AD18 -> 2167.7503 | AG18: 1667000 | AH18: =+AG18/AD18 -> 2167.7503 | AK18: Diciembre | AL18: 2282 | AM18: 2064 | AN18: =+AM18-AL18 -> -218 | AO18: =+AP18/AM18 -> 2276.1725 | AP18: 4698020 | AQ18: =+AP18/AM18 -> 2276.1725 | AT18: Diciembre | AU18: =+AV17 -> 2239 | AV18: 2122 | AW18: =+AV18-AU18 -> -117 | AX18: =+AY18/AV18 -> 3083.1433 | AY18: 6542430 | AZ18: =+AY18/AV18 -> 3083.1433 | BC18: Diciembre | BD18: =+BE17 -> 881 | BE18: 1245 | BF18: =+BE18-BD18 -> 364 | BG18: =+BH18/BE18 -> 2824.8353 | BH18: 3516920 | BI18: =+BH18/BE18 -> 2824.8353 | BL18: Diciembre | BM18: =+BN17 -> 2064 | BN18: 1687 | BO18: =+BN18-BM18 -> -377 | BP18: =+BQ18/BN18 -> 2837.8364 | BQ18: 4787430 | BR18: =+BQ18/BN18 -> 2837.8364 | BT18: Diciembre | BU18: =+BV17 -> 0 | BW18: =+BV18-BU18 -> 0 | BX18: =+BY18/BV18 -> #DIV/0! | BZ18: =+BY18/BV18 -> #DIV/0!
A22: TORRE B | J22: TORRE B | S22: TORRE B | AB22: TORRE B | AK22: TORRE B | AT22: TORRE B | BC22: TORRE B | BL22: TORRE B | BT22: TORRE B
A23: AÑO 2017 | J23: AÑO 2018 | S23: AÑO 2019 | AB23: AÑO 2020 | AK23: AÑO 2021 | AT23: AÑO 2022 | BC23: AÑO 2023 | BL23: AÑO 2024 | BT23: AÑO 2025
A24: MES | B24: CONS. ANTE | C24: CONSU ACT | D24: DIF | E24: M3 | F24: TOTAL | J24: MES | K24: CONS. ANTE | L24: CONSU ACT | M24: DIF | N24: M3 | O24: TOTAL | S24: MES | T24: CONS. ANTE | U24: CONSU ACT | V24: DIF | W24: M3 | X24: TOTAL | AB24: MES | AC24: CONS. ANTE | AD24: CONSU ACT | AE24: DIF | AF24: M3 | AG24: TOTAL | AK24: MES | AL24: CONS. ANTE | AM24: CONSU ACT | AN24: DIF | AO24: M3 | AP24: TOTAL | AT24: MES | AU24: CONS. ANTE | AV24: CONSU ACT | AW24: DIF | AX24: M3 | AY24: TOTAL | BC24: MES | BD24: CONS. ANTE | BE24: CONSU ACT | BF24: DIF | BG24: M3 | BH24: TOTAL | BL24: MES | BM24: CONS. ANTE | BN24: CONSU ACT | BO24: DIF | BP24: M3 | BQ24: TOTAL | BT24: MES | BU24: CONS. ANTE | BV24: CONSU ACT | BW24: DIF | BX24: M3 | BY24: TOTAL
A25: Enero | B25: 1125 | C25: 708 | D25: =+C25-B25 -> -417 | E25: =+F25/C25 -> 2155.0141 | F25: 1525750 | G25: =+F25/C25 -> 2155.0141 | J25: Enero | K25: 821 | L25: 812 | M25: =+L25-K25 -> -9 | N25: =+O25/L25 -> 2257.4015 | O25: 1833010 | P25: =+O25/L25 -> 2257.4015 | S25: Enero | T25: 933 | U25: 824 | V25: =+U25-T25 -> -109 | W25: =+X25/U25 -> 2329.9029 | X25: 1919840 | Y25: =+X25/U25 -> 2329.9029 | AB25: Enero | AC25: 960 | AD25: 837 | AE25: =+AD25-AC25 -> -123 | AF25: =+AG25/AD25 -> 2190.5257 | AG25: 1833470 | AH25: =+AG25/AD25 -> 2190.5257 | AK25: Enero | AL25: 1015 | AM25: 1171 | AN25: =+AM25-AL25 -> 156 | AO25: =+AP25/AM25 -> 2053.5013 | AP25: 2404650 | AQ25: =+AP25/AM25 -> 2053.5013 | AT25: Enero | AU25: =+AM36 -> 1213 | AV25: 1079 | AW25: =+AV25-AU25 -> -134 | AX25: =+AY25/AV25 -> 2386.5709 | AY25: 2575110 | AZ25: =+AY25/AV25 -> 2386.5709 | BC25: Enero | BD25: =+AV36 -> 1383 | BE25: 1365 | BF25: =+BE25-BD25 -> -18 | BG25: =+BH25/BE25 -> 3060.9304 | BH25: 4178170 | BI25: =+BH25/BE25 -> 3060.9304 | BL25: Enero | BM25: =+BE36 -> 1037 | BN25: 1077 | BO25: =+BN25-BM25 -> 40 | BP25: =+BQ25/BN25 -> 2675.3482 | BQ25: 2881350 | BR25: =+BQ25/BN25 -> 2675.3482 | BT25: Enero | BU25: =+BN36 -> 848 | BV25: 838 | BW25: =+BV25-BU25 -> -10 | BX25: =+BY25/BV25 -> 2981.6826 | BY25: 2498650 | BZ25: =+BY25/BV25 -> 2981.6826
A26: Febrero | B26: 708 | C26: 953 | D26: =+C26-B26 -> 245 | E26: =+F26/C26 -> 2345.7293 | F26: 2235480 | G26: =+F26/C26 -> 2345.7293 | J26: Febrero | K26: 812 | L26: 863 | M26: =+L26-K26 -> 51 | N26: =+O26/L26 -> 2309.3163 | O26: 1992940 | P26: =+O26/L26 -> 2309.3163 | S26: Febrero | T26: 824 | U26: 939 | V26: =+U26-T26 -> 115 | W26: =+X26/U26 -> 2304.6539 | X26: 2164070 | Y26: =+X26/U26 -> 2304.6539 | AB26: Febrero | AC26: 837 | AD26: 914 | AE26: =+AD26-AC26 -> 77 | AF26: =+AG26/AD26 -> 2442.8884 | AG26: 2232800 | AH26: =+AG26/AD26 -> 2442.8884 | AK26: Febrero | AL26: 1171 | AM26: 1181 | AN26: =+AM26-AL26 -> 10 | AO26: =+AP26/AM26 -> 2075.7409 | AP26: 2451450 | AQ26: =+AP26/AM26 -> 2075.7409 | AT26: Febrero | AU26: =+AV25 -> 1079 | AV26: 1259 | AW26: =+AV26-AU26 -> 180 | AX26: =+AY26/AV26 -> 2494.0588 | AY26: 3140020 | AZ26: =+AY26/AV26 -> 2494.0588 | BC26: Febrero | BD26: =+BE25 -> 1365 | BE26: 1282 | BF26: =+BE26-BD26 -> -83 | BG26: =+BH26/BE26 -> 3078.3229 | BH26: 3946410 | BI26: =+BH26/BE26 -> 3078.3229 | BL26: Febrero | BM26: =+BN25 -> 1077 | BN26: 1327 | BO26: =+BN26-BM26 -> 250 | BP26: =+BQ26/BN26 -> 2876.9254 | BQ26: 3817680 | BR26: =+BQ26/BN26 -> 2876.9254 | BT26: Febrero | BU26: =+BV25 -> 838 | BV26: 908 | BW26: =+BV26-BU26 -> 70 | BX26: =+BY26/BV26 -> 4050.3965 | BY26: 3677760 | BZ26: =+BY26/BV26 -> 4050.3965
